Workbook

Sheet README
A1: Enterprise project portfolio dataset
A2: Source workbook for the portfolio web app. Twelve related tables, one per sheet, all joined on stable IDs.
A4: How to read it
A5: Blue text | B5: Inputs. Safe to edit; the app and every formula update from them.
A6: Green text | B6: Lookups pulled from another table by ID (INDEX/MATCH).
A7: Black text | B7: Calculated. Do not overwrite; change the inputs or Settings instead.
A8: Yellow fill | B8: Key assumptions in Settings (RAG thresholds, contingency, as-of date).
A10: Tables
A11: tbl_Projects | B11: One row per project. Contract, schedule, earned value (EV, PV, CPI, SPI, EAC), margin, cash and RAG status.
A12: tbl_Resources | B12: People, rates, capacity and live utilization.
A13: tbl_Allocations | B13: Who is assigned to which project, when, and at what %. Planned vs actual hours.
A14: tbl_Estimates | B14: Effort estimates by phase. v1 Baseline for all; v2 Re-forecast where a project was re-planned.
A15: tbl_Budget | B15: Approved budget by project and cost category, with burn against actuals.
A16: tbl_Actuals | B16: Monthly cost ledger: timesheets, supplier invoices, expenses.
A17: tbl_Milestones | B17: Five milestones per project; Fixed Price milestones trigger billing.
A18: tbl_Invoices | B18: Invoices raised, payment status and aging.
A19: tbl_RAID | B19: Risks, issues, assumptions and dependencies with scoring and exposure.
A20: tbl_ChangeRequests | B20: Scope and budget changes. Only Approved CRs flow into project value and budget.
A21: tbl_Snapshots | B21: Month-end history (Jan-Aug 2026) for trend charts. Append-only static values.
A22: tbl_Clients | B22: Client accounts and payment terms.
... A24: tbl_Settings | B24: Thresholds and the AsOfDate. Named ranges make formulas readable (e.g. RAG_CostRed).
A26: Relationships
A27: ProjectID | B27: Projects -> Allocations, Estimates, Budget, Actuals, Milestones, Invoices, RAID, ChangeRequests, Snapshots
A28: EmployeeID | B28: Resources -> Allocations, Actuals, Projects.ProjectManagerID, RAID.OwnerID, ChangeRequests.RaisedByID
A29: ClientID | B29: Clients -> Projects (Invoices reach Clients through Projects)
A30: MilestoneID | B30: Milestones -> Invoices (Fixed Price billing)
A32: Built-in test scenarios
A33: Healthy | B33: P-1001, P-1004, P-1007, P-1009, P-1011, P-1012, P-1014, P-1016 - on budget and on time.
A34: Cost overrun | B34: P-1002 (severe - margin now Red), P-1013 (mild) - burning budget faster than progress.
A35: Schedule slip | B35: P-1003 (late), P-1010 (past baseline end, still open).
A36: Everything at risk | B36: P-1005, P-1017 (P-1017 forecasts a negative margin).
A37: Margin squeeze | B37: P-1006 (margin Amber). P-1015 has a CR that costs more than it earns but is still Green - a leading indicator to watch in trends.
A38: Other states | B38: P-1018 to P-1020 Completed (P-1019 finished 6 weeks late and over budget), P-1021 On Hold, P-1022 to P-1024 Planned.
A39: People | B39: A handful of people are overallocated (>100%) and some sit on the bench, to exercise the resource heatmap.
A40: Cash | B40: Aurora Retail and Bluewater Municipal have disputed invoices and Harbourview pays late, so every aging bucket is populated.
A42: For the app
A43: Read tables by name | B43: Read each tbl_* by name, not by sheet or cell range, so inserting rows or moving columns never breaks the sync.
A44: AsOfDate | B44: Fixed at 2026-09-11 so results are reproducible. Set it to =TODAY() for live use.
A45: Formula results | B45: Calculated values (EAC, RAG, HealthScore) are computed in the workbook, so the app can display them directly or recompute them itself.
A46: Data volume | B46: 24 projects, 63 people, ~1,400 ledger lines, ~100 invoices, ~70 RAID items.

Sheet Summary
A1: Portfolio summary
A2: ="As of "&TEXT(AsOfDate,"d mmm yyyy")&" | actuals to "&TEXT(ActualsCutoff,"d mmm yyyy") -> As of 11 Sep 2026 | actuals to 31 Aug 2026
A3: Every value is a live formula. DrillTarget describes the filter the app should open when the number is tapped.
A5: KPI | B5: Value | C5: DrillTarget
A6: Active projects | B6: =COUNTIF(Projects!$J$2:$J$500,"Active") -> 17 | C6: Projects | Status = Active
A7: Active contract value | B7: =SUMIFS(Projects!$W$2:$W$500,Projects!$J$2:$J$500,"Active") -> 16200000 | C7: Projects | Status = Active | sort CurrentContractValue desc
A8: Active budget (BAC) | B8: =SUMIFS(Projects!$Z$2:$Z$500,Projects!$J$2:$J$500,"Active") -> 10875900 | C8: Projects | Status = Active
A9: Actual cost to date (active) | B9: =SUMIFS(Projects!$AB$2:$AB$500,Projects!$J$2:$J$500,"Active") -> 7204719.1 | C9: Actuals | Project.Status = Active
A10: Estimate at completion (active) | B10: =SUMIFS(Projects!$AH$2:$AH$500,Projects!$J$2:$J$500,"Active") -> 11145600 | C10: Projects | Status = Active | sort VAC asc
A11: Forecast margin % (active) | B11: =IFERROR((B7-B10)/B7,0) -> 0.31200003 | C11: Projects | Status = Active | sort ForecastMarginPct asc
A12: Target margin % (weighted) | B12: =IFERROR(SUMPRODUCT((Projects!$J$2:$J$500="Active")*Projects!$W$2:$W$500*Projects!$S$2:$S$500)/B7,0) -> 0.36280247 | C12: Projects | Status = Active
A13: Red projects | B13: =COUNTIFS(Projects!$J$2:$J$500,"Active",Projects!$BC$2:$BC$500,"Red") -> 4 | C13: Projects | Status = Active AND OverallRAG = Red
A14: Amber projects | B14: =COUNTIFS(Projects!$J$2:$J$500,"Active",Projects!$BC$2:$BC$500,"Amber") -> 4 | C14: Projects | Status = Active AND OverallRAG = Amber
A15: Green projects | B15: =COUNTIFS(Projects!$J$2:$J$500,"Active",Projects!$BC$2:$BC$500,"Green") -> 9 | C15: Projects | Status = Active AND OverallRAG = Green
A16: Average health score | B16: =IFERROR(AVERAGEIFS(Projects!$BD$2:$BD$500,Projects!$J$2:$J$500,"Active"),0) -> 74.117647 | C16: Projects | Status = Active | sort HealthScore asc
A17: Average schedule slip (days) | B17: =IFERROR(AVERAGEIFS(Projects!$AO$2:$AO$500,Projects!$J$2:$J$500,"Active"),0) -> 17.941176 | C17: Projects | Status = Active | sort ScheduleSlipDays desc
A18: Overallocated people | B18: =COUNTIF(Resources!$R$2:$R$500,"Overallocated") -> 6 | C18: Resources | UtilizationStatus = Overallocated
A19: Under-utilized people | B19: =COUNTIF(Resources!$R$2:$R$500,"Under-utilized") -> 23 | C19: Resources | UtilizationStatus = Under-utilized
A20: Bench capacity (hrs/week) | B20: =SUM(Resources!$Q$2:$Q$500) -> 720 | C20: Resources | AvailableHrsPerWeek > 0
A21: Outstanding receivables | B21: =SUMIFS(Invoices!$F$2:$F$2000,Invoices!$K$2:$K$2000,"Outstanding")+SUMIFS(Invoices!$F$2:$F$2000,Invoices!$K$2:$K$2000,"Overdue") -> 1937308.9 | C21: Invoices | Status <> Paid
A22: Overdue receivables | B22: =SUMIFS(Invoices!$F$2:$F$2000,Invoices!$K$2:$K$2000,"Overdue") -> 789503.99 | C22: Invoices | Status = Overdue | sort DaysOverdue desc
A23: Unbilled WIP (active) | B23: =SUMIFS(Projects!$AS$2:$AS$500,Projects!$J$2:$J$500,"Active") -> 2117514.4 | C23: Projects | Status = Active | sort UnbilledWIP desc
A24: Open critical risks | B24: =COUNTIFS(RAID!$P$2:$P$2000,"Critical",RAID!$J$2:$J$2000,"<>Closed") -> 6 | C24: RAID | Severity = Critical AND Status <> Closed
A25: Open risk exposure (weighted) | B25: =SUMIFS(RAID!$Q$2:$Q$2000,RAID!$J$2:$J$2000,"Open")+SUMIFS(RAID!$Q$2:$Q$2000,RAID!$J$2:$J$2000,"Mitigating") -> 1632400 | C25: RAID | Status <> Closed | sort ExpectedExposure desc
A26: Pending change requests | B26: =COUNTIF(ChangeRequests!$P$2:$P$1000,"Yes") -> 8 | C26: ChangeRequests | IsPending = Yes
A27: Pending CR cost impact | B27: =SUMIFS(ChangeRequests!$I$2:$I$1000,ChangeRequests!$P$2:$P$1000,"Yes") -> 402000 | C27: ChangeRequests | IsPending = Yes
A28: Overdue milestones | B28: =COUNTIF(Milestones!$L$2:$L$2000,"Overdue") -> 4 | C28: Milestones | Status = Overdue
A30: By portfolio (active projects)
A31: Portfolio | B31: ActiveProjects | C31: ContractValue | D31: Budget | E31: ActualCost | F31: EAC | G31: ForecastMarginPct | H31: RedProjects | I31: AvgHealthScore
A32: Customer Experience | B32: =COUNTIFS(Projects!$E$2:$E$500,A32,Projects!$J$2:$J$500,"Active") -> 4 | C32: =SUMIFS(Projects!$W$2:$W$500,Projects!$E$2:$E$500,A32,Projects!$J$2:$J$500,"Active") -> 3345000 | D32: =SUMIFS(Projects!$Z$2:$Z$500,Projects!$E$2:$E$500,A32,Projects!$J$2:$J$500,"Active") -> 2264800 | E32: =SUMIFS(Projects!$AB$2:$AB$500,Projects!$E$2:$E$500,A32,Projects!$J$2:$J$500,"Active") -> 2077124.5 | F32: =SUMIFS(Projects!$AH$2:$AH$500,Projects!$E$2:$E$500,A32,Projects!$J$2:$J$500,"Active") -> 2459104.5 | G32: =IFERROR((C32-F32)/C32,0) -> 0.2648417 | H32: =COUNTIFS(Projects!$E$2:$E$500,A32,Projects!$J$2:$J$500,"Active",Projects!$BC$2:$BC$500,"Red") -> 2 | I32: =IFERROR(AVERAGEIFS(Projects!$BD$2:$BD$500,Projects!$E$2:$E$500,A32,Projects!$J$2:$J$500,"Active"),0) -> 50.75
A33: Data & AI | B33: =COUNTIFS(Projects!$E$2:$E$500,A33,Projects!$J$2:$J$500,"Active") -> 4 | C33: =SUMIFS(Projects!$W$2:$W$500,Projects!$E$2:$E$500,A33,Projects!$J$2:$J$500,"Active") -> 3765000 | D33: =SUMIFS(Projects!$Z$2:$Z$500,Projects!$E$2:$E$500,A33,Projects!$J$2:$J$500,"Active") -> 2449000 | E33: =SUMIFS(Projects!$AB$2:$AB$500,Projects!$E$2:$E$500,A33,Projects!$J$2:$J$500,"Active") -> 1294670.1 | F33: =SUMIFS(Projects!$AH$2:$AH$500,Projects!$E$2:$E$500,A33,Projects!$J$2:$J$500,"Active") -> 2569291.1 | G33: =IFERROR((C33-F33)/C33,0) -> 0.31758536 | H33: =COUNTIFS(Projects!$E$2:$E$500,A33,Projects!$J$2:$J$500,"Active",Projects!$BC$2:$BC$500,"Red") -> 1 | I33: =IFERROR(AVERAGEIFS(Projects!$BD$2:$BD$500,Projects!$E$2:$E$500,A33,Projects!$J$2:$J$500,"Active"),0) -> 70.75
A34: Cloud & Infrastructure | B34: =COUNTIFS(Projects!$E$2:$E$500,A34,Projects!$J$2:$J$500,"Active") -> 3 | C34: =SUMIFS(Projects!$W$2:$W$500,Projects!$E$2:$E$500,A34,Projects!$J$2:$J$500,"Active") -> 3370000 | D34: =SUMIFS(Projects!$Z$2:$Z$500,Projects!$E$2:$E$500,A34,Projects!$J$2:$J$500,"Active") -> 2218900 | E34: =SUMIFS(Projects!$AB$2:$AB$500,Projects!$E$2:$E$500,A34,Projects!$J$2:$J$500,"Active") -> 1631497.2 | F34: =SUMIFS(Projects!$AH$2:$AH$500,Projects!$E$2:$E$500,A34,Projects!$J$2:$J$500,"Active") -> 2165651.4 | G34: =IFERROR((C34-F34)/C34,0) -> 0.35737346 | H34: =COUNTIFS(Projects!$E$2:$E$500,A34,Projects!$J$2:$J$500,"Active",Projects!$BC$2:$BC$500,"Red") -> 0 | I34: =IFERROR(AVERAGEIFS(Projects!$BD$2:$BD$500,Projects!$E$2:$E$500,A34,Projects!$J$2:$J$500,"Active"),0) -> 89
A35: Digital Transformation | B35: =COUNTIFS(Projects!$E$2:$E$500,A35,Projects!$J$2:$J$500,"Active") -> 3 | C35: =SUMIFS(Projects!$W$2:$W$500,Projects!$E$2:$E$500,A35,Projects!$J$2:$J$500,"Active") -> 3945000 | D35: =SUMIFS(Projects!$Z$2:$Z$500,Projects!$E$2:$E$500,A35,Projects!$J$2:$J$500,"Active") -> 2739700 | E35: =SUMIFS(Projects!$AB$2:$AB$500,Projects!$E$2:$E$500,A35,Projects!$J$2:$J$500,"Active") -> 1489505.2 | F35: =SUMIFS(Projects!$AH$2:$AH$500,Projects!$E$2:$E$500,A35,Projects!$J$2:$J$500,"Active") -> 2677873 | G35: =IFERROR((C35-F35)/C35,0) -> 0.32119822 | H35: =COUNTIFS(Projects!$E$2:$E$500,A35,Projects!$J$2:$J$500,"Active",Projects!$BC$2:$BC$500,"Red") -> 0 | I35: =IFERROR(AVERAGEIFS(Projects!$BD$2:$BD$500,Projects!$E$2:$E$500,A35,Projects!$J$2:$J$500,"Active"),0) -> 89.666667
A36: Operational Excellence | B36: =COUNTIFS(Projects!$E$2:$E$500,A36,Projects!$J$2:$J$500,"Active") -> 3 | C36: =SUMIFS(Projects!$W$2:$W$500,Projects!$E$2:$E$500,A36,Projects!$J$2:$J$500,"Active") -> 1775000 | D36: =SUMIFS(Projects!$Z$2:$Z$500,Projects!$E$2:$E$500,A36,Projects!$J$2:$J$500,"Active") -> 1203500 | E36: =SUMIFS(Projects!$AB$2:$AB$500,Projects!$E$2:$E$500,A36,Projects!$J$2:$J$500,"Active") -> 711922.14 | F36: =SUMIFS(Projects!$AH$2:$AH$500,Projects!$E$2:$E$500,A36,Projects!$J$2:$J$500,"Active") -> 1273679.5 | G36: =IFERROR((C36-F36)/C36,0) -> 0.28243409 | H36: =COUNTIFS(Projects!$E$2:$E$500,A36,Projects!$J$2:$J$500,"Active",Projects!$BC$2:$BC$500,"Red") -> 1 | I36: =IFERROR(AVERAGEIFS(Projects!$BD$2:$BD$500,Projects!$E$2:$E$500,A36,Projects!$J$2:$J$500,"Active"),0) -> 79.333333
A38: Monthly trend (all projects)
A39: MonthEnd | B39: LabourCost | C39: NonLabourCost | D39: TotalCost | E39: HoursLogged | F39: BillableValue | G39: Invoiced | H39: Collected
A40: 45930 | B40: =SUMIFS(Actuals!$J$2:$J$6000,Actuals!$B$2:$B$6000,A40,Actuals!$D$2:$D$6000,"Labour") -> 226537.33 | C40: =SUMIFS(Actuals!$J$2:$J$6000,Actuals!$B$2:$B$6000,A40)-B40 -> 60878.79 | D40: =B40+C40 -> 287416.12 | E40: =SUMIFS(Actuals!$H$2:$H$6000,Actuals!$B$2:$B$6000,A40) -> 2508.1 | F40: =SUMIFS(Actuals!$M$2:$M$6000,Actuals!$B$2:$B$6000,A40) -> 440100 | G40: =SUMIFS(Invoices!$F$2:$F$2000,Invoices!$D$2:$D$2000,">"&EOMONTH(A40,-1),Invoices!$D$2:$D$2000,"<="&A40) -> 222055.56 | H40: =SUMIFS(Invoices!$F$2:$F$2000,Invoices!$G$2:$G$2000,">"&EOMONTH(A40,-1),Invoices!$G$2:$G$2000,"<="&A40) -> 124000
A41: 45961 | B41: =SUMIFS(Actuals!$J$2:$J$6000,Actuals!$B$2:$B$6000,A41,Actuals!$D$2:$D$6000,"Labour") -> 308954.55 | C41: =SUMIFS(Actuals!$J$2:$J$6000,Actuals!$B$2:$B$6000,A41)-B41 -> 60021.69 | D41: =B41+C41 -> 368976.24 | E41: =SUMIFS(Actuals!$H$2:$H$6000,Actuals!$B$2:$B$6000,A41) -> 3627.6 | F41: =SUMIFS(Actuals!$M$2:$M$6000,Actuals!$B$2:$B$6000,A41) -> 589236.5 | G41: =SUMIFS(Invoices!$F$2:$F$2000,Invoices!$D$2:$D$2000,">"&EOMONTH(A41,-1),Invoices!$D$2:$D$2000,"<="&A41) -> 327691.25 | H41: =SUMIFS(Invoices!$F$2:$F$2000,Invoices!$G$2:$G$2000,">"&EOMONTH(A41,-1),Invoices!$G$2:$G$2000,"<="&A41) -> 399635.69
A42: 45991 | B42: =SUMIFS(Actuals!$J$2:$J$6000,Actuals!$B$2:$B$6000,A42,Actuals!$D$2:$D$6000,"Labour") -> 338524.28 | C42: =SUMIFS(Actuals!$J$2:$J$6000,Actuals!$B$2:$B$6000,A42)-B42 -> 113878.9 | D42: =B42+C42 -> 452403.18 | E42: =SUMIFS(Actuals!$H$2:$H$6000,Actuals!$B$2:$B$6000,A42) -> 3956.9 | F42: =SUMIFS(Actuals!$M$2:$M$6000,Actuals!$B$2:$B$6000,A42) -> 648146.5 | G42: =SUMIFS(Invoices!$F$2:$F$2000,Invoices!$D$2:$D$2000,">"&EOMONTH(A42,-1),Invoices!$D$2:$D$2000,"<="&A42) -> 287739.67 | H42: =SUMIFS(Invoices!$F$2:$F$2000,Invoices!$G$2:$G$2000,">"&EOMONTH(A42,-1),Invoices!$G$2:$G$2000,"<="&A42) -> 161111.12
A43: 46022 | B43: =SUMIFS(Actuals!$J$2:$J$6000,Actuals!$B$2:$B$6000,A43,Actuals!$D$2:$D$6000,"Labour") -> 451604.36 | C43: =SUMIFS(Actuals!$J$2:$J$6000,Actuals!$B$2:$B$6000,A43)-B43 -> 76822.19 | D43: =B43+C43 -> 528426.55 | E43: =SUMIFS(Actuals!$H$2:$H$6000,Actuals!$B$2:$B$6000,A43) -> 5293.6 | F43: =SUMIFS(Actuals!$M$2:$M$6000,Actuals!$B$2:$B$6000,A43) -> 872226.5 | G43: =SUMIFS(Invoices!$F$2:$F$2000,Invoices!$D$2:$D$2000,">"&EOMONTH(A43,-1),Invoices!$D$2:$D$2000,"<="&A43) -> 1143552.1 | H43: =SUMIFS(Invoices!$F$2:$F$2000,Invoices!$G$2:$G$2000,">"&EOMONTH(A43,-1),Invoices!$G$2:$G$2000,"<="&A43) -> 528868.46
A44: 46053 | B44: =SUMIFS(Actuals!$J$2:$J$6000,Actuals!$B$2:$B$6000,A44,Actuals!$D$2:$D$6000,"Labour") -> 497834.41 | C44: =SUMIFS(Actuals!$J$2:$J$6000,Actuals!$B$2:$B$6000,A44)-B44 -> 87184.61 | D44: =B44+C44 -> 585019.02 | E44: =SUMIFS(Actuals!$H$2:$H$6000,Actuals!$B$2:$B$6000,A44) -> 5871.3 | F44: =SUMIFS(Actuals!$M$2:$M$6000,Actuals!$B$2:$B$6000,A44) -> 950566 | G44: =SUMIFS(Invoices!$F$2:$F$2000,Invoices!$D$2:$D$2000,">"&EOMONTH(A44,-1),Invoices!$D$2:$D$2000,"<="&A44) -> 530581.74 | H44: =SUMIFS(Invoices!$F$2:$F$2000,Invoices!$G$2:$G$2000,">"&EOMONTH(A44,-1),Invoices!$G$2:$G$2000,"<="&A44) -> 848791.2
A45: 46081 | B45: =SUMIFS(Actuals!$J$2:$J$6000,Actuals!$B$2:$B$6000,A45,Actuals!$D$2:$D$6000,"Labour") -> 569847.6 | C45: =SUMIFS(Actuals!$J$2:$J$6000,Actuals!$B$2:$B$6000,A45)-B45 -> 107260.81 | D45: =B45+C45 -> 677108.41 | E45: =SUMIFS(Actuals!$H$2:$H$6000,Actuals!$B$2:$B$6000,A45) -> 6692.9 | F45: =SUMIFS(Actuals!$M$2:$M$6000,Actuals!$B$2:$B$6000,A45) -> 1094059 | G45: =SUMIFS(Invoices!$F$2:$F$2000,Invoices!$D$2:$D$2000,">"&EOMONTH(A45,-1),Invoices!$D$2:$D$2000,"<="&A45) -> 824162.77 | H45: =SUMIFS(Invoices!$F$2:$F$2000,Invoices!$G$2:$G$2000,">"&EOMONTH(A45,-1),Invoices!$G$2:$G$2000,"<="&A45) -> 600753.08
A46: 46112 | B46: =SUMIFS(Actuals!$J$2:$J$6000,Actuals!$B$2:$B$6000,A46,Actuals!$D$2:$D$6000,"Labour") -> 715100.43 | C46: =SUMIFS(Actuals!$J$2:$J$6000,Actuals!$B$2:$B$6000,A46)-B46 -> 142395.94 | D46: =B46+C46 -> 857496.37 | E46: =SUMIFS(Actuals!$H$2:$H$6000,Actuals!$B$2:$B$6000,A46) -> 8495.3 | F46: =SUMIFS(Actuals!$M$2:$M$6000,Actuals!$B$2:$B$6000,A46) -> 1375508 | G46: =SUMIFS(Invoices!$F$2:$F$2000,Invoices!$D$2:$D$2000,">"&EOMONTH(A46,-1),Invoices!$D$2:$D$2000,"<="&A46) -> 734835.08 | H46: =SUMIFS(Invoices!$F$2:$F$2000,Invoices!$G$2:$G$2000,">"&EOMONTH(A46,-1),Invoices!$G$2:$G$2000,"<="&A46) -> 890179.04
A47: 46142 | B47: =SUMIFS(Actuals!$J$2:$J$6000,Actuals!$B$2:$B$6000,A47,Actuals!$D$2:$D$6000,"Labour") -> 755200.62 | C47: =SUMIFS(Actuals!$J$2:$J$6000,Actuals!$B$2:$B$6000,A47)-B47 -> 205185.93 | D47: =B47+C47 -> 960386.55 | E47: =SUMIFS(Actuals!$H$2:$H$6000,Actuals!$B$2:$B$6000,A47) -> 8986.2 | F47: =SUMIFS(Actuals!$M$2:$M$6000,Actuals!$B$2:$B$6000,A47) -> 1450093 | G47: =SUMIFS(Invoices!$F$2:$F$2000,Invoices!$D$2:$D$2000,">"&EOMONTH(A47,-1),Invoices!$D$2:$D$2000,"<="&A47) -> 922901.46 | H47: =SUMIFS(Invoices!$F$2:$F$2000,Invoices!$G$2:$G$2000,">"&EOMONTH(A47,-1),Invoices!$G$2:$G$2000,"<="&A47) -> 412835.19
A48: 46173 | B48: =SUMIFS(Actuals!$J$2:$J$6000,Actuals!$B$2:$B$6000,A48,Actuals!$D$2:$D$6000,"Labour") -> 721440.5 | C48: =SUMIFS(Actuals!$J$2:$J$6000,Actuals!$B$2:$B$6000,A48)-B48 -> 156690.34 | D48: =B48+C48 -> 878130.84 | E48: =SUMIFS(Actuals!$H$2:$H$6000,Actuals!$B$2:$B$6000,A48) -> 8546.1 | F48: =SUMIFS(Actuals!$M$2:$M$6000,Actuals!$B$2:$B$6000,A48) -> 1379447.5 | G48: =SUMIFS(Invoices!$F$2:$F$2000,Invoices!$D$2:$D$2000,">"&EOMONTH(A48,-1),Invoices!$D$2:$D$2000,"<="&A48) -> 1067186.1 | H48: =SUMIFS(Invoices!$F$2:$F$2000,Invoices!$G$2:$G$2000,">"&EOMONTH(A48,-1),Invoices!$G$2:$G$2000,"<="&A48) -> 1270401.5
A49: 46203 | B49: =SUMIFS(Actuals!$J$2:$J$6000,Actuals!$B$2:$B$6000,A49,Actuals!$D$2:$D$6000,"Labour") -> 746624.31 | C49: =SUMIFS(Actuals!$J$2:$J$6000,Actuals!$B$2:$B$6000,A49)-B49 -> 151714.79 | D49: =B49+C49 -> 898339.1 | E49: =SUMIFS(Actuals!$H$2:$H$6000,Actuals!$B$2:$B$6000,A49) -> 8801.9 | F49: =SUMIFS(Actuals!$M$2:$M$6000,Actuals!$B$2:$B$6000,A49) -> 1443917.5 | G49: =SUMIFS(Invoices!$F$2:$F$2000,Invoices!$D$2:$D$2000,">"&EOMONTH(A49,-1),Invoices!$D$2:$D$2000,"<="&A49) -> 1331587.5 | H49: =SUMIFS(Invoices!$F$2:$F$2000,Invoices!$G$2:$G$2000,">"&EOMONTH(A49,-1),Invoices!$G$2:$G$2000,"<="&A49) -> 670630.5
A50: 46234 | B50: =SUMIFS(Actuals!$J$2:$J$6000,Actuals!$B$2:$B$6000,A50,Actuals!$D$2:$D$6000,"Labour") -> 767116.61 | C50: =SUMIFS(Actuals!$J$2:$J$6000,Actuals!$B$2:$B$6000,A50)-B50 -> 154180.86 | D50: =B50+C50 -> 921297.47 | E50: =SUMIFS(Actuals!$H$2:$H$6000,Actuals!$B$2:$B$6000,A50) -> 9005.7 | F50: =SUMIFS(Actuals!$M$2:$M$6000,Actuals!$B$2:$B$6000,A50) -> 1478260.5 | G50: =SUMIFS(Invoices!$F$2:$F$2000,Invoices!$D$2:$D$2000,">"&EOMONTH(A50,-1),Invoices!$D$2:$D$2000,"<="&A50) -> 1627762.8 | H50: =SUMIFS(Invoices!$F$2:$F$2000,Invoices!$G$2:$G$2000,">"&EOMONTH(A50,-1),Invoices!$G$2:$G$2000,"<="&A50) -> 1403118.8
A51: 46265 | B51: =SUMIFS(Actuals!$J$2:$J$6000,Actuals!$B$2:$B$6000,A51,Actuals!$D$2:$D$6000,"Labour") -> 709187.36 | C51: =SUMIFS(Actuals!$J$2:$J$6000,Actuals!$B$2:$B$6000,A51)-B51 -> 153370.12 | D51: =B51+C51 -> 862557.48 | E51: =SUMIFS(Actuals!$H$2:$H$6000,Actuals!$B$2:$B$6000,A51) -> 8321.5 | F51: =SUMIFS(Actuals!$M$2:$M$6000,Actuals!$B$2:$B$6000,A51) -> 1365848.5 | G51: =SUMIFS(Invoices!$F$2:$F$2000,Invoices!$D$2:$D$2000,">"&EOMONTH(A51,-1),Invoices!$D$2:$D$2000,"<="&A51) -> 721864.92 | H51: =SUMIFS(Invoices!$F$2:$F$2000,Invoices!$G$2:$G$2000,">"&EOMONTH(A51,-1),Invoices!$G$2:$G$2000,"<="&A51) -> 765692.15

Sheet Projects
A1: ProjectID | B1: ProjectName | C1: ClientID | D1: ClientName | E1: Portfolio | F1: BusinessUnit | G1: ProjectManagerID | H1: ProjectManager | I1: ExecutiveSponsor | J1: Status | K1: Phase | L1: Priority | M1: ContractType | N1: StrategicScore | O1: BaselineStart | P1: BaselineEnd | Q1: ForecastEnd | R1: OriginalContractValue | S1: TargetMarginPct | T1: PctComplete | U1: LastStatusUpdate | V1: ApprovedCRRevenue | W1: CurrentContractValue | X1: BaselineBudget | Y1: ApprovedCRCost | Z1: CurrentBudget | AA1: ActualHours | AB1: ActualCost | AC1: ElapsedPct | AD1: EarnedValue | AE1: PlannedValue | AF1: CPI | AG1: SPI | AH1: EAC | AI1: ETC | AJ1: VAC | AK1: BudgetBurnPct | AL1: ForecastMarginAmt | AM1: ForecastMarginPct | AN1: MarginVsTarget | AO1: ScheduleSlipDays | AP1: DaysRemaining | AQ1: InvoicedToDate | AR1: CollectedToDate | AS1: UnbilledWIP | AT1: OpenRisks | AU1: OpenIssues | AV1: OpenRiskExposure | AW1: PendingCRs | AX1: TeamSize | AY1: NextMilestoneDate | AZ1: CostRAG | BA1: ScheduleRAG | BB1: MarginRAG | BC1: OverallRAG | BD1: HealthScore
A2: P-1001 | B2: Patient Portal Modernization | C2: C-101 | D2: =IFERROR(INDEX(Clients!$B$2:$B$200,MATCH(C2,Clients!$A$2:$A$200,0)),"Unknown client") -> Northgate Health Network | E2: Customer Experience | F2: Health & Public | G2: E-0003 | H2: =IFERROR(INDEX(Resources!$B$2:$B$500,MATCH(G2,Resources!$A$2:$A$500,0)),"") -> Aisha Tremblay | I2: Dr. Anne Keller | J2: Active | K2: Test & Deploy | L2: P2 | M2: Fixed Price | N2: 7 | O2: 45964 | P2: 46325 | Q2: 46329 | R2: 1100000 | S2: 0.34 | T2: 0.87 | U2: 46272 | V2: =SUMIFS(ChangeRequests!$H$2:$H$1000,ChangeRequests!$B$2:$B$1000,A2,ChangeRequests!$G$2:$G$1000,"Approved") -> 35000 | W2: =R2+V2 -> 1135000 | X2: =SUMIFS(Budget!$E$2:$E$2000,Budget!$B$2:$B$2000,A2) -> 726500 | Y2: =SUMIFS(ChangeRequests!$I$2:$I$1000,ChangeRequests!$B$2:$B$1000,A2,ChangeRequests!$G$2:$G$1000,"Approved") -> 22000 | Z2: =X2+Y2 -> 748500 | AA2: =SUMIFS(Actuals!$H$2:$H$6000,Actuals!$C$2:$C$6000,A2) -> 5585 | AB2: =SUMIFS(Actuals!$J$2:$J$6000,Actuals!$C$2:$C$6000,A2) -> 569689.28 | AC2: =IF(J2="Completed",1,IF(AsOfDate<=O2,0,MIN(1,(AsOfDate-O2)/MAX(1,P2-O2)))) -> 0.86426593 | AD2: =T2*Z2 -> 651195 | AE2: =AC2*Z2 -> 646903.05 | AF2: =IF(AB2=0,1,AD2/AB2) -> 1.1430705 | AG2: =IF(AE2=0,1,AD2/AE2) -> 1.0066346 | AH2: =IF(J2="Completed",AB2,IF(T2<0.05,MAX(Z2,AB2),AB2/T2)) -> 654815.26 | AI2: =MAX(0,AH2-AB2) -> 85125.984 | AJ2: =Z2-AH2 -> 93684.736 | AK2: =IF(Z2=0,0,AB2/Z2) -> 0.76110792 | AL2: =W2-AH2 -> 480184.74 | AM2: =IF(W2=0,0,AL2/W2) -> 0.42307025 | AN2: =AM2-S2 -> 0.083070252 | AO2: =Q2-P2 -> 4 | AP2: =IF(J2="Completed",0,MAX(0,Q2-AsOfDate)) -> 53 | AQ2: =SUMIFS(Invoices!$F$2:$F$2000,Invoices!$B$2:$B$2000,A2) -> 660000 | AR2: =SUMIFS(Invoices!$F$2:$F$2000,Invoices!$B$2:$B$2000,A2,Invoices!$K$2:$K$2000,"Paid") -> 660000 | AS2: =T2*W2-AQ2 -> 327450 | AT2: =COUNTIFS(RAID!$B$2:$B$2000,A2,RAID!$C$2:$C$2000,"Risk",RAID!$J$2:$J$2000,"<>Closed") -> 0 | AU2: =COUNTIFS(RAID!$B$2:$B$2000,A2,RAID!$C$2:$C$2000,"Issue",RAID!$J$2:$J$2000,"<>Closed") -> 0 | AV2: =SUMIFS(RAID!$Q$2:$Q$2000,RAID!$B$2:$B$2000,A2,RAID!$J$2:$J$2000,"<>Closed") -> 0 | AW2: =COUNTIFS(ChangeRequests!$B$2:$B$1000,A2,ChangeRequests!$P$2:$P$1000,"Yes") -> 0 | AX2: =COUNTIFS(Allocations!$B$2:$B$2000,A2,Allocations!$K$2:$K$2000,"Yes") -> 4 | AY2: =IF(COUNTIFS(Milestones!$B$2:$B$2000,A2,Milestones!$L$2:$L$2000,"<>Completed")=0,"",_xlfn.MINIFS(Milestones!$F$2:$F$2000,Milestones!$B$2:$B$2000,A2,Milestones!$L$2:$L$2000,"<>Completed")) -> 46293 | AZ2: =IF(J2="Planned","N/A",IF(AK2-T2>RAG_CostRed,"Red",IF(AK2-T2>RAG_CostAmber,"Amber","Green"))) -> Green | BA2: =IF(J2="Planned","N/A",IF(AO2>RAG_ScheduleRedDays,"Red",IF(AO2>RAG_ScheduleAmberDays,"Amber","Green"))) -> Green | BB2: =IF(J2="Planned","N/A",IF(AM2<MarginFloor,"Red",IF(AM2<S2-MarginTolerance,"Amber","Green"))) -> Green | BC2: =IF(J2="Planned","N/A",IF(OR(AZ2="Red",BA2="Red",BB2="Red"),"Red",IF(OR(AZ2="Amber",BA2="Amber",BB2="Amber"),"Amber","Green"))) -> Green | BD2: =IF(J2="Planned","",MAX(0,ROUND(100-MAX(0,AK2-T2)*150-MAX(0,AO2)*0.4-MAX(0,S2-AM2)*150,0))) -> 98
A3: P-1002 | B3: Claims Automation Engine | C3: C-102 | D3: =IFERROR(INDEX(Clients!$B$2:$B$200,MATCH(C3,Clients!$A$2:$A$200,0)),"Unknown client") -> Crestline Insurance | E3: Operational Excellence | F3: Financial Services | G3: E-0004 | H3: =IFERROR(INDEX(Resources!$B$2:$B$500,MATCH(G3,Resources!$A$2:$A$500,0)),"") -> Liam Roy | I3: Robert Lindqvist | J3: Active | K3: Execute | L3: P1 | M3: Fixed Price | N3: 7 | O3: 46034 | P3: 46374 | Q3: 46391 | R3: 685000 | S3: 0.32 | T3: 0.57 | U3: 46271 | V3: =SUMIFS(ChangeRequests!$H$2:$H$1000,ChangeRequests!$B$2:$B$1000,A3,ChangeRequests!$G$2:$G$1000,"Approved") -> 85000 | W3: =R3+V3 -> 770000 | X3: =SUMIFS(Budget!$E$2:$E$2000,Budget!$B$2:$B$2000,A3) -> 466100 | Y3: =SUMIFS(ChangeRequests!$I$2:$I$1000,ChangeRequests!$B$2:$B$1000,A3,ChangeRequests!$G$2:$G$1000,"Approved") -> 70000 | Z3: =X3+Y3 -> 536100 | AA3: =SUMIFS(Actuals!$H$2:$H$6000,Actuals!$C$2:$C$6000,A3) -> 4086.4 | AB3: =SUMIFS(Actuals!$J$2:$J$6000,Actuals!$C$2:$C$6000,A3) -> 382554.58 | AC3: =IF(J3="Completed",1,IF(AsOfDate<=O3,0,MIN(1,(AsOfDate-O3)/MAX(1,P3-O3)))) -> 0.71176471 | AD3: =T3*Z3 -> 305577 | AE3: =AC3*Z3 -> 381577.06 | AF3: =IF(AB3=0,1,AD3/AB3) -> 0.79878014 | AG3: =IF(AE3=0,1,AD3/AE3) -> 0.80082645 | AH3: =IF(J3="Completed",AB3,IF(T3<0.05,MAX(Z3,AB3),AB3/T3)) -> 671148.39 | AI3: =MAX(0,AH3-AB3) -> 288593.81 | AJ3: =Z3-AH3 -> -135048.39 | AK3: =IF(Z3=0,0,AB3/Z3) -> 0.7135881 | AL3: =W3-AH3 -> 98851.614 | AM3: =IF(W3=0,0,AL3/W3) -> 0.12837872 | AN3: =AM3-S3 -> -0.19162128 | AO3: =Q3-P3 -> 17 | AP3: =IF(J3="Completed",0,MAX(0,Q3-AsOfDate)) -> 115 | AQ3: =SUMIFS(Invoices!$F$2:$F$2000,Invoices!$B$2:$B$2000,A3) -> 205500 | AR3: =SUMIFS(Invoices!$F$2:$F$2000,Invoices!$B$2:$B$2000,A3,Invoices!$K$2:$K$2000,"Paid") -> 205500 | AS3: =T3*W3-AQ3 -> 233400 | AT3: =COUNTIFS(RAID!$B$2:$B$2000,A3,RAID!$C$2:$C$2000,"Risk",RAID!$J$2:$J$2000,"<>Closed") -> 3 | AU3: =COUNTIFS(RAID!$B$2:$B$2000,A3,RAID!$C$2:$C$2000,"Issue",RAID!$J$2:$J$2000,"<>Closed") -> 0 | AV3: =SUMIFS(RAID!$Q$2:$Q$2000,RAID!$B$2:$B$2000,A3,RAID!$J$2:$J$2000,"<>Closed") -> 105800 | AW3: =COUNTIFS(ChangeRequests!$B$2:$B$1000,A3,ChangeRequests!$P$2:$P$1000,"Yes") -> 1 | AX3: =COUNTIFS(Allocations!$B$2:$B$2000,A3,Allocations!$K$2:$K$2000,"Yes") -> 6 | AY3: =IF(COUNTIFS(Milestones!$B$2:$B$2000,A3,Milestones!$L$2:$L$2000,"<>Completed")=0,"",_xlfn.MINIFS(Milestones!$F$2:$F$2000,Milestones!$B$2:$B$2000,A3,Milestones!$L$2:$L$2000,"<>Completed")) -> 46269 | AZ3: =IF(J3="Planned","N/A",IF(AK3-T3>RAG_CostRed,"Red",IF(AK3-T3>RAG_CostAmber,"Amber","Green"))) -> Amber | BA3: =IF(J3="Planned","N/A",IF(AO3>RAG_ScheduleRedDays,"Red",IF(AO3>RAG_ScheduleAmberDays,"Amber","Green"))) -> Amber | BB3: =IF(J3="Planned","N/A",IF(AM3<MarginFloor,"Red",IF(AM3<S3-MarginTolerance,"Amber","Green"))) -> Red | BC3: =IF(J3="Planned","N/A",IF(OR(AZ3="Red",BA3="Red",BB3="Red"),"Red",IF(OR(AZ3="Amber",BA3="Amber",BB3="Amber"),"Amber","Green"))) -> Red | BD3: =IF(J3="Planned","",MAX(0,ROUND(100-MAX(0,AK3-T3)*150-MAX(0,AO3)*0.4-MAX(0,S3-AM3)*150,0))) -> 43
A4: P-1003 | B4: Enterprise Data Lakehouse | C4: C-103 | D4: =IFERROR(INDEX(Clients!$B$2:$B$200,MATCH(C4,Clients!$A$2:$A$200,0)),"Unknown client") -> Maple Ridge Financial | E4: Data & AI | F4: Financial Services | G4: E-0005 | H4: =IFERROR(INDEX(Resources!$B$2:$B$500,MATCH(G4,Resources!$A$2:$A$500,0)),"") -> Mei Fraser | I4: Janet Osei | J4: Active | K4: Execute | L4: P3 | M4: Time & Materials | N4: 10 | O4: 45908 | P4: 46353 | Q4: 46394 | R4: 1165000 | S4: 0.42 | T4: 0.66 | U4: 46270 | V4: =SUMIFS(ChangeRequests!$H$2:$H$1000,ChangeRequests!$B$2:$B$1000,A4,ChangeRequests!$G$2:$G$1000,"Approved") -> 180000 | W4: =R4+V4 -> 1345000 | X4: =SUMIFS(Budget!$E$2:$E$2000,Budget!$B$2:$B$2000,A4) -> 769600 | Y4: =SUMIFS(ChangeRequests!$I$2:$I$1000,ChangeRequests!$B$2:$B$1000,A4,ChangeRequests!$G$2:$G$1000,"Approved") -> 110000 | Z4: =X4+Y4 -> 879600 | AA4: =SUMIFS(Actuals!$H$2:$H$6000,Actuals!$C$2:$C$6000,A4) -> 5722.4 | AB4: =SUMIFS(Actuals!$J$2:$J$6000,Actuals!$C$2:$C$6000,A4) -> 614808.15 | AC4: =IF(J4="Completed",1,IF(AsOfDate<=O4,0,MIN(1,(AsOfDate-O4)/MAX(1,P4-O4)))) -> 0.82696629 | AD4: =T4*Z4 -> 580536 | AE4: =AC4*Z4 -> 727399.55 | AF4: =IF(AB4=0,1,AD4/AB4) -> 0.94425554 | AG4: =IF(AE4=0,1,AD4/AE4) -> 0.79809783 | AH4: =IF(J4="Completed",AB4,IF(T4<0.05,MAX(Z4,AB4),AB4/T4)) -> 931527.5 | AI4: =MAX(0,AH4-AB4) -> 316719.35 | AJ4: =Z4-AH4 -> -51927.5 | AK4: =IF(Z4=0,0,AB4/Z4) -> 0.69896334 | AL4: =W4-AH4 -> 413472.5 | AM4: =IF(W4=0,0,AL4/W4) -> 0.3074145 | AN4: =AM4-S4 -> -0.1125855 | AO4: =Q4-P4 -> 41 | AP4: =IF(J4="Completed",0,MAX(0,Q4-AsOfDate)) -> 118 | AQ4: =SUMIFS(Invoices!$F$2:$F$2000,Invoices!$B$2:$B$2000,A4) -> 1061258.4 | AR4: =SUMIFS(Invoices!$F$2:$F$2000,Invoices!$B$2:$B$2000,A4,Invoices!$K$2:$K$2000,"Paid") -> 875084.78 | AS4: =T4*W4-AQ4 -> -173558.45 | AT4: =COUNTIFS(RAID!$B$2:$B$2000,A4,RAID!$C$2:$C$2000,"Risk",RAID!$J$2:$J$2000,"<>Closed") -> 2 | AU4: =COUNTIFS(RAID!$B$2:$B$2000,A4,RAID!$C$2:$C$2000,"Issue",RAID!$J$2:$J$2000,"<>Closed") -> 0 | AV4: =SUMIFS(RAID!$Q$2:$Q$2000,RAID!$B$2:$B$2000,A4,RAID!$J$2:$J$2000,"<>Closed") -> 108800 | AW4: =COUNTIFS(ChangeRequests!$B$2:$B$1000,A4,ChangeRequests!$P$2:$P$1000,"Yes") -> 1 | AX4: =COUNTIFS(Allocations!$B$2:$B$2000,A4,Allocations!$K$2:$K$2000,"Yes") -> 5 | AY4: =IF(COUNTIFS(Milestones!$B$2:$B$2000,A4,Milestones!$L$2:$L$2000,"<>Completed")=0,"",_xlfn.MINIFS(Milestones!$F$2:$F$2000,Milestones!$B$2:$B$2000,A4,Milestones!$L$2:$L$2000,"<>Completed")) -> 46263 | AZ4: =IF(J4="Planned","N/A",IF(AK4-T4>RAG_CostRed,"Red",IF(AK4-T4>RAG_CostAmber,"Amber","Green"))) -> Green | BA4: =IF(J4="Planned","N/A",IF(AO4>RAG_ScheduleRedDays,"Red",IF(AO4>RAG_ScheduleAmberDays,"Amber","Green"))) -> Amber | BB4: =IF(J4="Planned","N/A",IF(AM4<MarginFloor,"Red",IF(AM4<S4-MarginTolerance,"Amber","Green"))) -> Amber | BC4: =IF(J4="Planned","N/A",IF(OR(AZ4="Red",BA4="Red",BB4="Red"),"Red",IF(OR(AZ4="Amber",BA4="Amber",BB4="Amber"),"Amber","Green"))) -> Amber | BD4: =IF(J4="Planned","",MAX(0,ROUND(100-MAX(0,AK4-T4)*150-MAX(0,AO4)*0.4-MAX(0,S4-AM4)*150,0))) -> 61
A5: P-1004 | B5: Cloud Migration Wave 2 | C5: C-104 | D5: =IFERROR(INDEX(Clients!$B$2:$B$200,MATCH(C5,Clients!$A$2:$A$200,0)),"Unknown client") -> Harbourview Logistics | E5: Cloud & Infrastructure | F5: Industrial | G5: E-0006 | H5: =IFERROR(INDEX(Resources!$B$2:$B$500,MATCH(G5,Resources!$A$2:$A$500,0)),"") -> Noah Rahimi | I5: Paul Moreau | J5: Active | K5: Execute | L5: P1 | M5: Fixed Price | N5: 6 | O5: 46055 | P5: 46416 | Q5: 46422 | R5: 1155000 | S5: 0.36 | T5: 0.61 | U5: 46269 | V5: =SUMIFS(ChangeRequests!$H$2:$H$1000,ChangeRequests!$B$2:$B$1000,A5,ChangeRequests!$G$2:$G$1000,"Approved") -> 0 | W5: =R5+V5 -> 1155000 | X5: =SUMIFS(Budget!$E$2:$E$2000,Budget!$B$2:$B$2000,A5) -> 738500 | Y5: =SUMIFS(ChangeRequests!$I$2:$I$1000,ChangeRequests!$B$2:$B$1000,A5,ChangeRequests!$G$2:$G$1000,"Approved") -> 0 | Z5: =X5+Y5 -> 738500 | AA5: =SUMIFS(Actuals!$H$2:$H$6000,Actuals!$C$2:$C$6000,A5) -> 2972.5 | AB5: =SUMIFS(Actuals!$J$2:$J$6000,Actuals!$C$2:$C$6000,A5) -> 440837.72 | AC5: =IF(J5="Completed",1,IF(AsOfDate<=O5,0,MIN(1,(AsOfDate-O5)/MAX(1,P5-O5)))) -> 0.61218837 | AD5: =T5*Z5 -> 450485 | AE5: =AC5*Z5 -> 452101.11 | AF5: =IF(AB5=0,1,AD5/AB5) -> 1.021884 | AG5: =IF(AE5=0,1,AD5/AE5) -> 0.99642534 | AH5: =IF(J5="Completed",AB5,IF(T5<0.05,MAX(Z5,AB5),AB5/T5)) -> 722684.79 | AI5: =MAX(0,AH5-AB5) -> 281847.07 | AJ5: =Z5-AH5 -> 15815.213 | AK5: =IF(Z5=0,0,AB5/Z5) -> 0.59693666 | AL5: =W5-AH5 -> 432315.21 | AM5: =IF(W5=0,0,AL5/W5) -> 0.37429889 | AN5: =AM5-S5 -> 0.014298886 | AO5: =Q5-P5 -> 6 | AP5: =IF(J5="Completed",0,MAX(0,Q5-AsOfDate)) -> 146 | AQ5: =SUMIFS(Invoices!$F$2:$F$2000,Invoices!$B$2:$B$2000,A5) -> 346500 | AR5: =SUMIFS(Invoices!$F$2:$F$2000,Invoices!$B$2:$B$2000,A5,Invoices!$K$2:$K$2000,"Paid") -> 346500 | AS5: =T5*W5-AQ5 -> 358050 | AT5: =COUNTIFS(RAID!$B$2:$B$2000,A5,RAID!$C$2:$C$2000,"Risk",RAID!$J$2:$J$2000,"<>Closed") -> 0 | AU5: =COUNTIFS(RAID!$B$2:$B$2000,A5,RAID!$C$2:$C$2000,"Issue",RAID!$J$2:$J$2000,"<>Closed") -> 1 | AV5: =SUMIFS(RAID!$Q$2:$Q$2000,RAID!$B$2:$B$2000,A5,RAID!$J$2:$J$2000,"<>Closed") -> 65400 | AW5: =COUNTIFS(ChangeRequests!$B$2:$B$1000,A5,ChangeRequests!$P$2:$P$1000,"Yes") -> 1 | AX5: =COUNTIFS(Allocations!$B$2:$B$2000,A5,Allocations!$K$2:$K$2000,"Yes") -> 4 | AY5: =IF(COUNTIFS(Milestones!$B$2:$B$2000,A5,Milestones!$L$2:$L$2000,"<>Completed")=0,"",_xlfn.MINIFS(Milestones!$F$2:$F$2000,Milestones!$B$2:$B$2000,A5,Milestones!$L$2:$L$2000,"<>Completed")) -> 46310 | AZ5: =IF(J5="Planned","N/A",IF(AK5-T5>RAG_CostRed,"Red",IF(AK5-T5>RAG_CostAmber,"Amber","Green"))) -> Green | BA5: =IF(J5="Planned","N/A",IF(AO5>RAG_ScheduleRedDays,"Red",IF(AO5>RAG_ScheduleAmberDays,"Amber","Green"))) -> Green | BB5: =IF(J5="Planned","N/A",IF(AM5<MarginFloor,"Red",IF(AM5<S5-MarginTolerance,"Amber","Green"))) -> Green | BC5: =IF(J5="Planned","N/A",IF(OR(AZ5="Red",BA5="Red",BB5="Red"),"Red",IF(OR(AZ5="Amber",BA5="Amber",BB5="Amber"),"Amber","Green"))) -> Green | BD5: =IF(J5="Planned","",MAX(0,ROUND(100-MAX(0,AK5-T5)*150-MAX(0,AO5)*0.4-MAX(0,S5-AM5)*150,0))) -> 98
A6: P-1005 | B6: Fraud Detection ML Platform | C6: C-105 | D6: =IFERROR(INDEX(Clients!$B$2:$B$200,MATCH(C6,Clients!$A$2:$A$200,0)),"Unknown client") -> Ironbridge Capital | E6: Data & AI | F6: Financial Services | G6: E-0007 | H6: =IFERROR(INDEX(Resources!$B$2:$B$500,MATCH(G6,Resources!$A$2:$A$500,0)),"") -> Fatima Cohen | I6: Karen Whitfield | J6: Active | K6: Execute | L6: P1 | M6: Fixed Price | N6: 5 | O6: 46083 | P6: 46444 | Q6: 46510 | R6: 740000 | S6: 0.38 | T6: 0.4 | U6: 46273 | V6: =SUMIFS(ChangeRequests!$H$2:$H$1000,ChangeRequests!$B$2:$B$1000,A6,ChangeRequests!$G$2:$G$1000,"Approved") -> 120000 | W6: =R6+V6 -> 860000 | X6: =SUMIFS(Budget!$E$2:$E$2000,Budget!$B$2:$B$2000,A6) -> 459200 | Y6: =SUMIFS(ChangeRequests!$I$2:$I$1000,ChangeRequests!$B$2:$B$1000,A6,ChangeRequests!$G$2:$G$1000,"Approved") -> 95000 | Z6: =X6+Y6 -> 554200 | AA6: =SUMIFS(Actuals!$H$2:$H$6000,Actuals!$C$2:$C$6000,A6) -> 2942.1 | AB6: =SUMIFS(Actuals!$J$2:$J$6000,Actuals!$C$2:$C$6000,A6) -> 289303.7 | AC6: =IF(J6="Completed",1,IF(AsOfDate<=O6,0,MIN(1,(AsOfDate-O6)/MAX(1,P6-O6)))) -> 0.53462604 | AD6: =T6*Z6 -> 221680 | AE6: =AC6*Z6 -> 296289.75 | AF6: =IF(AB6=0,1,AD6/AB6) -> 0.76625359 | AG6: =IF(AE6=0,1,AD6/AE6) -> 0.74818653 | AH6: =IF(J6="Completed",AB6,IF(T6<0.05,MAX(Z6,AB6),AB6/T6)) -> 723259.25 | AI6: =MAX(0,AH6-AB6) -> 433955.55 | AJ6: =Z6-AH6 -> -169059.25 | AK6: =IF(Z6=0,0,AB6/Z6) -> 0.52202039 | AL6: =W6-AH6 -> 136740.75 | AM6: =IF(W6=0,0,AL6/W6) -> 0.15900087 | AN6: =AM6-S6 -> -0.22099913 | AO6: =Q6-P6 -> 66 | AP6: =IF(J6="Completed",0,MAX(0,Q6-AsOfDate)) -> 234 | AQ6: =SUMIFS(Invoices!$F$2:$F$2000,Invoices!$B$2:$B$2000,A6) -> 222000 | AR6: =SUMIFS(Invoices!$F$2:$F$2000,Invoices!$B$2:$B$2000,A6,Invoices!$K$2:$K$2000,"Paid") -> 222000 | AS6: =T6*W6-AQ6 -> 122000 | AT6: =COUNTIFS(RAID!$B$2:$B$2000,A6,RAID!$C$2:$C$2000,"Risk",RAID!$J$2:$J$2000,"<>Closed") -> 2 | AU6: =COUNTIFS(RAID!$B$2:$B$2000,A6,RAID!$C$2:$C$2000,"Issue",RAID!$J$2:$J$2000,"<>Closed") -> 1 | AV6: =SUMIFS(RAID!$Q$2:$Q$2000,RAID!$B$2:$B$2000,A6,RAID!$J$2:$J$2000,"<>Closed") -> 337800 | AW6: =COUNTIFS(ChangeRequests!$B$2:$B$1000,A6,ChangeRequests!$P$2:$P$1000,"Yes") -> 2 | AX6: =COUNTIFS(Allocations!$B$2:$B$2000,A6,Allocations!$K$2:$K$2000,"Yes") -> 6 | AY6: =IF(COUNTIFS(Milestones!$B$2:$B$2000,A6,Milestones!$L$2:$L$2000,"<>Completed")=0,"",_xlfn.MINIFS(Milestones!$F$2:$F$2000,Milestones!$B$2:$B$2000,A6,Milestones!$L$2:$L$2000,"<>Completed")) -> 46377 | AZ6: =IF(J6="Planned","N/A",IF(AK6-T6>RAG_CostRed,"Red",IF(AK6-T6>RAG_CostAmber,"Amber","Green"))) -> Amber | BA6: =IF(J6="Planned","N/A",IF(AO6>RAG_ScheduleRedDays,"Red",IF(AO6>RAG_ScheduleAmberDays,"Amber","Green"))) -> Red | BB6: =IF(J6="Planned","N/A",IF(AM6<MarginFloor,"Red",IF(AM6<S6-MarginTolerance,"Amber","Green"))) -> Amber | BC6: =IF(J6="Planned","N/A",IF(OR(AZ6="Red",BA6="Red",BB6="Red"),"Red",IF(OR(AZ6="Amber",BA6="Amber",BB6="Amber"),"Amber","Green"))) -> Red | BD6: =IF(J6="Planned","",MAX(0,ROUND(100-MAX(0,AK6-T6)*150-MAX(0,AO6)*0.4-MAX(0,S6-AM6)*150,0))) -> 22
A7: P-1006 | B7: Omnichannel Commerce Replatform | C7: C-106 | D7: =IFERROR(INDEX(Clients!$B$2:$B$200,MATCH(C7,Clients!$A$2:$A$200,0)),"Unknown client") -> Aurora Retail Group | E7: Customer Experience | F7: Consumer | G7: E-0009 | H7: =IFERROR(INDEX(Resources!$B$2:$B$500,MATCH(G7,Resources!$A$2:$A$500,0)),"") -> Olivia Silva | I7: Luc Bergeron | J7: Active | K7: Test & Deploy | L7: P2 | M7: Fixed Price | N7: 7 | O7: 45936 | P7: 46290 | Q7: 46300 | R7: 940000 | S7: 0.38 | T7: 0.92 | U7: 46272 | V7: =SUMIFS(ChangeRequests!$H$2:$H$1000,ChangeRequests!$B$2:$B$1000,A7,ChangeRequests!$G$2:$G$1000,"Approved") -> 40000 | W7: =R7+V7 -> 980000 | X7: =SUMIFS(Budget!$E$2:$E$2000,Budget!$B$2:$B$2000,A7) -> 582300 | Y7: =SUMIFS(ChangeRequests!$I$2:$I$1000,ChangeRequests!$B$2:$B$1000,A7,ChangeRequests!$G$2:$G$1000,"Approved") -> 48000 | Z7: =X7+Y7 -> 630300 | AA7: =SUMIFS(Actuals!$H$2:$H$6000,Actuals!$C$2:$C$6000,A7) -> 7769.4 | AB7: =SUMIFS(Actuals!$J$2:$J$6000,Actuals!$C$2:$C$6000,A7) -> 622397.49 | AC7: =IF(J7="Completed",1,IF(AsOfDate<=O7,0,MIN(1,(AsOfDate-O7)/MAX(1,P7-O7)))) -> 0.96045198 | AD7: =T7*Z7 -> 579876 | AE7: =AC7*Z7 -> 605372.88 | AF7: =IF(AB7=0,1,AD7/AB7) -> 0.93168114 | AG7: =IF(AE7=0,1,AD7/AE7) -> 0.95788235 | AH7: =IF(J7="Completed",AB7,IF(T7<0.05,MAX(Z7,AB7),AB7/T7)) -> 676519.01 | AI7: =MAX(0,AH7-AB7) -> 54121.521 | AJ7: =Z7-AH7 -> -46219.011 | AK7: =IF(Z7=0,0,AB7/Z7) -> 0.9874623 | AL7: =W7-AH7 -> 303480.99 | AM7: =IF(W7=0,0,AL7/W7) -> 0.30967448 | AN7: =AM7-S7 -> -0.070325521 | AO7: =Q7-P7 -> 10 | AP7: =IF(J7="Completed",0,MAX(0,Q7-AsOfDate)) -> 24 | AQ7: =SUMIFS(Invoices!$F$2:$F$2000,Invoices!$B$2:$B$2000,A7) -> 752000 | AR7: =SUMIFS(Invoices!$F$2:$F$2000,Invoices!$B$2:$B$2000,A7,Invoices!$K$2:$K$2000,"Paid") -> 282000 | AS7: =T7*W7-AQ7 -> 149600 | AT7: =COUNTIFS(RAID!$B$2:$B$2000,A7,RAID!$C$2:$C$2000,"Risk",RAID!$J$2:$J$2000,"<>Closed") -> 0 | AU7: =COUNTIFS(RAID!$B$2:$B$2000,A7,RAID!$C$2:$C$2000,"Issue",RAID!$J$2:$J$2000,"<>Closed") -> 1 | AV7: =SUMIFS(RAID!$Q$2:$Q$2000,RAID!$B$2:$B$2000,A7,RAID!$J$2:$J$2000,"<>Closed") -> 21000 | AW7: =COUNTIFS(ChangeRequests!$B$2:$B$1000,A7,ChangeRequests!$P$2:$P$1000,"Yes") -> 0 | AX7: =COUNTIFS(Allocations!$B$2:$B$2000,A7,Allocations!$K$2:$K$2000,"Yes") -> 4 | AY7: =IF(COUNTIFS(Milestones!$B$2:$B$2000,A7,Milestones!$L$2:$L$2000,"<>Completed")=0,"",_xlfn.MINIFS(Milestones!$F$2:$F$2000,Milestones!$B$2:$B$2000,A7,Milestones!$L$2:$L$2000,"<>Completed")) -> 46300 | AZ7: =IF(J7="Planned","N/A",IF(AK7-T7>RAG_CostRed,"Red",IF(AK7-T7>RAG_CostAmber,"Amber","Green"))) -> Green | BA7: =IF(J7="Planned","N/A",IF(AO7>RAG_ScheduleRedDays,"Red",IF(AO7>RAG_ScheduleAmberDays,"Amber","Green"))) -> Green | BB7: =IF(J7="Planned","N/A",IF(AM7<MarginFloor,"Red",IF(AM7<S7-MarginTolerance,"Amber","Green"))) -> Amber | BC7: =IF(J7="Planned","N/A",IF(OR(AZ7="Red",BA7="Red",BB7="Red"),"Red",IF(OR(AZ7="Amber",BA7="Amber",BB7="Amber"),"Amber","Green"))) -> Amber | BD7: =IF(J7="Planned","",MAX(0,ROUND(100-MAX(0,AK7-T7)*150-MAX(0,AO7)*0.4-MAX(0,S7-AM7)*150,0))) -> 75
A8: P-1007 | B8: Student Information System Upgrade | C8: C-107 | D8: =IFERROR(INDEX(Clients!$B$2:$B$200,MATCH(C8,Clients!$A$2:$A$200,0)),"Unknown client") -> Pinecrest University | E8: Digital Transformation | F8: Health & Public | G8: E-0008 | H8: =IFERROR(INDEX(Resources!$B$2:$B$500,MATCH(G8,Resources!$A$2:$A$500,0)),"") -> Ethan Park | I8: Prof. Ellen Shaw | J8: Active | K8: Execute | L8: P1 | M8: Fixed Price | N8: 10 | O8: 46118 | P8: 46472 | Q8: 46475 | R8: 970000 | S8: 0.34 | T8: 0.43 | U8: 46271 | V8: =SUMIFS(ChangeRequests!$H$2:$H$1000,ChangeRequests!$B$2:$B$1000,A8,ChangeRequests!$G$2:$G$1000,"Approved") -> 0 | W8: =R8+V8 -> 970000 | X8: =SUMIFS(Budget!$E$2:$E$2000,Budget!$B$2:$B$2000,A8) -> 639400 | Y8: =SUMIFS(ChangeRequests!$I$2:$I$1000,ChangeRequests!$B$2:$B$1000,A8,ChangeRequests!$G$2:$G$1000,"Approved") -> 0 | Z8: =X8+Y8 -> 639400 | AA8: =SUMIFS(Actuals!$H$2:$H$6000,Actuals!$C$2:$C$6000,A8) -> 2307 | AB8: =SUMIFS(Actuals!$J$2:$J$6000,Actuals!$C$2:$C$6000,A8) -> 249953.93 | AC8: =IF(J8="Completed",1,IF(AsOfDate<=O8,0,MIN(1,(AsOfDate-O8)/MAX(1,P8-O8)))) -> 0.44632768 | AD8: =T8*Z8 -> 274942 | AE8: =AC8*Z8 -> 285381.92 | AF8: =IF(AB8=0,1,AD8/AB8) -> 1.0999707 | AG8: =IF(AE8=0,1,AD8/AE8) -> 0.96341772 | AH8: =IF(J8="Completed",AB8,IF(T8<0.05,MAX(Z8,AB8),AB8/T8)) -> 581288.21 | AI8: =MAX(0,AH8-AB8) -> 331334.28 | AJ8: =Z8-AH8 -> 58111.791 | AK8: =IF(Z8=0,0,AB8/Z8) -> 0.3909195 | AL8: =W8-AH8 -> 388711.79 | AM8: =IF(W8=0,0,AL8/W8) -> 0.4007338 | AN8: =AM8-S8 -> 0.060733805 | AO8: =Q8-P8 -> 3 | AP8: =IF(J8="Completed",0,MAX(0,Q8-AsOfDate)) -> 199 | AQ8: =SUMIFS(Invoices!$F$2:$F$2000,Invoices!$B$2:$B$2000,A8) -> 291000 | AR8: =SUMIFS(Invoices!$F$2:$F$2000,Invoices!$B$2:$B$2000,A8,Invoices!$K$2:$K$2000,"Paid") -> 97000 | AS8: =T8*W8-AQ8 -> 126100 | AT8: =COUNTIFS(RAID!$B$2:$B$2000,A8,RAID!$C$2:$C$2000,"Risk",RAID!$J$2:$J$2000,"<>Closed") -> 2 | AU8: =COUNTIFS(RAID!$B$2:$B$2000,A8,RAID!$C$2:$C$2000,"Issue",RAID!$J$2:$J$2000,"<>Closed") -> 0 | AV8: =SUMIFS(RAID!$Q$2:$Q$2000,RAID!$B$2:$B$2000,A8,RAID!$J$2:$J$2000,"<>Closed") -> 22800 | AW8: =COUNTIFS(ChangeRequests!$B$2:$B$1000,A8,ChangeRequests!$P$2:$P$1000,"Yes") -> 1 | AX8: =COUNTIFS(Allocations!$B$2:$B$2000,A8,Allocations!$K$2:$K$2000,"Yes") -> 5 | AY8: =IF(COUNTIFS(Milestones!$B$2:$B$2000,A8,Milestones!$L$2:$L$2000,"<>Completed")=0,"",_xlfn.MINIFS(Milestones!$F$2:$F$2000,Milestones!$B$2:$B$2000,A8,Milestones!$L$2:$L$2000,"<>Completed")) -> 46366 | AZ8: =IF(J8="Planned","N/A",IF(AK8-T8>RAG_CostRed,"Red",IF(AK8-T8>RAG_CostAmber,"Amber","Green"))) -> Green | BA8: =IF(J8="Planned","N/A",IF(AO8>RAG_ScheduleRedDays,"Red",IF(AO8>RAG_ScheduleAmberDays,"Amber","Green"))) -> Green | BB8: =IF(J8="Planned","N/A",IF(AM8<MarginFloor,"Red",IF(AM8<S8-MarginTolerance,"Amber","Green"))) -> Green | BC8: =IF(J8="Planned","N/A",IF(OR(AZ8="Red",BA8="Red",BB8="Red"),"Red",IF(OR(AZ8="Amber",BA8="Amber",BB8="Amber"),"Amber","Green"))) -> Green | BD8: =IF(J8="Planned","",MAX(0,ROUND(100-MAX(0,AK8-T8)*150-MAX(0,AO8)*0.4-MAX(0,S8-AM8)*150,0))) -> 99
A9: P-1008 | B9: Network Operations Centre Refresh | C9: C-108 | D9: =IFERROR(INDEX(Clients!$B$2:$B$200,MATCH(C9,Clients!$A$2:$A$200,0)),"Unknown client") -> Summit Telecom | E9: Cloud & Infrastructure | F9: Industrial | G9: E-0010 | H9: =IFERROR(INDEX(Resources!$B$2:$B$500,MATCH(G9,Resources!$A$2:$A$500,0)),"") -> Arjun Baptiste | I9: Trevor Nakamura | J9: Active | K9: Test & Deploy | L9: P2 | M9: Time & Materials | N9: 9 | O9: 46027 | P9: 46311 | Q9: 46328 | R9: 710000 | S9: 0.42 | T9: 0.85 | U9: 46270 | V9: =SUMIFS(ChangeRequests!$H$2:$H$1000,ChangeRequests!$B$2:$B$1000,A9,ChangeRequests!$G$2:$G$1000,"Approved") -> 55000 | W9: =R9+V9 -> 765000 | X9: =SUMIFS(Budget!$E$2:$E$2000,Budget!$B$2:$B$2000,A9) -> 498500 | Y9: =SUMIFS(ChangeRequests!$I$2:$I$1000,ChangeRequests!$B$2:$B$1000,A9,ChangeRequests!$G$2:$G$1000,"Approved") -> 38000 | Z9: =X9+Y9 -> 536500 | AA9: =SUMIFS(Actuals!$H$2:$H$6000,Actuals!$C$2:$C$6000,A9) -> 3581.3 | AB9: =SUMIFS(Actuals!$J$2:$J$6000,Actuals!$C$2:$C$6000,A9) -> 464449.86 | AC9: =IF(J9="Completed",1,IF(AsOfDate<=O9,0,MIN(1,(AsOfDate-O9)/MAX(1,P9-O9)))) -> 0.87676056 | AD9: =T9*Z9 -> 456025 | AE9: =AC9*Z9 -> 470382.04 | AF9: =IF(AB9=0,1,AD9/AB9) -> 0.98186056 | AG9: =IF(AE9=0,1,AD9/AE9) -> 0.96947791 | AH9: =IF(J9="Completed",AB9,IF(T9<0.05,MAX(Z9,AB9),AB9/T9)) -> 546411.6 | AI9: =MAX(0,AH9-AB9) -> 81961.74 | AJ9: =Z9-AH9 -> -9911.6 | AK9: =IF(Z9=0,0,AB9/Z9) -> 0.86570337 | AL9: =W9-AH9 -> 218588.4 | AM9: =IF(W9=0,0,AL9/W9) -> 0.28573647 | AN9: =AM9-S9 -> -0.13426353 | AO9: =Q9-P9 -> 17 | AP9: =IF(J9="Completed",0,MAX(0,Q9-AsOfDate)) -> 52 | AQ9: =SUMIFS(Invoices!$F$2:$F$2000,Invoices!$B$2:$B$2000,A9) -> 716418.97 | AR9: =SUMIFS(Invoices!$F$2:$F$2000,Invoices!$B$2:$B$2000,A9,Invoices!$K$2:$K$2000,"Paid") -> 639535.85 | AS9: =T9*W9-AQ9 -> -66168.97 | AT9: =COUNTIFS(RAID!$B$2:$B$2000,A9,RAID!$C$2:$C$2000,"Risk",RAID!$J$2:$J$2000,"<>Closed") -> 1 | AU9: =COUNTIFS(RAID!$B$2:$B$2000,A9,RAID!$C$2:$C$2000,"Issue",RAID!$J$2:$J$2000,"<>Closed") -> 0 | AV9: =SUMIFS(RAID!$Q$2:$Q$2000,RAID!$B$2:$B$2000,A9,RAID!$J$2:$J$2000,"<>Closed") -> 6000 | AW9: =COUNTIFS(ChangeRequests!$B$2:$B$1000,A9,ChangeRequests!$P$2:$P$1000,"Yes") -> 0 | AX9: =COUNTIFS(Allocations!$B$2:$B$2000,A9,Allocations!$K$2:$K$2000,"Yes") -> 4 | AY9: =IF(COUNTIFS(Milestones!$B$2:$B$2000,A9,Milestones!$L$2:$L$2000,"<>Completed")=0,"",_xlfn.MINIFS(Milestones!$F$2:$F$2000,Milestones!$B$2:$B$2000,A9,Milestones!$L$2:$L$2000,"<>Completed")) -> 46296 | AZ9: =IF(J9="Planned","N/A",IF(AK9-T9>RAG_CostRed,"Red",IF(AK9-T9>RAG_CostAmber,"Amber","Green"))) -> Green | BA9: =IF(J9="Planned","N/A",IF(AO9>RAG_ScheduleRedDays,"Red",IF(AO9>RAG_ScheduleAmberDays,"Amber","Green"))) -> Amber | BB9: =IF(J9="Planned","N/A",IF(AM9<MarginFloor,"Red",IF(AM9<S9-MarginTolerance,"Amber","Green"))) -> Amber | BC9: =IF(J9="Planned","N/A",IF(OR(AZ9="Red",BA9="Red",BB9="Red"),"Red",IF(OR(AZ9="Amber",BA9="Amber",BB9="Amber"),"Amber","Green"))) -> Amber | BD9: =IF(J9="Planned","",MAX(0,ROUND(100-MAX(0,AK9-T9)*150-MAX(0,AO9)*0.4-MAX(0,S9-AM9)*150,0))) -> 71
A10: P-1009 | B10: Smart Factory IoT Pilot | C10: C-109 | D10: =IFERROR(INDEX(Clients!$B$2:$B$200,MATCH(C10,Clients!$A$2:$A$200,0)),"Unknown client") -> Granite Manufacturing | E10: Operational Excellence | F10: Industrial | G10: E-0005 | H10: =IFERROR(INDEX(Resources!$B$2:$B$500,MATCH(G10,Resources!$A$2:$A$500,0)),"") -> Mei Fraser | I10: Greg Kowalski | J10: Active | K10: Execute | L10: P2 | M10: Fixed Price | N10: 10 | O10: 46146 | P10: 46367 | Q10: 46370 | R10: 535000 | S10: 0.36 | T10: 0.5 | U10: 46269 | V10: =SUMIFS(ChangeRequests!$H$2:$H$1000,ChangeRequests!$B$2:$B$1000,A10,ChangeRequests!$G$2:$G$1000,"Approved") -> 0 | W10: =R10+V10 -> 535000 | X10: =SUMIFS(Budget!$E$2:$E$2000,Budget!$B$2:$B$2000,A10) -> 342700 | Y10: =SUMIFS(ChangeRequests!$I$2:$I$1000,ChangeRequests!$B$2:$B$1000,A10,ChangeRequests!$G$2:$G$1000,"Approved") -> 0 | Z10: =X10+Y10 -> 342700 | AA10: =SUMIFS(Actuals!$H$2:$H$6000,Actuals!$C$2:$C$6000,A10) -> 1798 | AB10: =SUMIFS(Actuals!$J$2:$J$6000,Actuals!$C$2:$C$6000,A10) -> 160755.53 | AC10: =IF(J10="Completed",1,IF(AsOfDate<=O10,0,MIN(1,(AsOfDate-O10)/MAX(1,P10-O10)))) -> 0.58823529 | AD10: =T10*Z10 -> 171350 | AE10: =AC10*Z10 -> 201588.24 | AF10: =IF(AB10=0,1,AD10/AB10) -> 1.0659042 | AG10: =IF(AE10=0,1,AD10/AE10) -> 0.85 | AH10: =IF(J10="Completed",AB10,IF(T10<0.05,MAX(Z10,AB10),AB10/T10)) -> 321511.06 | AI10: =MAX(0,AH10-AB10) -> 160755.53 | AJ10: =Z10-AH10 -> 21188.94 | AK10: =IF(Z10=0,0,AB10/Z10) -> 0.46908529 | AL10: =W10-AH10 -> 213488.94 | AM10: =IF(W10=0,0,AL10/W10) -> 0.39904475 | AN10: =AM10-S10 -> 0.039044748 | AO10: =Q10-P10 -> 3 | AP10: =IF(J10="Completed",0,MAX(0,Q10-AsOfDate)) -> 94 | AQ10: =SUMIFS(Invoices!$F$2:$F$2000,Invoices!$B$2:$B$2000,A10) -> 160500 | AR10: =SUMIFS(Invoices!$F$2:$F$2000,Invoices!$B$2:$B$2000,A10,Invoices!$K$2:$K$2000,"Paid") -> 160500 | AS10: =T10*W10-AQ10 -> 107000 | AT10: =COUNTIFS(RAID!$B$2:$B$2000,A10,RAID!$C$2:$C$2000,"Risk",RAID!$J$2:$J$2000,"<>Closed") -> 1 | AU10: =COUNTIFS(RAID!$B$2:$B$2000,A10,RAID!$C$2:$C$2000,"Issue",RAID!$J$2:$J$2000,"<>Closed") -> 1 | AV10: =SUMIFS(RAID!$Q$2:$Q$2000,RAID!$B$2:$B$2000,A10,RAID!$J$2:$J$2000,"<>Closed") -> 70600 | AW10: =COUNTIFS(ChangeRequests!$B$2:$B$1000,A10,ChangeRequests!$P$2:$P$1000,"Yes") -> 0 | AX10: =COUNTIFS(Allocations!$B$2:$B$2000,A10,Allocations!$K$2:$K$2000,"Yes") -> 6 | AY10: =IF(COUNTIFS(Milestones!$B$2:$B$2000,A10,Milestones!$L$2:$L$2000,"<>Completed")=0,"",_xlfn.MINIFS(Milestones!$F$2:$F$2000,Milestones!$B$2:$B$2000,A10,Milestones!$L$2:$L$2000,"<>Completed")) -> 46301 | AZ10: =IF(J10="Planned","N/A",IF(AK10-T10>RAG_CostRed,"Red",IF(AK10-T10>RAG_CostAmber,"Amber","Green"))) -> Green | BA10: =IF(J10="Planned","N/A",IF(AO10>RAG_ScheduleRedDays,"Red",IF(AO10>RAG_ScheduleAmberDays,"Amber","Green"))) -> Green | BB10: =IF(J10="Planned","N/A",IF(AM10<MarginFloor,"Red",IF(AM10<S10-MarginTolerance,"Amber","Green"))) -> Green | BC10: =IF(J10="Planned","N/A",IF(OR(AZ10="Red",BA10="Red",BB10="Red"),"Red",IF(OR(AZ10="Amber",BA10="Amber",BB10="Amber"),"Amber","Green"))) -> Green | BD10: =IF(J10="Planned","",MAX(0,ROUND(100-MAX(0,AK10-T10)*150-MAX(0,AO10)*0.4-MAX(0,S10-AM10)*150,0))) -> 99
A11: P-1010 | B11: 311 Citizen Services App | C11: C-110 | D11: =IFERROR(INDEX(Clients!$B$2:$B$200,MATCH(C11,Clients!$A$2:$A$200,0)),"Unknown client") -> Bluewater Municipal Services | E11: Customer Experience | F11: Health & Public | G11: E-0007 | H11: =IFERROR(INDEX(Resources!$B$2:$B$500,MATCH(G11,Resources!$A$2:$A$500,0)),"") -> Fatima Cohen | I11: Mayor's Office - D. Price | J11: Active | K11: Test & Deploy | L11: P2 | M11: Fixed Price | N11: 10 | O11: 45992 | P11: 46262 | Q11: 46311 | R11: 735000 | S11: 0.38 | T11: 0.86 | U11: 46273 | V11: =SUMIFS(ChangeRequests!$H$2:$H$1000,ChangeRequests!$B$2:$B$1000,A11,ChangeRequests!$G$2:$G$1000,"Approved") -> 30000 | W11: =R11+V11 -> 765000 | X11: =SUMIFS(Budget!$E$2:$E$2000,Budget!$B$2:$B$2000,A11) -> 455000 | Y11: =SUMIFS(ChangeRequests!$I$2:$I$1000,ChangeRequests!$B$2:$B$1000,A11,ChangeRequests!$G$2:$G$1000,"Approved") -> 42000 | Z11: =X11+Y11 -> 497000 | AA11: =SUMIFS(Actuals!$H$2:$H$6000,Actuals!$C$2:$C$6000,A11) -> 5522.3 | AB11: =SUMIFS(Actuals!$J$2:$J$6000,Actuals!$C$2:$C$6000,A11) -> 513842.3 | AC11: =IF(J11="Completed",1,IF(AsOfDate<=O11,0,MIN(1,(AsOfDate-O11)/MAX(1,P11-O11)))) -> 1 | AD11: =T11*Z11 -> 427420 | AE11: =AC11*Z11 -> 497000 | AF11: =IF(AB11=0,1,AD11/AB11) -> 0.83181163 | AG11: =IF(AE11=0,1,AD11/AE11) -> 0.86 | AH11: =IF(J11="Completed",AB11,IF(T11<0.05,MAX(Z11,AB11),AB11/T11)) -> 597491.05 | AI11: =MAX(0,AH11-AB11) -> 83648.747 | AJ11: =Z11-AH11 -> -100491.05 | AK11: =IF(Z11=0,0,AB11/Z11) -> 1.0338879 | AL11: =W11-AH11 -> 167508.95 | AM11: =IF(W11=0,0,AL11/W11) -> 0.21896595 | AN11: =AM11-S11 -> -0.16103405 | AO11: =Q11-P11 -> 49 | AP11: =IF(J11="Completed",0,MAX(0,Q11-AsOfDate)) -> 35 | AQ11: =SUMIFS(Invoices!$F$2:$F$2000,Invoices!$B$2:$B$2000,A11) -> 441000 | AR11: =SUMIFS(Invoices!$F$2:$F$2000,Invoices!$B$2:$B$2000,A11,Invoices!$K$2:$K$2000,"Paid") -> 220500 | AS11: =T11*W11-AQ11 -> 216900 | AT11: =COUNTIFS(RAID!$B$2:$B$2000,A11,RAID!$C$2:$C$2000,"Risk",RAID!$J$2:$J$2000,"<>Closed") -> 2 | AU11: =COUNTIFS(RAID!$B$2:$B$2000,A11,RAID!$C$2:$C$2000,"Issue",RAID!$J$2:$J$2000,"<>Closed") -> 1 | AV11: =SUMIFS(RAID!$Q$2:$Q$2000,RAID!$B$2:$B$2000,A11,RAID!$J$2:$J$2000,"<>Closed") -> 286400 | AW11: =COUNTIFS(ChangeRequests!$B$2:$B$1000,A11,ChangeRequests!$P$2:$P$1000,"Yes") -> 0 | AX11: =COUNTIFS(Allocations!$B$2:$B$2000,A11,Allocations!$K$2:$K$2000,"Yes") -> 4 | AY11: =IF(COUNTIFS(Milestones!$B$2:$B$2000,A11,Milestones!$L$2:$L$2000,"<>Completed")=0,"",_xlfn.MINIFS(Milestones!$F$2:$F$2000,Milestones!$B$2:$B$2000,A11,Milestones!$L$2:$L$2000,"<>Completed")) -> 46267 | AZ11: =IF(J11="Planned","N/A",IF(AK11-T11>RAG_CostRed,"Red",IF(AK11-T11>RAG_CostAmber,"Amber","Green"))) -> Amber | BA11: =IF(J11="Planned","N/A",IF(AO11>RAG_ScheduleRedDays,"Red",IF(AO11>RAG_ScheduleAmberDays,"Amber","Green"))) -> Red | BB11: =IF(J11="Planned","N/A",IF(AM11<MarginFloor,"Red",IF(AM11<S11-MarginTolerance,"Amber","Green"))) -> Amber | BC11: =IF(J11="Planned","N/A",IF(OR(AZ11="Red",BA11="Red",BB11="Red"),"Red",IF(OR(AZ11="Amber",BA11="Amber",BB11="Amber"),"Amber","Green"))) -> Red | BD11: =IF(J11="Planned","",MAX(0,ROUND(100-MAX(0,AK11-T11)*150-MAX(0,AO11)*0.4-MAX(0,S11-AM11)*150,0))) -> 30
A12: P-1011 | B12: Clinical Trials Data Hub | C12: C-111 | D12: =IFERROR(INDEX(Clients!$B$2:$B$200,MATCH(C12,Clients!$A$2:$A$200,0)),"Unknown client") -> Evergreen Pharma | E12: Data & AI | F12: Health & Public | G12: E-0006 | H12: =IFERROR(INDEX(Resources!$B$2:$B$500,MATCH(G12,Resources!$A$2:$A$500,0)),"") -> Noah Rahimi | I12: Dr. Mira Castellano | J12: Active | K12: Execute | L12: P3 | M12: Time & Materials | N12: 6 | O12: 46069 | P12: 46507 | Q12: 46507 | R12: 975000 | S12: 0.42 | T12: 0.42 | U12: 46272 | V12: =SUMIFS(ChangeRequests!$H$2:$H$1000,ChangeRequests!$B$2:$B$1000,A12,ChangeRequests!$G$2:$G$1000,"Approved") -> 75000 | W12: =R12+V12 -> 1050000 | X12: =SUMIFS(Budget!$E$2:$E$2000,Budget!$B$2:$B$2000,A12) -> 620700 | Y12: =SUMIFS(ChangeRequests!$I$2:$I$1000,ChangeRequests!$B$2:$B$1000,A12,ChangeRequests!$G$2:$G$1000,"Approved") -> 48000 | Z12: =X12+Y12 -> 668700 | AA12: =SUMIFS(Actuals!$H$2:$H$6000,Actuals!$C$2:$C$6000,A12) -> 2296.3 | AB12: =SUMIFS(Actuals!$J$2:$J$6000,Actuals!$C$2:$C$6000,A12) -> 248297.41 | AC12: =IF(J12="Completed",1,IF(AsOfDate<=O12,0,MIN(1,(AsOfDate-O12)/MAX(1,P12-O12)))) -> 0.47260274 | AD12: =T12*Z12 -> 280854 | AE12: =AC12*Z12 -> 316029.45 | AF12: =IF(AB12=0,1,AD12/AB12) -> 1.1311193 | AG12: =IF(AE12=0,1,AD12/AE12) -> 0.88869565 | AH12: =IF(J12="Completed",AB12,IF(T12<0.05,MAX(Z12,AB12),AB12/T12)) -> 591184.31 | AI12: =MAX(0,AH12-AB12) -> 342886.9 | AJ12: =Z12-AH12 -> 77515.69 | AK12: =IF(Z12=0,0,AB12/Z12) -> 0.37131361 | AL12: =W12-AH12 -> 458815.69 | AM12: =IF(W12=0,0,AL12/W12) -> 0.43696732 | AN12: =AM12-S12 -> 0.016967324 | AO12: =Q12-P12 -> 0 | AP12: =IF(J12="Completed",0,MAX(0,Q12-AsOfDate)) -> 231 | AQ12: =SUMIFS(Invoices!$F$2:$F$2000,Invoices!$B$2:$B$2000,A12) -> 415431.38 | AR12: =SUMIFS(Invoices!$F$2:$F$2000,Invoices!$B$2:$B$2000,A12,Invoices!$K$2:$K$2000,"Paid") -> 263059.05 | AS12: =T12*W12-AQ12 -> 25568.62 | AT12: =COUNTIFS(RAID!$B$2:$B$2000,A12,RAID!$C$2:$C$2000,"Risk",RAID!$J$2:$J$2000,"<>Closed") -> 1 | AU12: =COUNTIFS(RAID!$B$2:$B$2000,A12,RAID!$C$2:$C$2000,"Issue",RAID!$J$2:$J$2000,"<>Closed") -> 0 | AV12: =SUMIFS(RAID!$Q$2:$Q$2000,RAID!$B$2:$B$2000,A12,RAID!$J$2:$J$2000,"<>Closed") -> 25200 | AW12: =COUNTIFS(ChangeRequests!$B$2:$B$1000,A12,ChangeRequests!$P$2:$P$1000,"Yes") -> 0 | AX12: =COUNTIFS(Allocations!$B$2:$B$2000,A12,Allocations!$K$2:$K$2000,"Yes") -> 6 | AY12: =IF(COUNTIFS(Milestones!$B$2:$B$2000,A12,Milestones!$L$2:$L$2000,"<>Completed")=0,"",_xlfn.MINIFS(Milestones!$F$2:$F$2000,Milestones!$B$2:$B$2000,A12,Milestones!$L$2:$L$2000,"<>Completed")) -> 46374 | AZ12: =IF(J12="Planned","N/A",IF(AK12-T12>RAG_CostRed,"Red",IF(AK12-T12>RAG_CostAmber,"Amber","Green"))) -> Green | BA12: =IF(J12="Planned","N/A",IF(AO12>RAG_ScheduleRedDays,"Red",IF(AO12>RAG_ScheduleAmberDays,"Amber","Green"))) -> Green | BB12: =IF(J12="Planned","N/A",IF(AM12<MarginFloor,"Red",IF(AM12<S12-MarginTolerance,"Amber","Green"))) -> Green | BC12: =IF(J12="Planned","N/A",IF(OR(AZ12="Red",BA12="Red",BB12="Red"),"Red",IF(OR(AZ12="Amber",BA12="Amber",BB12="Amber"),"Amber","Green"))) -> Green | BD12: =IF(J12="Planned","",MAX(0,ROUND(100-MAX(0,AK12-T12)*150-MAX(0,AO12)*0.4-MAX(0,S12-AM12)*150,0))) -> 100
A13: P-1012 | B13: Grid Analytics Dashboard | C13: C-112 | D13: =IFERROR(INDEX(Clients!$B$2:$B$200,MATCH(C13,Clients!$A$2:$A$200,0)),"Unknown client") -> Lakeshore Energy | E13: Data & AI | F13: Industrial | G13: E-0010 | H13: =IFERROR(INDEX(Resources!$B$2:$B$500,MATCH(G13,Resources!$A$2:$A$500,0)),"") -> Arjun Baptiste | I13: Alan Fortier | J13: Active | K13: Execute | L13: P2 | M13: Fixed Price | N13: 5 | O13: 46174 | P13: 46374 | Q13: 46374 | R13: 510000 | S13: 0.32 | T13: 0.44 | U13: 46271 | V13: =SUMIFS(ChangeRequests!$H$2:$H$1000,ChangeRequests!$B$2:$B$1000,A13,ChangeRequests!$G$2:$G$1000,"Approved") -> 0 | W13: =R13+V13 -> 510000 | X13: =SUMIFS(Budget!$E$2:$E$2000,Budget!$B$2:$B$2000,A13) -> 346500 | Y13: =SUMIFS(ChangeRequests!$I$2:$I$1000,ChangeRequests!$B$2:$B$1000,A13,ChangeRequests!$G$2:$G$1000,"Approved") -> 0 | Z13: =X13+Y13 -> 346500 | AA13: =SUMIFS(Actuals!$H$2:$H$6000,Actuals!$C$2:$C$6000,A13) -> 1289.2 | AB13: =SUMIFS(Actuals!$J$2:$J$6000,Actuals!$C$2:$C$6000,A13) -> 142260.82 | AC13: =IF(J13="Completed",1,IF(AsOfDate<=O13,0,MIN(1,(AsOfDate-O13)/MAX(1,P13-O13)))) -> 0.51 | AD13: =T13*Z13 -> 152460 | AE13: =AC13*Z13 -> 176715 | AF13: =IF(AB13=0,1,AD13/AB13) -> 1.0716935 | AG13: =IF(AE13=0,1,AD13/AE13) -> 0.8627451 | AH13: =IF(J13="Completed",AB13,IF(T13<0.05,MAX(Z13,AB13),AB13/T13)) -> 323320.05 | AI13: =MAX(0,AH13-AB13) -> 181059.23 | AJ13: =Z13-AH13 -> 23179.955 | AK13: =IF(Z13=0,0,AB13/Z13) -> 0.41056514 | AL13: =W13-AH13 -> 186679.95 | AM13: =IF(W13=0,0,AL13/W13) -> 0.36603913 | AN13: =AM13-S13 -> 0.046039127 | AO13: =Q13-P13 -> 0 | AP13: =IF(J13="Completed",0,MAX(0,Q13-AsOfDate)) -> 98 | AQ13: =SUMIFS(Invoices!$F$2:$F$2000,Invoices!$B$2:$B$2000,A13) -> 153000 | AR13: =SUMIFS(Invoices!$F$2:$F$2000,Invoices!$B$2:$B$2000,A13,Invoices!$K$2:$K$2000,"Paid") -> 153000 | AS13: =T13*W13-AQ13 -> 71400 | AT13: =COUNTIFS(RAID!$B$2:$B$2000,A13,RAID!$C$2:$C$2000,"Risk",RAID!$J$2:$J$2000,"<>Closed") -> 0 | AU13: =COUNTIFS(RAID!$B$2:$B$2000,A13,RAID!$C$2:$C$2000,"Issue",RAID!$J$2:$J$2000,"<>Closed") -> 0 | AV13: =SUMIFS(RAID!$Q$2:$Q$2000,RAID!$B$2:$B$2000,A13,RAID!$J$2:$J$2000,"<>Closed") -> 0 | AW13: =COUNTIFS(ChangeRequests!$B$2:$B$1000,A13,ChangeRequests!$P$2:$P$1000,"Yes") -> 0 | AX13: =COUNTIFS(Allocations!$B$2:$B$2000,A13,Allocations!$K$2:$K$2000,"Yes") -> 6 | AY13: =IF(COUNTIFS(Milestones!$B$2:$B$2000,A13,Milestones!$L$2:$L$2000,"<>Completed")=0,"",_xlfn.MINIFS(Milestones!$F$2:$F$2000,Milestones!$B$2:$B$2000,A13,Milestones!$L$2:$L$2000,"<>Completed")) -> 46314 | AZ13: =IF(J13="Planned","N/A",IF(AK13-T13>RAG_CostRed,"Red",IF(AK13-T13>RAG_CostAmber,"Amber","Green"))) -> Green | BA13: =IF(J13="Planned","N/A",IF(AO13>RAG_ScheduleRedDays,"Red",IF(AO13>RAG_ScheduleAmberDays,"Amber","Green"))) -> Green | BB13: =IF(J13="Planned","N/A",IF(AM13<MarginFloor,"Red",IF(AM13<S13-MarginTolerance,"Amber","Green"))) -> Green | BC13: =IF(J13="Planned","N/A",IF(OR(AZ13="Red",BA13="Red",BB13="Red"),"Red",IF(OR(AZ13="Amber",BA13="Amber",BB13="Amber"),"Amber","Green"))) -> Green | BD13: =IF(J13="Planned","",MAX(0,ROUND(100-MAX(0,AK13-T13)*150-MAX(0,AO13)*0.4-MAX(0,S13-AM13)*150,0))) -> 100
... A25: P-1024 | B25: Municipal Asset Management | C25: C-110 | D25: =IFERROR(INDEX(Clients!$B$2:$B$200,MATCH(C25,Clients!$A$2:$A$200,0)),"Unknown client") -> Bluewater Municipal Services | E25: Digital Transformation | F25: Health & Public | G25: E-0005 | H25: =IFERROR(INDEX(Resources!$B$2:$B$500,MATCH(G25,Resources!$A$2:$A$500,0)),"") -> Mei Fraser | I25: Mayor's Office - D. Price | J25: Planned | K25: Initiate | L25: P2 | M25: Fixed Price | N25: 9 | O25: 46398 | P25: 46689 | Q25: 46689 | R25: 1090000 | S25: 0.36 | T25: 0 | U25: 46252 | V25: =SUMIFS(ChangeRequests!$H$2:$H$1000,ChangeRequests!$B$2:$B$1000,A25,ChangeRequests!$G$2:$G$1000,"Approved") -> 0 | W25: =R25+V25 -> 1090000 | X25: =SUMIFS(Budget!$E$2:$E$2000,Budget!$B$2:$B$2000,A25) -> 698500 | Y25: =SUMIFS(ChangeRequests!$I$2:$I$1000,ChangeRequests!$B$2:$B$1000,A25,ChangeRequests!$G$2:$G$1000,"Approved") -> 0 | Z25: =X25+Y25 -> 698500 | AA25: =SUMIFS(Actuals!$H$2:$H$6000,Actuals!$C$2:$C$6000,A25) -> 0 | AB25: =SUMIFS(Actuals!$J$2:$J$6000,Actuals!$C$2:$C$6000,A25) -> 0 | AC25: =IF(J25="Completed",1,IF(AsOfDate<=O25,0,MIN(1,(AsOfDate-O25)/MAX(1,P25-O25)))) -> 0 | AD25: =T25*Z25 -> 0 | AE25: =AC25*Z25 -> 0 | AF25: =IF(AB25=0,1,AD25/AB25) -> 1 | AG25: =IF(AE25=0,1,AD25/AE25) -> 1 | AH25: =IF(J25="Completed",AB25,IF(T25<0.05,MAX(Z25,AB25),AB25/T25)) -> 698500 | AI25: =MAX(0,AH25-AB25) -> 698500 | AJ25: =Z25-AH25 -> 0 | AK25: =IF(Z25=0,0,AB25/Z25) -> 0 | AL25: =W25-AH25 -> 391500 | AM25: =IF(W25=0,0,AL25/W25) -> 0.35917431 | AN25: =AM25-S25 -> -0.00082568807 | AO25: =Q25-P25 -> 0 | AP25: =IF(J25="Completed",0,MAX(0,Q25-AsOfDate)) -> 413 | AQ25: =SUMIFS(Invoices!$F$2:$F$2000,Invoices!$B$2:$B$2000,A25) -> 0 | AR25: =SUMIFS(Invoices!$F$2:$F$2000,Invoices!$B$2:$B$2000,A25,Invoices!$K$2:$K$2000,"Paid") -> 0 | AS25: =T25*W25-AQ25 -> 0 | AT25: =COUNTIFS(RAID!$B$2:$B$2000,A25,RAID!$C$2:$C$2000,"Risk",RAID!$J$2:$J$2000,"<>Closed") -> 0 | AU25: =COUNTIFS(RAID!$B$2:$B$2000,A25,RAID!$C$2:$C$2000,"Issue",RAID!$J$2:$J$2000,"<>Closed") -> 0 | AV25: =SUMIFS(RAID!$Q$2:$Q$2000,RAID!$B$2:$B$2000,A25,RAID!$J$2:$J$2000,"<>Closed") -> 0 | AW25: =COUNTIFS(ChangeRequests!$B$2:$B$1000,A25,ChangeRequests!$P$2:$P$1000,"Yes") -> 0 | AX25: =COUNTIFS(Allocations!$B$2:$B$2000,A25,Allocations!$K$2:$K$2000,"Yes") -> 0 | AY25: =IF(COUNTIFS(Milestones!$B$2:$B$2000,A25,Milestones!$L$2:$L$2000,"<>Completed")=0,"",_xlfn.MINIFS(Milestones!$F$2:$F$2000,Milestones!$B$2:$B$2000,A25,Milestones!$L$2:$L$2000,"<>Completed")) -> 46427 | AZ25: =IF(J25="Planned","N/A",IF(AK25-T25>RAG_CostRed,"Red",IF(AK25-T25>RAG_CostAmber,"Amber","Green"))) -> N/A | BA25: =IF(J25="Planned","N/A",IF(AO25>RAG_ScheduleRedDays,"Red",IF(AO25>RAG_ScheduleAmberDays,"Amber","Green"))) -> N/A | BB25: =IF(J25="Planned","N/A",IF(AM25<MarginFloor,"Red",IF(AM25<S25-MarginTolerance,"Amber","Green"))) -> N/A | BC25: =IF(J25="Planned","N/A",IF(OR(AZ25="Red",BA25="Red",BB25="Red"),"Red",IF(OR(AZ25="Amber",BA25="Amber",BB25="Amber"),"Amber","Green"))) -> N/A | BD25: =IF(J25="Planned","",MAX(0,ROUND(100-MAX(0,AK25-T25)*150-MAX(0,AO25)*0.4-MAX(0,S25-AM25)*150,0)))

Sheet Resources
A1: EmployeeID | B1: FullName | C1: Role | D1: Department | E1: Level | F1: Location | G1: EmploymentType | H1: CostRateHr | I1: BillRateHr | J1: WeeklyCapacityHrs | K1: ManagerID | L1: ManagerName | M1: PrimarySkill | N1: StartDate | O1: CurrentAllocationPct | P1: ActiveAssignments | Q1: AvailableHrsPerWeek | R1: UtilizationStatus | S1: HoursLoggedYTD | T1: BillableHoursYTD | U1: BillableRatioYTD
A2: E-0001 | B2: Helena Marsh | C2: Director, Delivery | D2: PMO | E2: L7 | F2: Toronto | G2: FTE | H2: 135 | I2: 0 | J2: 0 | L2: =IFERROR(INDEX(Resources!$B$2:$B$500,MATCH(K2,Resources!$A$2:$A$500,0)),"") | M2: Portfolio governance | N2: 42436 | O2: =SUMIFS(Allocations!$J$2:$J$2000,Allocations!$D$2:$D$2000,A2,Allocations!$H$2:$H$2000,"<="&AsOfDate,Allocations!$I$2:$I$2000,">="&AsOfDate) -> 0 | P2: =COUNTIFS(Allocations!$D$2:$D$2000,A2,Allocations!$H$2:$H$2000,"<="&AsOfDate,Allocations!$I$2:$I$2000,">="&AsOfDate) -> 0 | Q2: =ROUND(J2*MAX(0,1-O2),1) -> 0 | R2: =IF(J2=0,"Non-assignable",IF(O2>OverallocationThreshold,"Overallocated",IF(O2<UnderutilizationThreshold,"Under-utilized","Healthy"))) -> Non-assignable | S2: =SUMIFS(Actuals!$H$2:$H$6000,Actuals!$E$2:$E$6000,A2,Actuals!$B$2:$B$6000,">="&DATE(YEAR(AsOfDate),1,1)) -> 0 | T2: =SUMIFS(Actuals!$H$2:$H$6000,Actuals!$E$2:$E$6000,A2,Actuals!$B$2:$B$6000,">="&DATE(YEAR(AsOfDate),1,1),Actuals!$I$2:$I$6000,"Yes") -> 0 | U2: =IF(S2=0,0,T2/S2) -> 0
A3: E-0002 | B3: Gordon Achebe | C3: Director, Engineering | D3: Engineering | E3: L7 | F3: Toronto | G3: FTE | H3: 140 | I3: 0 | J3: 0 | L3: =IFERROR(INDEX(Resources!$B$2:$B$500,MATCH(K3,Resources!$A$2:$A$500,0)),"") | M3: Engineering leadership | N3: 42989 | O3: =SUMIFS(Allocations!$J$2:$J$2000,Allocations!$D$2:$D$2000,A3,Allocations!$H$2:$H$2000,"<="&AsOfDate,Allocations!$I$2:$I$2000,">="&AsOfDate) -> 0 | P3: =COUNTIFS(Allocations!$D$2:$D$2000,A3,Allocations!$H$2:$H$2000,"<="&AsOfDate,Allocations!$I$2:$I$2000,">="&AsOfDate) -> 0 | Q3: =ROUND(J3*MAX(0,1-O3),1) -> 0 | R3: =IF(J3=0,"Non-assignable",IF(O3>OverallocationThreshold,"Overallocated",IF(O3<UnderutilizationThreshold,"Under-utilized","Healthy"))) -> Non-assignable | S3: =SUMIFS(Actuals!$H$2:$H$6000,Actuals!$E$2:$E$6000,A3,Actuals!$B$2:$B$6000,">="&DATE(YEAR(AsOfDate),1,1)) -> 0 | T3: =SUMIFS(Actuals!$H$2:$H$6000,Actuals!$E$2:$E$6000,A3,Actuals!$B$2:$B$6000,">="&DATE(YEAR(AsOfDate),1,1),Actuals!$I$2:$I$6000,"Yes") -> 0 | U3: =IF(S3=0,0,T3/S3) -> 0
A4: E-0003 | B4: Aisha Tremblay | C4: Project Manager | D4: PMO | E4: L6 | F4: Toronto | G4: FTE | H4: 102.08 | I4: 205 | J4: 40 | K4: E-0001 | L4: =IFERROR(INDEX(Resources!$B$2:$B$500,MATCH(K4,Resources!$A$2:$A$500,0)),"") -> Helena Marsh | M4: Stakeholder mgmt | N4: 44614 | O4: =SUMIFS(Allocations!$J$2:$J$2000,Allocations!$D$2:$D$2000,A4,Allocations!$H$2:$H$2000,"<="&AsOfDate,Allocations!$I$2:$I$2000,">="&AsOfDate) -> 0.75 | P4: =COUNTIFS(Allocations!$D$2:$D$2000,A4,Allocations!$H$2:$H$2000,"<="&AsOfDate,Allocations!$I$2:$I$2000,">="&AsOfDate) -> 2 | Q4: =ROUND(J4*MAX(0,1-O4),1) -> 10 | R4: =IF(J4=0,"Non-assignable",IF(O4>OverallocationThreshold,"Overallocated",IF(O4<UnderutilizationThreshold,"Under-utilized","Healthy"))) -> Healthy | S4: =SUMIFS(Actuals!$H$2:$H$6000,Actuals!$E$2:$E$6000,A4,Actuals!$B$2:$B$6000,">="&DATE(YEAR(AsOfDate),1,1)) -> 876.7 | T4: =SUMIFS(Actuals!$H$2:$H$6000,Actuals!$E$2:$E$6000,A4,Actuals!$B$2:$B$6000,">="&DATE(YEAR(AsOfDate),1,1),Actuals!$I$2:$I$6000,"Yes") -> 673.1 | U4: =IF(S4=0,0,T4/S4) -> 0.76776548
A5: E-0004 | B5: Liam Roy | C5: Project Manager | D5: PMO | E5: L6 | F5: Ottawa | G5: FTE | H5: 102.08 | I5: 205 | J5: 40 | K5: E-0003 | L5: =IFERROR(INDEX(Resources!$B$2:$B$500,MATCH(K5,Resources!$A$2:$A$500,0)),"") -> Aisha Tremblay | M5: Stakeholder mgmt | N5: 43033 | O5: =SUMIFS(Allocations!$J$2:$J$2000,Allocations!$D$2:$D$2000,A5,Allocations!$H$2:$H$2000,"<="&AsOfDate,Allocations!$I$2:$I$2000,">="&AsOfDate) -> 0.75 | P5: =COUNTIFS(Allocations!$D$2:$D$2000,A5,Allocations!$H$2:$H$2000,"<="&AsOfDate,Allocations!$I$2:$I$2000,">="&AsOfDate) -> 2 | Q5: =ROUND(J5*MAX(0,1-O5),1) -> 10 | R5: =IF(J5=0,"Non-assignable",IF(O5>OverallocationThreshold,"Overallocated",IF(O5<UnderutilizationThreshold,"Under-utilized","Healthy"))) -> Healthy | S5: =SUMIFS(Actuals!$H$2:$H$6000,Actuals!$E$2:$E$6000,A5,Actuals!$B$2:$B$6000,">="&DATE(YEAR(AsOfDate),1,1)) -> 1358.1 | T5: =SUMIFS(Actuals!$H$2:$H$6000,Actuals!$E$2:$E$6000,A5,Actuals!$B$2:$B$6000,">="&DATE(YEAR(AsOfDate),1,1),Actuals!$I$2:$I$6000,"Yes") -> 1358.1 | U5: =IF(S5=0,0,T5/S5) -> 1
A6: E-0005 | B6: Mei Fraser | C6: Project Manager | D6: PMO | E6: L2 | F6: Remote | G6: FTE | H6: 74.8 | I6: 150 | J6: 40 | K6: E-0003 | L6: =IFERROR(INDEX(Resources!$B$2:$B$500,MATCH(K6,Resources!$A$2:$A$500,0)),"") -> Aisha Tremblay | M6: Stakeholder mgmt | N6: 45256 | O6: =SUMIFS(Allocations!$J$2:$J$2000,Allocations!$D$2:$D$2000,A6,Allocations!$H$2:$H$2000,"<="&AsOfDate,Allocations!$I$2:$I$2000,">="&AsOfDate) -> 1.25 | P6: =COUNTIFS(Allocations!$D$2:$D$2000,A6,Allocations!$H$2:$H$2000,"<="&AsOfDate,Allocations!$I$2:$I$2000,">="&AsOfDate) -> 3 | Q6: =ROUND(J6*MAX(0,1-O6),1) -> 0 | R6: =IF(J6=0,"Non-assignable",IF(O6>OverallocationThreshold,"Overallocated",IF(O6<UnderutilizationThreshold,"Under-utilized","Healthy"))) -> Overallocated | S6: =SUMIFS(Actuals!$H$2:$H$6000,Actuals!$E$2:$E$6000,A6,Actuals!$B$2:$B$6000,">="&DATE(YEAR(AsOfDate),1,1)) -> 1621.1 | T6: =SUMIFS(Actuals!$H$2:$H$6000,Actuals!$E$2:$E$6000,A6,Actuals!$B$2:$B$6000,">="&DATE(YEAR(AsOfDate),1,1),Actuals!$I$2:$I$6000,"Yes") -> 1248.4 | U6: =IF(S6=0,0,T6/S6) -> 0.77009438
A7: E-0006 | B7: Noah Rahimi | C7: Project Manager | D7: PMO | E7: L4 | F7: Vancouver | G7: FTE | H7: 88 | I7: 175 | J7: 40 | K7: E-0003 | L7: =IFERROR(INDEX(Resources!$B$2:$B$500,MATCH(K7,Resources!$A$2:$A$500,0)),"") -> Aisha Tremblay | M7: Stakeholder mgmt | N7: 44045 | O7: =SUMIFS(Allocations!$J$2:$J$2000,Allocations!$D$2:$D$2000,A7,Allocations!$H$2:$H$2000,"<="&AsOfDate,Allocations!$I$2:$I$2000,">="&AsOfDate) -> 0.5 | P7: =COUNTIFS(Allocations!$D$2:$D$2000,A7,Allocations!$H$2:$H$2000,"<="&AsOfDate,Allocations!$I$2:$I$2000,">="&AsOfDate) -> 2 | Q7: =ROUND(J7*MAX(0,1-O7),1) -> 20 | R7: =IF(J7=0,"Non-assignable",IF(O7>OverallocationThreshold,"Overallocated",IF(O7<UnderutilizationThreshold,"Under-utilized","Healthy"))) -> Under-utilized | S7: =SUMIFS(Actuals!$H$2:$H$6000,Actuals!$E$2:$E$6000,A7,Actuals!$B$2:$B$6000,">="&DATE(YEAR(AsOfDate),1,1)) -> 1000.5 | T7: =SUMIFS(Actuals!$H$2:$H$6000,Actuals!$E$2:$E$6000,A7,Actuals!$B$2:$B$6000,">="&DATE(YEAR(AsOfDate),1,1),Actuals!$I$2:$I$6000,"Yes") -> 303.8 | U7: =IF(S7=0,0,T7/S7) -> 0.30364818
A8: E-0007 | B8: Fatima Cohen | C8: Project Manager | D8: PMO | E8: L6 | F8: Toronto | G8: FTE | H8: 102.08 | I8: 205 | J8: 40 | K8: E-0003 | L8: =IFERROR(INDEX(Resources!$B$2:$B$500,MATCH(K8,Resources!$A$2:$A$500,0)),"") -> Aisha Tremblay | M8: PRINCE2 | N8: 43021 | O8: =SUMIFS(Allocations!$J$2:$J$2000,Allocations!$D$2:$D$2000,A8,Allocations!$H$2:$H$2000,"<="&AsOfDate,Allocations!$I$2:$I$2000,">="&AsOfDate) -> 0.75 | P8: =COUNTIFS(Allocations!$D$2:$D$2000,A8,Allocations!$H$2:$H$2000,"<="&AsOfDate,Allocations!$I$2:$I$2000,">="&AsOfDate) -> 2 | Q8: =ROUND(J8*MAX(0,1-O8),1) -> 10 | R8: =IF(J8=0,"Non-assignable",IF(O8>OverallocationThreshold,"Overallocated",IF(O8<UnderutilizationThreshold,"Under-utilized","Healthy"))) -> Healthy | S8: =SUMIFS(Actuals!$H$2:$H$6000,Actuals!$E$2:$E$6000,A8,Actuals!$B$2:$B$6000,">="&DATE(YEAR(AsOfDate),1,1)) -> 1229.3 | T8: =SUMIFS(Actuals!$H$2:$H$6000,Actuals!$E$2:$E$6000,A8,Actuals!$B$2:$B$6000,">="&DATE(YEAR(AsOfDate),1,1),Actuals!$I$2:$I$6000,"Yes") -> 1229.3 | U8: =IF(S8=0,0,T8/S8) -> 1
A9: E-0008 | B9: Ethan Park | C9: Project Manager | D9: PMO | E9: L5 | F9: Toronto | G9: FTE | H9: 95.04 | I9: 190 | J9: 40 | K9: E-0003 | L9: =IFERROR(INDEX(Resources!$B$2:$B$500,MATCH(K9,Resources!$A$2:$A$500,0)),"") -> Aisha Tremblay | M9: Agile delivery | N9: 45041 | O9: =SUMIFS(Allocations!$J$2:$J$2000,Allocations!$D$2:$D$2000,A9,Allocations!$H$2:$H$2000,"<="&AsOfDate,Allocations!$I$2:$I$2000,">="&AsOfDate) -> 0.75 | P9: =COUNTIFS(Allocations!$D$2:$D$2000,A9,Allocations!$H$2:$H$2000,"<="&AsOfDate,Allocations!$I$2:$I$2000,">="&AsOfDate) -> 2 | Q9: =ROUND(J9*MAX(0,1-O9),1) -> 10 | R9: =IF(J9=0,"Non-assignable",IF(O9>OverallocationThreshold,"Overallocated",IF(O9<UnderutilizationThreshold,"Under-utilized","Healthy"))) -> Healthy | S9: =SUMIFS(Actuals!$H$2:$H$6000,Actuals!$E$2:$E$6000,A9,Actuals!$B$2:$B$6000,">="&DATE(YEAR(AsOfDate),1,1)) -> 766.6 | T9: =SUMIFS(Actuals!$H$2:$H$6000,Actuals!$E$2:$E$6000,A9,Actuals!$B$2:$B$6000,">="&DATE(YEAR(AsOfDate),1,1),Actuals!$I$2:$I$6000,"Yes") -> 766.6 | U9: =IF(S9=0,0,T9/S9) -> 1
A10: E-0009 | B10: Olivia Silva | C10: Project Manager | D10: PMO | E10: L2 | F10: Remote | G10: FTE | H10: 74.8 | I10: 150 | J10: 40 | K10: E-0003 | L10: =IFERROR(INDEX(Resources!$B$2:$B$500,MATCH(K10,Resources!$A$2:$A$500,0)),"") -> Aisha Tremblay | M10: Agile delivery | N10: 45038 | O10: =SUMIFS(Allocations!$J$2:$J$2000,Allocations!$D$2:$D$2000,A10,Allocations!$H$2:$H$2000,"<="&AsOfDate,Allocations!$I$2:$I$2000,">="&AsOfDate) -> 1 | P10: =COUNTIFS(Allocations!$D$2:$D$2000,A10,Allocations!$H$2:$H$2000,"<="&AsOfDate,Allocations!$I$2:$I$2000,">="&AsOfDate) -> 2 | Q10: =ROUND(J10*MAX(0,1-O10),1) -> 0 | R10: =IF(J10=0,"Non-assignable",IF(O10>OverallocationThreshold,"Overallocated",IF(O10<UnderutilizationThreshold,"Under-utilized","Healthy"))) -> Healthy | S10: =SUMIFS(Actuals!$H$2:$H$6000,Actuals!$E$2:$E$6000,A10,Actuals!$B$2:$B$6000,">="&DATE(YEAR(AsOfDate),1,1)) -> 1444.7 | T10: =SUMIFS(Actuals!$H$2:$H$6000,Actuals!$E$2:$E$6000,A10,Actuals!$B$2:$B$6000,">="&DATE(YEAR(AsOfDate),1,1),Actuals!$I$2:$I$6000,"Yes") -> 1444.7 | U10: =IF(S10=0,0,T10/S10) -> 1
A11: E-0010 | B11: Arjun Baptiste | C11: Project Manager | D11: PMO | E11: L4 | F11: Toronto | G11: FTE | H11: 88 | I11: 175 | J11: 40 | K11: E-0003 | L11: =IFERROR(INDEX(Resources!$B$2:$B$500,MATCH(K11,Resources!$A$2:$A$500,0)),"") -> Aisha Tremblay | M11: Agile delivery | N11: 44887 | O11: =SUMIFS(Allocations!$J$2:$J$2000,Allocations!$D$2:$D$2000,A11,Allocations!$H$2:$H$2000,"<="&AsOfDate,Allocations!$I$2:$I$2000,">="&AsOfDate) -> 0.75 | P11: =COUNTIFS(Allocations!$D$2:$D$2000,A11,Allocations!$H$2:$H$2000,"<="&AsOfDate,Allocations!$I$2:$I$2000,">="&AsOfDate) -> 2 | Q11: =ROUND(J11*MAX(0,1-O11),1) -> 10 | R11: =IF(J11=0,"Non-assignable",IF(O11>OverallocationThreshold,"Overallocated",IF(O11<UnderutilizationThreshold,"Under-utilized","Healthy"))) -> Healthy | S11: =SUMIFS(Actuals!$H$2:$H$6000,Actuals!$E$2:$E$6000,A11,Actuals!$B$2:$B$6000,">="&DATE(YEAR(AsOfDate),1,1)) -> 1256.1 | T11: =SUMIFS(Actuals!$H$2:$H$6000,Actuals!$E$2:$E$6000,A11,Actuals!$B$2:$B$6000,">="&DATE(YEAR(AsOfDate),1,1),Actuals!$I$2:$I$6000,"Yes") -> 838.4 | U11: =IF(S11=0,0,T11/S11) -> 0.66746278
A12: E-0011 | B12: Chloe Reyes | C12: Solution Architect | D12: Architecture | E12: L6 | F12: Mississauga | G12: FTE | H12: 129.92 | I12: 260 | J12: 40 | K12: E-0002 | L12: =IFERROR(INDEX(Resources!$B$2:$B$500,MATCH(K12,Resources!$A$2:$A$500,0)),"") -> Gordon Achebe | M12: Salesforce | N12: 45635 | O12: =SUMIFS(Allocations!$J$2:$J$2000,Allocations!$D$2:$D$2000,A12,Allocations!$H$2:$H$2000,"<="&AsOfDate,Allocations!$I$2:$I$2000,">="&AsOfDate) -> 0.25 | P12: =COUNTIFS(Allocations!$D$2:$D$2000,A12,Allocations!$H$2:$H$2000,"<="&AsOfDate,Allocations!$I$2:$I$2000,">="&AsOfDate) -> 1 | Q12: =ROUND(J12*MAX(0,1-O12),1) -> 30 | R12: =IF(J12=0,"Non-assignable",IF(O12>OverallocationThreshold,"Overallocated",IF(O12<UnderutilizationThreshold,"Under-utilized","Healthy"))) -> Under-utilized | S12: =SUMIFS(Actuals!$H$2:$H$6000,Actuals!$E$2:$E$6000,A12,Actuals!$B$2:$B$6000,">="&DATE(YEAR(AsOfDate),1,1)) -> 583.6 | T12: =SUMIFS(Actuals!$H$2:$H$6000,Actuals!$E$2:$E$6000,A12,Actuals!$B$2:$B$6000,">="&DATE(YEAR(AsOfDate),1,1),Actuals!$I$2:$I$6000,"Yes") -> 583.6 | U12: =IF(S12=0,0,T12/S12) -> 1
A13: E-0012 | B13: Mateo Bianchi | C13: Solution Architect | D13: Architecture | E13: L6 | F13: Montreal | G13: FTE | H13: 129.92 | I13: 260 | J13: 40 | K13: E-0011 | L13: =IFERROR(INDEX(Resources!$B$2:$B$500,MATCH(K13,Resources!$A$2:$A$500,0)),"") -> Chloe Reyes | M13: Salesforce | N13: 45941 | O13: =SUMIFS(Allocations!$J$2:$J$2000,Allocations!$D$2:$D$2000,A13,Allocations!$H$2:$H$2000,"<="&AsOfDate,Allocations!$I$2:$I$2000,">="&AsOfDate) -> 0.25 | P13: =COUNTIFS(Allocations!$D$2:$D$2000,A13,Allocations!$H$2:$H$2000,"<="&AsOfDate,Allocations!$I$2:$I$2000,">="&AsOfDate) -> 1 | Q13: =ROUND(J13*MAX(0,1-O13),1) -> 30 | R13: =IF(J13=0,"Non-assignable",IF(O13>OverallocationThreshold,"Overallocated",IF(O13<UnderutilizationThreshold,"Under-utilized","Healthy"))) -> Under-utilized | S13: =SUMIFS(Actuals!$H$2:$H$6000,Actuals!$E$2:$E$6000,A13,Actuals!$B$2:$B$6000,">="&DATE(YEAR(AsOfDate),1,1)) -> 711 | T13: =SUMIFS(Actuals!$H$2:$H$6000,Actuals!$E$2:$E$6000,A13,Actuals!$B$2:$B$6000,">="&DATE(YEAR(AsOfDate),1,1),Actuals!$I$2:$I$6000,"Yes") -> 711 | U13: =IF(S13=0,0,T13/S13) -> 1
A14: E-0013 | B14: Hana Clarke | C14: Solution Architect | D14: Architecture | E14: L5 | F14: Mississauga | G14: FTE | H14: 120.96 | I14: 245 | J14: 40 | K14: E-0011 | L14: =IFERROR(INDEX(Resources!$B$2:$B$500,MATCH(K14,Resources!$A$2:$A$500,0)),"") -> Chloe Reyes | M14: Integration | N14: 44238 | O14: =SUMIFS(Allocations!$J$2:$J$2000,Allocations!$D$2:$D$2000,A14,Allocations!$H$2:$H$2000,"<="&AsOfDate,Allocations!$I$2:$I$2000,">="&AsOfDate) -> 0.5 | P14: =COUNTIFS(Allocations!$D$2:$D$2000,A14,Allocations!$H$2:$H$2000,"<="&AsOfDate,Allocations!$I$2:$I$2000,">="&AsOfDate) -> 2 | Q14: =ROUND(J14*MAX(0,1-O14),1) -> 20 | R14: =IF(J14=0,"Non-assignable",IF(O14>OverallocationThreshold,"Overallocated",IF(O14<UnderutilizationThreshold,"Under-utilized","Healthy"))) -> Under-utilized | S14: =SUMIFS(Actuals!$H$2:$H$6000,Actuals!$E$2:$E$6000,A14,Actuals!$B$2:$B$6000,">="&DATE(YEAR(AsOfDate),1,1)) -> 790 | T14: =SUMIFS(Actuals!$H$2:$H$6000,Actuals!$E$2:$E$6000,A14,Actuals!$B$2:$B$6000,">="&DATE(YEAR(AsOfDate),1,1),Actuals!$I$2:$I$6000,"Yes") -> 790 | U14: =IF(S14=0,0,T14/S14) -> 1
A15: E-0014 | B15: Lucas Okoro | C15: Solution Architect | D15: Architecture | E15: L3 | F15: Remote | G15: FTE | H15: 104.16 | I15: 210 | J15: 40 | K15: E-0011 | L15: =IFERROR(INDEX(Resources!$B$2:$B$500,MATCH(K15,Resources!$A$2:$A$500,0)),"") -> Chloe Reyes | M15: Integration | N15: 44129 | O15: =SUMIFS(Allocations!$J$2:$J$2000,Allocations!$D$2:$D$2000,A15,Allocations!$H$2:$H$2000,"<="&AsOfDate,Allocations!$I$2:$I$2000,">="&AsOfDate) -> 0.5 | P15: =COUNTIFS(Allocations!$D$2:$D$2000,A15,Allocations!$H$2:$H$2000,"<="&AsOfDate,Allocations!$I$2:$I$2000,">="&AsOfDate) -> 1 | Q15: =ROUND(J15*MAX(0,1-O15),1) -> 20 | R15: =IF(J15=0,"Non-assignable",IF(O15>OverallocationThreshold,"Overallocated",IF(O15<UnderutilizationThreshold,"Under-utilized","Healthy"))) -> Under-utilized | S15: =SUMIFS(Actuals!$H$2:$H$6000,Actuals!$E$2:$E$6000,A15,Actuals!$B$2:$B$6000,">="&DATE(YEAR(AsOfDate),1,1)) -> 775.1 | T15: =SUMIFS(Actuals!$H$2:$H$6000,Actuals!$E$2:$E$6000,A15,Actuals!$B$2:$B$6000,">="&DATE(YEAR(AsOfDate),1,1),Actuals!$I$2:$I$6000,"Yes") -> 775.1 | U15: =IF(S15=0,0,T15/S15) -> 1
... A64: E-0063 | B64: Callum Dubois | C64: Change Manager | D64: Delivery | E64: L5 | F64: Toronto | G64: FTE | H64: 77.76 | I64: 160 | J64: 32 | K64: E-0015 | L64: =IFERROR(INDEX(Resources!$B$2:$B$500,MATCH(K64,Resources!$A$2:$A$500,0)),"") -> Zara Vasquez | M64: Comms | N64: 42665 | O64: =SUMIFS(Allocations!$J$2:$J$2000,Allocations!$D$2:$D$2000,A64,Allocations!$H$2:$H$2000,"<="&AsOfDate,Allocations!$I$2:$I$2000,">="&AsOfDate) -> 0.5 | P64: =COUNTIFS(Allocations!$D$2:$D$2000,A64,Allocations!$H$2:$H$2000,"<="&AsOfDate,Allocations!$I$2:$I$2000,">="&AsOfDate) -> 2 | Q64: =ROUND(J64*MAX(0,1-O64),1) -> 16 | R64: =IF(J64=0,"Non-assignable",IF(O64>OverallocationThreshold,"Overallocated",IF(O64<UnderutilizationThreshold,"Under-utilized","Healthy"))) -> Under-utilized | S64: =SUMIFS(Actuals!$H$2:$H$6000,Actuals!$E$2:$E$6000,A64,Actuals!$B$2:$B$6000,">="&DATE(YEAR(AsOfDate),1,1)) -> 307.1 | T64: =SUMIFS(Actuals!$H$2:$H$6000,Actuals!$E$2:$E$6000,A64,Actuals!$B$2:$B$6000,">="&DATE(YEAR(AsOfDate),1,1),Actuals!$I$2:$I$6000,"Yes") -> 307.1 | U64: =IF(S64=0,0,T64/S64) -> 1

Sheet Allocations
A1: AllocationID | B1: ProjectID | C1: ProjectName | D1: EmployeeID | E1: EmployeeName | F1: ProjectRole | G1: Billable | H1: StartDate | I1: EndDate | J1: AllocationPct | K1: IsActive | L1: WorkingDays | M1: PlannedHours | N1: CostRateHr | O1: BillRateHr | P1: PlannedCost | Q1: PlannedRevenue | R1: ActualHours | S1: HoursBurnPct
A2: A-0001 | B2: P-1001 | C2: =IFERROR(INDEX(Projects!$B$2:$B$500,MATCH(B2,Projects!$A$2:$A$500,0)),"") -> Patient Portal Modernization | D2: E-0003 | E2: =IFERROR(INDEX(Resources!$B$2:$B$500,MATCH(D2,Resources!$A$2:$A$500,0)),"") -> Aisha Tremblay | F2: Delivery Lead | G2: Yes | H2: 45964 | I2: 46329 | J2: 0.5 | K2: =IF(AND(AsOfDate>=H2,AsOfDate<=I2),"Yes","No") -> Yes | L2: =NETWORKDAYS(H2,I2) -> 262 | M2: =ROUND(L2*INDEX(Resources!$J$2:$J$500,MATCH(D2,Resources!$A$2:$A$500,0))/5*J2,1) -> 1048 | N2: =INDEX(Resources!$H$2:$H$500,MATCH(D2,Resources!$A$2:$A$500,0)) -> 102.08 | O2: =INDEX(Resources!$I$2:$I$500,MATCH(D2,Resources!$A$2:$A$500,0)) -> 205 | P2: =M2*N2 -> 106979.84 | Q2: =IF(G2="Yes",M2*O2,0) -> 214840 | R2: =SUMIFS(Actuals!$H$2:$H$6000,Actuals!$C$2:$C$6000,B2,Actuals!$E$2:$E$6000,D2) -> 829.1 | S2: =IF(M2=0,0,R2/M2) -> 0.79112595
A3: A-0002 | B3: P-1001 | C3: =IFERROR(INDEX(Projects!$B$2:$B$500,MATCH(B3,Projects!$A$2:$A$500,0)),"") -> Patient Portal Modernization | D3: E-0020 | E3: =IFERROR(INDEX(Resources!$B$2:$B$500,MATCH(D3,Resources!$A$2:$A$500,0)),"") -> Diego Costa | F3: UX Designer | G3: Yes | H3: 45964 | I3: 46162 | J3: 0.75 | K3: =IF(AND(AsOfDate>=H3,AsOfDate<=I3),"Yes","No") -> No | L3: =NETWORKDAYS(H3,I3) -> 143 | M3: =ROUND(L3*INDEX(Resources!$J$2:$J$500,MATCH(D3,Resources!$A$2:$A$500,0))/5*J3,1) -> 858 | N3: =INDEX(Resources!$H$2:$H$500,MATCH(D3,Resources!$A$2:$A$500,0)) -> 85.84 | O3: =INDEX(Resources!$I$2:$I$500,MATCH(D3,Resources!$A$2:$A$500,0)) -> 175 | P3: =M3*N3 -> 73650.72 | Q3: =IF(G3="Yes",M3*O3,0) -> 150150 | R3: =SUMIFS(Actuals!$H$2:$H$6000,Actuals!$C$2:$C$6000,B3,Actuals!$E$2:$E$6000,D3) -> 847.6 | S3: =IF(M3=0,0,R3/M3) -> 0.98787879
A4: A-0003 | B4: P-1001 | C4: =IFERROR(INDEX(Projects!$B$2:$B$500,MATCH(B4,Projects!$A$2:$A$500,0)),"") -> Patient Portal Modernization | D4: E-0023 | E4: =IFERROR(INDEX(Resources!$B$2:$B$500,MATCH(D4,Resources!$A$2:$A$500,0)),"") -> Yuki Wright | F4: Tech Lead | G4: Yes | H4: 45964 | I4: 46329 | J4: 0.75 | K4: =IF(AND(AsOfDate>=H4,AsOfDate<=I4),"Yes","No") -> Yes | L4: =NETWORKDAYS(H4,I4) -> 262 | M4: =ROUND(L4*INDEX(Resources!$J$2:$J$500,MATCH(D4,Resources!$A$2:$A$500,0))/5*J4,1) -> 1572 | N4: =INDEX(Resources!$H$2:$H$500,MATCH(D4,Resources!$A$2:$A$500,0)) -> 106.72 | O4: =INDEX(Resources!$I$2:$I$500,MATCH(D4,Resources!$A$2:$A$500,0)) -> 215 | P4: =M4*N4 -> 167763.84 | Q4: =IF(G4="Yes",M4*O4,0) -> 337980 | R4: =SUMIFS(Actuals!$H$2:$H$6000,Actuals!$C$2:$C$6000,B4,Actuals!$E$2:$E$6000,D4) -> 1262 | S4: =IF(M4=0,0,R4/M4) -> 0.80279898
A5: A-0004 | B5: P-1001 | C5: =IFERROR(INDEX(Projects!$B$2:$B$500,MATCH(B5,Projects!$A$2:$A$500,0)),"") -> Patient Portal Modernization | D5: E-0031 | E5: =IFERROR(INDEX(Resources!$B$2:$B$500,MATCH(D5,Resources!$A$2:$A$500,0)),"") -> Jin Alvarez | F5: Developer | G5: Yes | H5: 45964 | I5: 46329 | J5: 1 | K5: =IF(AND(AsOfDate>=H5,AsOfDate<=I5),"Yes","No") -> Yes | L5: =NETWORKDAYS(H5,I5) -> 262 | M5: =ROUND(L5*INDEX(Resources!$J$2:$J$500,MATCH(D5,Resources!$A$2:$A$500,0))/5*J5,1) -> 2096 | N5: =INDEX(Resources!$H$2:$H$500,MATCH(D5,Resources!$A$2:$A$500,0)) -> 74.24 | O5: =INDEX(Resources!$I$2:$I$500,MATCH(D5,Resources!$A$2:$A$500,0)) -> 150 | P5: =M5*N5 -> 155607.04 | Q5: =IF(G5="Yes",M5*O5,0) -> 314400 | R5: =SUMIFS(Actuals!$H$2:$H$6000,Actuals!$C$2:$C$6000,B5,Actuals!$E$2:$E$6000,D5) -> 1670 | S5: =IF(M5=0,0,R5/M5) -> 0.79675573
A6: A-0005 | B6: P-1001 | C6: =IFERROR(INDEX(Projects!$B$2:$B$500,MATCH(B6,Projects!$A$2:$A$500,0)),"") -> Patient Portal Modernization | D6: E-0042 | E6: =IFERROR(INDEX(Resources!$B$2:$B$500,MATCH(D6,Resources!$A$2:$A$500,0)),"") -> Nina Yilmaz | F6: QA Analyst | G6: Yes | H6: 46126 | I6: 46329 | J6: 0.5 | K6: =IF(AND(AsOfDate>=H6,AsOfDate<=I6),"Yes","No") -> Yes | L6: =NETWORKDAYS(H6,I6) -> 146 | M6: =ROUND(L6*INDEX(Resources!$J$2:$J$500,MATCH(D6,Resources!$A$2:$A$500,0))/5*J6,1) -> 584 | N6: =INDEX(Resources!$H$2:$H$500,MATCH(D6,Resources!$A$2:$A$500,0)) -> 64.96 | O6: =INDEX(Resources!$I$2:$I$500,MATCH(D6,Resources!$A$2:$A$500,0)) -> 135 | P6: =M6*N6 -> 37936.64 | Q6: =IF(G6="Yes",M6*O6,0) -> 78840 | R6: =SUMIFS(Actuals!$H$2:$H$6000,Actuals!$C$2:$C$6000,B6,Actuals!$E$2:$E$6000,D6) -> 413.1 | S6: =IF(M6=0,0,R6/M6) -> 0.70736301
A7: A-0006 | B7: P-1001 | C7: =IFERROR(INDEX(Projects!$B$2:$B$500,MATCH(B7,Projects!$A$2:$A$500,0)),"") -> Patient Portal Modernization | D7: E-0015 | E7: =IFERROR(INDEX(Resources!$B$2:$B$500,MATCH(D7,Resources!$A$2:$A$500,0)),"") -> Zara Vasquez | F7: Business Analyst | G7: Yes | H7: 45964 | I7: 46162 | J7: 0.5 | K7: =IF(AND(AsOfDate>=H7,AsOfDate<=I7),"Yes","No") -> No | L7: =NETWORKDAYS(H7,I7) -> 143 | M7: =ROUND(L7*INDEX(Resources!$J$2:$J$500,MATCH(D7,Resources!$A$2:$A$500,0))/5*J7,1) -> 572 | N7: =INDEX(Resources!$H$2:$H$500,MATCH(D7,Resources!$A$2:$A$500,0)) -> 78.88 | O7: =INDEX(Resources!$I$2:$I$500,MATCH(D7,Resources!$A$2:$A$500,0)) -> 160 | P7: =M7*N7 -> 45119.36 | Q7: =IF(G7="Yes",M7*O7,0) -> 91520 | R7: =SUMIFS(Actuals!$H$2:$H$6000,Actuals!$C$2:$C$6000,B7,Actuals!$E$2:$E$6000,D7) -> 563.2 | S7: =IF(M7=0,0,R7/M7) -> 0.98461538
A8: A-0007 | B8: P-1002 | C8: =IFERROR(INDEX(Projects!$B$2:$B$500,MATCH(B8,Projects!$A$2:$A$500,0)),"") -> Claims Automation Engine | D8: E-0004 | E8: =IFERROR(INDEX(Resources!$B$2:$B$500,MATCH(D8,Resources!$A$2:$A$500,0)),"") -> Liam Roy | F8: Delivery Lead | G8: Yes | H8: 46034 | I8: 46391 | J8: 0.25 | K8: =IF(AND(AsOfDate>=H8,AsOfDate<=I8),"Yes","No") -> Yes | L8: =NETWORKDAYS(H8,I8) -> 256 | M8: =ROUND(L8*INDEX(Resources!$J$2:$J$500,MATCH(D8,Resources!$A$2:$A$500,0))/5*J8,1) -> 512 | N8: =INDEX(Resources!$H$2:$H$500,MATCH(D8,Resources!$A$2:$A$500,0)) -> 102.08 | O8: =INDEX(Resources!$I$2:$I$500,MATCH(D8,Resources!$A$2:$A$500,0)) -> 205 | P8: =M8*N8 -> 52264.96 | Q8: =IF(G8="Yes",M8*O8,0) -> 104960 | R8: =SUMIFS(Actuals!$H$2:$H$6000,Actuals!$C$2:$C$6000,B8,Actuals!$E$2:$E$6000,D8) -> 463.3 | S8: =IF(M8=0,0,R8/M8) -> 0.90488281
A9: A-0008 | B9: P-1002 | C9: =IFERROR(INDEX(Projects!$B$2:$B$500,MATCH(B9,Projects!$A$2:$A$500,0)),"") -> Claims Automation Engine | D9: E-0016 | E9: =IFERROR(INDEX(Resources!$B$2:$B$500,MATCH(D9,Resources!$A$2:$A$500,0)),"") -> Owen Bennett | F9: Business Analyst | G9: Yes | H9: 46034 | I9: 46391 | J9: 0.5 | K9: =IF(AND(AsOfDate>=H9,AsOfDate<=I9),"Yes","No") -> Yes | L9: =NETWORKDAYS(H9,I9) -> 256 | M9: =ROUND(L9*INDEX(Resources!$J$2:$J$500,MATCH(D9,Resources!$A$2:$A$500,0))/5*J9,1) -> 1024 | N9: =INDEX(Resources!$H$2:$H$500,MATCH(D9,Resources!$A$2:$A$500,0)) -> 73.44 | O9: =INDEX(Resources!$I$2:$I$500,MATCH(D9,Resources!$A$2:$A$500,0)) -> 150 | P9: =M9*N9 -> 75202.56 | Q9: =IF(G9="Yes",M9*O9,0) -> 153600 | R9: =SUMIFS(Actuals!$H$2:$H$6000,Actuals!$C$2:$C$6000,B9,Actuals!$E$2:$E$6000,D9) -> 964.5 | S9: =IF(M9=0,0,R9/M9) -> 0.94189453
A10: A-0009 | B10: P-1002 | C10: =IFERROR(INDEX(Projects!$B$2:$B$500,MATCH(B10,Projects!$A$2:$A$500,0)),"") -> Claims Automation Engine | D10: E-0024 | E10: =IFERROR(INDEX(Resources!$B$2:$B$500,MATCH(D10,Resources!$A$2:$A$500,0)),"") -> Isabel Gill | F10: Tech Lead | G10: Yes | H10: 46034 | I10: 46391 | J10: 0.5 | K10: =IF(AND(AsOfDate>=H10,AsOfDate<=I10),"Yes","No") -> Yes | L10: =NETWORKDAYS(H10,I10) -> 256 | M10: =ROUND(L10*INDEX(Resources!$J$2:$J$500,MATCH(D10,Resources!$A$2:$A$500,0))/5*J10,1) -> 1024 | N10: =INDEX(Resources!$H$2:$H$500,MATCH(D10,Resources!$A$2:$A$500,0)) -> 99.36 | O10: =INDEX(Resources!$I$2:$I$500,MATCH(D10,Resources!$A$2:$A$500,0)) -> 200 | P10: =M10*N10 -> 101744.64 | Q10: =IF(G10="Yes",M10*O10,0) -> 204800 | R10: =SUMIFS(Actuals!$H$2:$H$6000,Actuals!$C$2:$C$6000,B10,Actuals!$E$2:$E$6000,D10) -> 936.1 | S10: =IF(M10=0,0,R10/M10) -> 0.91416016
A11: A-0010 | B11: P-1002 | C11: =IFERROR(INDEX(Projects!$B$2:$B$500,MATCH(B11,Projects!$A$2:$A$500,0)),"") -> Claims Automation Engine | D11: E-0032 | E11: =IFERROR(INDEX(Resources!$B$2:$B$500,MATCH(D11,Resources!$A$2:$A$500,0)),"") -> Maya Osei | F11: Developer | G11: Yes | H11: 46034 | I11: 46391 | J11: 0.75 | K11: =IF(AND(AsOfDate>=H11,AsOfDate<=I11),"Yes","No") -> Yes | L11: =NETWORKDAYS(H11,I11) -> 256 | M11: =ROUND(L11*INDEX(Resources!$J$2:$J$500,MATCH(D11,Resources!$A$2:$A$500,0))/5*J11,1) -> 1536 | N11: =INDEX(Resources!$H$2:$H$500,MATCH(D11,Resources!$A$2:$A$500,0)) -> 59.52 | O11: =INDEX(Resources!$I$2:$I$500,MATCH(D11,Resources!$A$2:$A$500,0)) -> 120 | P11: =M11*N11 -> 91422.72 | Q11: =IF(G11="Yes",M11*O11,0) -> 184320 | R11: =SUMIFS(Actuals!$H$2:$H$6000,Actuals!$C$2:$C$6000,B11,Actuals!$E$2:$E$6000,D11) -> 1410.3 | S11: =IF(M11=0,0,R11/M11) -> 0.91816406
A12: A-0011 | B12: P-1002 | C12: =IFERROR(INDEX(Projects!$B$2:$B$500,MATCH(B12,Projects!$A$2:$A$500,0)),"") -> Claims Automation Engine | D12: E-0043 | E12: =IFERROR(INDEX(Resources!$B$2:$B$500,MATCH(D12,Resources!$A$2:$A$500,0)),"") -> Victor Chen | F12: QA Analyst | G12: Yes | H12: 46187 | I12: 46391 | J12: 0.25 | K12: =IF(AND(AsOfDate>=H12,AsOfDate<=I12),"Yes","No") -> Yes | L12: =NETWORKDAYS(H12,I12) -> 146 | M12: =ROUND(L12*INDEX(Resources!$J$2:$J$500,MATCH(D12,Resources!$A$2:$A$500,0))/5*J12,1) -> 292 | N12: =INDEX(Resources!$H$2:$H$500,MATCH(D12,Resources!$A$2:$A$500,0)) -> 81.2 | O12: =INDEX(Resources!$I$2:$I$500,MATCH(D12,Resources!$A$2:$A$500,0)) -> 135 | P12: =M12*N12 -> 23710.4 | Q12: =IF(G12="Yes",M12*O12,0) -> 39420 | R12: =SUMIFS(Actuals!$H$2:$H$6000,Actuals!$C$2:$C$6000,B12,Actuals!$E$2:$E$6000,D12) -> 158.7 | S12: =IF(M12=0,0,R12/M12) -> 0.54349315
A13: A-0012 | B13: P-1002 | C13: =IFERROR(INDEX(Projects!$B$2:$B$500,MATCH(B13,Projects!$A$2:$A$500,0)),"") -> Claims Automation Engine | D13: E-0062 | E13: =IFERROR(INDEX(Resources!$B$2:$B$500,MATCH(D13,Resources!$A$2:$A$500,0)),"") -> Mariam Brooks | F13: Change Manager | G13: Yes | H13: 46187 | I13: 46391 | J13: 0.25 | K13: =IF(AND(AsOfDate>=H13,AsOfDate<=I13),"Yes","No") -> Yes | L13: =NETWORKDAYS(H13,I13) -> 146 | M13: =ROUND(L13*INDEX(Resources!$J$2:$J$500,MATCH(D13,Resources!$A$2:$A$500,0))/5*J13,1) -> 292 | N13: =INDEX(Resources!$H$2:$H$500,MATCH(D13,Resources!$A$2:$A$500,0)) -> 83.52 | O13: =INDEX(Resources!$I$2:$I$500,MATCH(D13,Resources!$A$2:$A$500,0)) -> 175 | P13: =M13*N13 -> 24387.84 | Q13: =IF(G13="Yes",M13*O13,0) -> 51100 | R13: =SUMIFS(Actuals!$H$2:$H$6000,Actuals!$C$2:$C$6000,B13,Actuals!$E$2:$E$6000,D13) -> 153.5 | S13: =IF(M13=0,0,R13/M13) -> 0.52568493
... A146: A-0145 | B146: P-1024 | C146: =IFERROR(INDEX(Projects!$B$2:$B$500,MATCH(B146,Projects!$A$2:$A$500,0)),"") -> Municipal Asset Management | D146: E-0063 | E146: =IFERROR(INDEX(Resources!$B$2:$B$500,MATCH(D146,Resources!$A$2:$A$500,0)),"") -> Callum Dubois | F146: Change Manager | G146: Yes | H146: 46528 | I146: 46689 | J146: 0.25 | K146: =IF(AND(AsOfDate>=H146,AsOfDate<=I146),"Yes","No") -> No | L146: =NETWORKDAYS(H146,I146) -> 116 | M146: =ROUND(L146*INDEX(Resources!$J$2:$J$500,MATCH(D146,Resources!$A$2:$A$500,0))/5*J146,1) -> 185.6 | N146: =INDEX(Resources!$H$2:$H$500,MATCH(D146,Resources!$A$2:$A$500,0)) -> 77.76 | O146: =INDEX(Resources!$I$2:$I$500,MATCH(D146,Resources!$A$2:$A$500,0)) -> 160 | P146: =M146*N146 -> 14432.256 | Q146: =IF(G146="Yes",M146*O146,0) -> 29696 | R146: =SUMIFS(Actuals!$H$2:$H$6000,Actuals!$C$2:$C$6000,B146,Actuals!$E$2:$E$6000,D146) -> 0 | S146: =IF(M146=0,0,R146/M146) -> 0

Sheet Estimates
A1: EstimateLineID | B1: ProjectID | C1: EstimateVersion | D1: IsCurrent | E1: WBSCode | F1: Phase | G1: Workstream | H1: EstimatedHours | I1: BlendedCostRate | J1: Confidence | K1: EstimatedByID | L1: EstimateDate | M1: EstimatedBy | N1: ContingencyPct | O1: BaseCost | P1: ContingencyAmt | Q1: TotalEstimate
A2: EST-0001 | B2: P-1001 | C2: v1 Baseline | D2: Yes | E2: 1.0 | F2: Discovery | G2: Business & Analysis | H2: 624 | I2: 87.23 | J2: High | K2: E-0003 | L2: 45929 | M2: =IFERROR(INDEX(Resources!$B$2:$B$500,MATCH(K2,Resources!$A$2:$A$500,0)),"") -> Aisha Tremblay | N2: =IF(J2="High",Contingency_High,IF(J2="Medium",Contingency_Medium,Contingency_Low)) -> 0.05 | O2: =H2*I2 -> 54431.52 | P2: =O2*N2 -> 2721.576 | Q2: =O2+P2 -> 57153.096
A3: EST-0002 | B3: P-1001 | C3: v1 Baseline | D3: Yes | E3: 2.0 | F3: Design | G3: Experience & Architecture | H3: 1164 | I3: 87.23 | J3: High | K3: E-0003 | L3: 45929 | M3: =IFERROR(INDEX(Resources!$B$2:$B$500,MATCH(K3,Resources!$A$2:$A$500,0)),"") -> Aisha Tremblay | N3: =IF(J3="High",Contingency_High,IF(J3="Medium",Contingency_Medium,Contingency_Low)) -> 0.05 | O3: =H3*I3 -> 101535.72 | P3: =O3*N3 -> 5076.786 | Q3: =O3+P3 -> 106612.51
A4: EST-0003 | B4: P-1001 | C4: v1 Baseline | D4: Yes | E4: 3.0 | F4: Build | G4: Engineering | H4: 2968 | I4: 87.23 | J4: Medium | K4: E-0003 | L4: 45929 | M4: =IFERROR(INDEX(Resources!$B$2:$B$500,MATCH(K4,Resources!$A$2:$A$500,0)),"") -> Aisha Tremblay | N4: =IF(J4="High",Contingency_High,IF(J4="Medium",Contingency_Medium,Contingency_Low)) -> 0.1 | O4: =H4*I4 -> 258898.64 | P4: =O4*N4 -> 25889.864 | Q4: =O4+P4 -> 284788.5
A5: EST-0004 | B5: P-1001 | C5: v1 Baseline | D5: Yes | E5: 4.0 | F5: Test | G5: Quality Assurance | H5: 1265 | I5: 87.23 | J5: High | K5: E-0003 | L5: 45929 | M5: =IFERROR(INDEX(Resources!$B$2:$B$500,MATCH(K5,Resources!$A$2:$A$500,0)),"") -> Aisha Tremblay | N5: =IF(J5="High",Contingency_High,IF(J5="Medium",Contingency_Medium,Contingency_Low)) -> 0.05 | O5: =H5*I5 -> 110345.95 | P5: =O5*N5 -> 5517.2975 | Q5: =O5+P5 -> 115863.25
A6: EST-0005 | B6: P-1001 | C6: v1 Baseline | D6: Yes | E6: 5.0 | F6: Deploy | G6: Release & Change | H6: 665 | I6: 87.23 | J6: High | K6: E-0003 | L6: 45929 | M6: =IFERROR(INDEX(Resources!$B$2:$B$500,MATCH(K6,Resources!$A$2:$A$500,0)),"") -> Aisha Tremblay | N6: =IF(J6="High",Contingency_High,IF(J6="Medium",Contingency_Medium,Contingency_Low)) -> 0.05 | O6: =H6*I6 -> 58007.95 | P6: =O6*N6 -> 2900.3975 | Q6: =O6+P6 -> 60908.348
A7: EST-0006 | B7: P-1002 | C7: v1 Baseline | D7: No | E7: 1.0 | F7: Discovery | G7: Business & Analysis | H7: 492 | I7: 78.77 | J7: Low | K7: E-0004 | L7: 45992 | M7: =IFERROR(INDEX(Resources!$B$2:$B$500,MATCH(K7,Resources!$A$2:$A$500,0)),"") -> Liam Roy | N7: =IF(J7="High",Contingency_High,IF(J7="Medium",Contingency_Medium,Contingency_Low)) -> 0.15 | O7: =H7*I7 -> 38754.84 | P7: =O7*N7 -> 5813.226 | Q7: =O7+P7 -> 44568.066
A8: EST-0007 | B8: P-1002 | C8: v1 Baseline | D8: No | E8: 2.0 | F8: Design | G8: Experience & Architecture | H8: 776 | I8: 78.77 | J8: Low | K8: E-0004 | L8: 45992 | M8: =IFERROR(INDEX(Resources!$B$2:$B$500,MATCH(K8,Resources!$A$2:$A$500,0)),"") -> Liam Roy | N8: =IF(J8="High",Contingency_High,IF(J8="Medium",Contingency_Medium,Contingency_Low)) -> 0.15 | O8: =H8*I8 -> 61125.52 | P8: =O8*N8 -> 9168.828 | Q8: =O8+P8 -> 70294.348
A9: EST-0008 | B9: P-1002 | C9: v1 Baseline | D9: No | E9: 3.0 | F9: Build | G9: Engineering | H9: 1906 | I9: 78.77 | J9: Low | K9: E-0004 | L9: 45992 | M9: =IFERROR(INDEX(Resources!$B$2:$B$500,MATCH(K9,Resources!$A$2:$A$500,0)),"") -> Liam Roy | N9: =IF(J9="High",Contingency_High,IF(J9="Medium",Contingency_Medium,Contingency_Low)) -> 0.15 | O9: =H9*I9 -> 150135.62 | P9: =O9*N9 -> 22520.343 | Q9: =O9+P9 -> 172655.96
A10: EST-0009 | B10: P-1002 | C10: v1 Baseline | D10: No | E10: 4.0 | F10: Test | G10: Quality Assurance | H10: 850 | I10: 78.77 | J10: Low | K10: E-0004 | L10: 45992 | M10: =IFERROR(INDEX(Resources!$B$2:$B$500,MATCH(K10,Resources!$A$2:$A$500,0)),"") -> Liam Roy | N10: =IF(J10="High",Contingency_High,IF(J10="Medium",Contingency_Medium,Contingency_Low)) -> 0.15 | O10: =H10*I10 -> 66954.5 | P10: =O10*N10 -> 10043.175 | Q10: =O10+P10 -> 76997.675
A11: EST-0010 | B11: P-1002 | C11: v1 Baseline | D11: No | E11: 5.0 | F11: Deploy | G11: Release & Change | H11: 436 | I11: 78.77 | J11: Low | K11: E-0004 | L11: 45992 | M11: =IFERROR(INDEX(Resources!$B$2:$B$500,MATCH(K11,Resources!$A$2:$A$500,0)),"") -> Liam Roy | N11: =IF(J11="High",Contingency_High,IF(J11="Medium",Contingency_Medium,Contingency_Low)) -> 0.15 | O11: =H11*I11 -> 34343.72 | P11: =O11*N11 -> 5151.558 | Q11: =O11+P11 -> 39495.278
A12: EST-0011 | B12: P-1002 | C12: v2 Re-forecast | D12: Yes | E12: 1.0 | F12: Discovery | G12: Business & Analysis | H12: 583 | I12: 80.35 | J12: Medium | K12: E-0004 | L12: 46218 | M12: =IFERROR(INDEX(Resources!$B$2:$B$500,MATCH(K12,Resources!$A$2:$A$500,0)),"") -> Liam Roy | N12: =IF(J12="High",Contingency_High,IF(J12="Medium",Contingency_Medium,Contingency_Low)) -> 0.1 | O12: =H12*I12 -> 46844.05 | P12: =O12*N12 -> 4684.405 | Q12: =O12+P12 -> 51528.455
A13: EST-0012 | B13: P-1002 | C13: v2 Re-forecast | D13: Yes | E13: 2.0 | F13: Design | G13: Experience & Architecture | H13: 1062 | I13: 80.35 | J13: Medium | K13: E-0004 | L13: 46218 | M13: =IFERROR(INDEX(Resources!$B$2:$B$500,MATCH(K13,Resources!$A$2:$A$500,0)),"") -> Liam Roy | N13: =IF(J13="High",Contingency_High,IF(J13="Medium",Contingency_Medium,Contingency_Low)) -> 0.1 | O13: =H13*I13 -> 85331.7 | P13: =O13*N13 -> 8533.17 | Q13: =O13+P13 -> 93864.87
... A166: EST-0165 | B166: P-1024 | C166: v1 Baseline | D166: Yes | E166: 5.0 | F166: Deploy | G166: Release & Change | H166: 613 | I166: 83.86 | J166: Medium | K166: E-0005 | L166: 46360 | M166: =IFERROR(INDEX(Resources!$B$2:$B$500,MATCH(K166,Resources!$A$2:$A$500,0)),"") -> Mei Fraser | N166: =IF(J166="High",Contingency_High,IF(J166="Medium",Contingency_Medium,Contingency_Low)) -> 0.1 | O166: =H166*I166 -> 51406.18 | P166: =O166*N166 -> 5140.618 | Q166: =O166+P166 -> 56546.798

Sheet Budget
A1: BudgetLineID | B1: ProjectID | C1: ProjectName | D1: CostCategory | E1: BudgetAmount | F1: ApprovedDate | G1: ApprovedBy | H1: Notes | I1: ActualToDate | J1: Remaining | K1: BurnPct | L1: LineStatus
A2: B-0001 | B2: P-1001 | C2: =IFERROR(INDEX(Projects!$B$2:$B$500,MATCH(B2,Projects!$A$2:$A$500,0)),"") -> Patient Portal Modernization | D2: Labour | E2: 583200 | F2: 45939 | G2: Gordon Achebe | H2: From v1 baseline estimate | I2: =SUMIFS(Actuals!$J$2:$J$6000,Actuals!$C$2:$C$6000,B2,Actuals!$D$2:$D$6000,D2) -> 487314.13 | J2: =E2-I2 -> 95885.87 | K2: =IF(E2=0,0,I2/E2) -> 0.83558664 | L2: =IF(D2="Contingency","Reserve",IF(K2>1,"Overspent",IF(K2>=BudgetNearLimit,"Near limit","Within budget"))) -> Within budget
A3: B-0002 | B3: P-1001 | C3: =IFERROR(INDEX(Projects!$B$2:$B$500,MATCH(B3,Projects!$A$2:$A$500,0)),"") -> Patient Portal Modernization | D3: Software & Licences | E3: 36100 | F3: 45939 | G3: Gordon Achebe | I3: =SUMIFS(Actuals!$J$2:$J$6000,Actuals!$C$2:$C$6000,B3,Actuals!$D$2:$D$6000,D3) -> 29669.4 | J3: =E3-I3 -> 6430.6 | K3: =IF(E3=0,0,I3/E3) -> 0.82186704 | L3: =IF(D3="Contingency","Reserve",IF(K3>1,"Overspent",IF(K3>=BudgetNearLimit,"Near limit","Within budget"))) -> Within budget
A4: B-0003 | B4: P-1001 | C4: =IFERROR(INDEX(Projects!$B$2:$B$500,MATCH(B4,Projects!$A$2:$A$500,0)),"") -> Patient Portal Modernization | D4: Subcontractors | E4: 53200 | F4: 45939 | G4: Gordon Achebe | I4: =SUMIFS(Actuals!$J$2:$J$6000,Actuals!$C$2:$C$6000,B4,Actuals!$D$2:$D$6000,D4) -> 42535.38 | J4: =E4-I4 -> 10664.62 | K4: =IF(E4=0,0,I4/E4) -> 0.79953722 | L4: =IF(D4="Contingency","Reserve",IF(K4>1,"Overspent",IF(K4>=BudgetNearLimit,"Near limit","Within budget"))) -> Within budget
A5: B-0004 | B5: P-1001 | C5: =IFERROR(INDEX(Projects!$B$2:$B$500,MATCH(B5,Projects!$A$2:$A$500,0)),"") -> Patient Portal Modernization | D5: Travel & Expenses | E5: 11900 | F5: 45939 | G5: Gordon Achebe | I5: =SUMIFS(Actuals!$J$2:$J$6000,Actuals!$C$2:$C$6000,B5,Actuals!$D$2:$D$6000,D5) -> 10170.37 | J5: =E5-I5 -> 1729.63 | K5: =IF(E5=0,0,I5/E5) -> 0.85465294 | L5: =IF(D5="Contingency","Reserve",IF(K5>1,"Overspent",IF(K5>=BudgetNearLimit,"Near limit","Within budget"))) -> Within budget
A6: B-0005 | B6: P-1001 | C6: =IFERROR(INDEX(Projects!$B$2:$B$500,MATCH(B6,Projects!$A$2:$A$500,0)),"") -> Patient Portal Modernization | D6: Contingency | E6: 42100 | F6: 45939 | G6: Gordon Achebe | H6: Management reserve; drawn via CR | I6: =SUMIFS(Actuals!$J$2:$J$6000,Actuals!$C$2:$C$6000,B6,Actuals!$D$2:$D$6000,D6) -> 0 | J6: =E6-I6 -> 42100 | K6: =IF(E6=0,0,I6/E6) -> 0 | L6: =IF(D6="Contingency","Reserve",IF(K6>1,"Overspent",IF(K6>=BudgetNearLimit,"Near limit","Within budget"))) -> Reserve
A7: B-0006 | B7: P-1002 | C7: =IFERROR(INDEX(Projects!$B$2:$B$500,MATCH(B7,Projects!$A$2:$A$500,0)),"") -> Claims Automation Engine | D7: Labour | E7: 351300 | F7: 46002 | G7: Helena Marsh | H7: From v1 baseline estimate | I7: =SUMIFS(Actuals!$J$2:$J$6000,Actuals!$C$2:$C$6000,B7,Actuals!$D$2:$D$6000,D7) -> 320785.27 | J7: =E7-I7 -> 30514.73 | K7: =IF(E7=0,0,I7/E7) -> 0.91313769 | L7: =IF(D7="Contingency","Reserve",IF(K7>1,"Overspent",IF(K7>=BudgetNearLimit,"Near limit","Within budget"))) -> Near limit
A8: B-0007 | B8: P-1002 | C8: =IFERROR(INDEX(Projects!$B$2:$B$500,MATCH(B8,Projects!$A$2:$A$500,0)),"") -> Claims Automation Engine | D8: Hardware | E8: 28300 | F8: 46002 | G8: Helena Marsh | I8: =SUMIFS(Actuals!$J$2:$J$6000,Actuals!$C$2:$C$6000,B8,Actuals!$D$2:$D$6000,D8) -> 35530.14 | J8: =E8-I8 -> -7230.14 | K8: =IF(E8=0,0,I8/E8) -> 1.255482 | L8: =IF(D8="Contingency","Reserve",IF(K8>1,"Overspent",IF(K8>=BudgetNearLimit,"Near limit","Within budget"))) -> Overspent
A9: B-0008 | B9: P-1002 | C9: =IFERROR(INDEX(Projects!$B$2:$B$500,MATCH(B9,Projects!$A$2:$A$500,0)),"") -> Claims Automation Engine | D9: Software & Licences | E9: 18200 | F9: 46002 | G9: Helena Marsh | I9: =SUMIFS(Actuals!$J$2:$J$6000,Actuals!$C$2:$C$6000,B9,Actuals!$D$2:$D$6000,D9) -> 14042.27 | J9: =E9-I9 -> 4157.73 | K9: =IF(E9=0,0,I9/E9) -> 0.7715533 | L9: =IF(D9="Contingency","Reserve",IF(K9>1,"Overspent",IF(K9>=BudgetNearLimit,"Near limit","Within budget"))) -> Within budget
A10: B-0009 | B10: P-1002 | C10: =IFERROR(INDEX(Projects!$B$2:$B$500,MATCH(B10,Projects!$A$2:$A$500,0)),"") -> Claims Automation Engine | D10: Training | E10: 9000 | F10: 46002 | G10: Helena Marsh | I10: =SUMIFS(Actuals!$J$2:$J$6000,Actuals!$C$2:$C$6000,B10,Actuals!$D$2:$D$6000,D10) -> 7170.74 | J10: =E10-I10 -> 1829.26 | K10: =IF(E10=0,0,I10/E10) -> 0.79674889 | L10: =IF(D10="Contingency","Reserve",IF(K10>1,"Overspent",IF(K10>=BudgetNearLimit,"Near limit","Within budget"))) -> Within budget
A11: B-0010 | B11: P-1002 | C11: =IFERROR(INDEX(Projects!$B$2:$B$500,MATCH(B11,Projects!$A$2:$A$500,0)),"") -> Claims Automation Engine | D11: Travel & Expenses | E11: 6600 | F11: 46002 | G11: Helena Marsh | I11: =SUMIFS(Actuals!$J$2:$J$6000,Actuals!$C$2:$C$6000,B11,Actuals!$D$2:$D$6000,D11) -> 5026.16 | J11: =E11-I11 -> 1573.84 | K11: =IF(E11=0,0,I11/E11) -> 0.76153939 | L11: =IF(D11="Contingency","Reserve",IF(K11>1,"Overspent",IF(K11>=BudgetNearLimit,"Near limit","Within budget"))) -> Within budget
A12: B-0011 | B12: P-1002 | C12: =IFERROR(INDEX(Projects!$B$2:$B$500,MATCH(B12,Projects!$A$2:$A$500,0)),"") -> Claims Automation Engine | D12: Contingency | E12: 52700 | F12: 46002 | G12: Helena Marsh | H12: Management reserve; drawn via CR | I12: =SUMIFS(Actuals!$J$2:$J$6000,Actuals!$C$2:$C$6000,B12,Actuals!$D$2:$D$6000,D12) -> 0 | J12: =E12-I12 -> 52700 | K12: =IF(E12=0,0,I12/E12) -> 0 | L12: =IF(D12="Contingency","Reserve",IF(K12>1,"Overspent",IF(K12>=BudgetNearLimit,"Near limit","Within budget"))) -> Reserve
A13: B-0012 | B13: P-1003 | C13: =IFERROR(INDEX(Projects!$B$2:$B$500,MATCH(B13,Projects!$A$2:$A$500,0)),"") -> Enterprise Data Lakehouse | D13: Labour | E13: 576600 | F13: 45884 | G13: Gordon Achebe | H13: From v1 baseline estimate | I13: =SUMIFS(Actuals!$J$2:$J$6000,Actuals!$C$2:$C$6000,B13,Actuals!$D$2:$D$6000,D13) -> 526031.85 | J13: =E13-I13 -> 50568.15 | K13: =IF(E13=0,0,I13/E13) -> 0.91229943 | L13: =IF(D13="Contingency","Reserve",IF(K13>1,"Overspent",IF(K13>=BudgetNearLimit,"Near limit","Within budget"))) -> Near limit
A14: B-0013 | B14: P-1003 | C14: =IFERROR(INDEX(Projects!$B$2:$B$500,MATCH(B14,Projects!$A$2:$A$500,0)),"") -> Enterprise Data Lakehouse | D14: Cloud Hosting | E14: 59300 | F14: 45884 | G14: Gordon Achebe | I14: =SUMIFS(Actuals!$J$2:$J$6000,Actuals!$C$2:$C$6000,B14,Actuals!$D$2:$D$6000,D14) -> 49511.47 | J14: =E14-I14 -> 9788.53 | K14: =IF(E14=0,0,I14/E14) -> 0.83493204 | L14: =IF(D14="Contingency","Reserve",IF(K14>1,"Overspent",IF(K14>=BudgetNearLimit,"Near limit","Within budget"))) -> Within budget
A15: B-0014 | B15: P-1003 | C15: =IFERROR(INDEX(Projects!$B$2:$B$500,MATCH(B15,Projects!$A$2:$A$500,0)),"") -> Enterprise Data Lakehouse | D15: Software & Licences | E15: 39100 | F15: 45884 | G15: Gordon Achebe | I15: =SUMIFS(Actuals!$J$2:$J$6000,Actuals!$C$2:$C$6000,B15,Actuals!$D$2:$D$6000,D15) -> 32748.66 | J15: =E15-I15 -> 6351.34 | K15: =IF(E15=0,0,I15/E15) -> 0.83756164 | L15: =IF(D15="Contingency","Reserve",IF(K15>1,"Overspent",IF(K15>=BudgetNearLimit,"Near limit","Within budget"))) -> Within budget
A16: B-0015 | B16: P-1003 | C16: =IFERROR(INDEX(Projects!$B$2:$B$500,MATCH(B16,Projects!$A$2:$A$500,0)),"") -> Enterprise Data Lakehouse | D16: Travel & Expenses | E16: 8100 | F16: 45884 | G16: Gordon Achebe | I16: =SUMIFS(Actuals!$J$2:$J$6000,Actuals!$C$2:$C$6000,B16,Actuals!$D$2:$D$6000,D16) -> 6516.17 | J16: =E16-I16 -> 1583.83 | K16: =IF(E16=0,0,I16/E16) -> 0.80446543 | L16: =IF(D16="Contingency","Reserve",IF(K16>1,"Overspent",IF(K16>=BudgetNearLimit,"Near limit","Within budget"))) -> Within budget
A17: B-0016 | B17: P-1003 | C17: =IFERROR(INDEX(Projects!$B$2:$B$500,MATCH(B17,Projects!$A$2:$A$500,0)),"") -> Enterprise Data Lakehouse | D17: Contingency | E17: 86500 | F17: 45884 | G17: Gordon Achebe | H17: Management reserve; drawn via CR | I17: =SUMIFS(Actuals!$J$2:$J$6000,Actuals!$C$2:$C$6000,B17,Actuals!$D$2:$D$6000,D17) -> 0 | J17: =E17-I17 -> 86500 | K17: =IF(E17=0,0,I17/E17) -> 0 | L17: =IF(D17="Contingency","Reserve",IF(K17>1,"Overspent",IF(K17>=BudgetNearLimit,"Near limit","Within budget"))) -> Reserve
A18: B-0017 | B18: P-1004 | C18: =IFERROR(INDEX(Projects!$B$2:$B$500,MATCH(B18,Projects!$A$2:$A$500,0)),"") -> Cloud Migration Wave 2 | D18: Labour | E18: 524600 | F18: 46029 | G18: Gordon Achebe | H18: From v1 baseline estimate | I18: =SUMIFS(Actuals!$J$2:$J$6000,Actuals!$C$2:$C$6000,B18,Actuals!$D$2:$D$6000,D18) -> 316771 | J18: =E18-I18 -> 207829 | K18: =IF(E18=0,0,I18/E18) -> 0.6038334 | L18: =IF(D18="Contingency","Reserve",IF(K18>1,"Overspent",IF(K18>=BudgetNearLimit,"Near limit","Within budget"))) -> Within budget
A19: B-0018 | B19: P-1004 | C19: =IFERROR(INDEX(Projects!$B$2:$B$500,MATCH(B19,Projects!$A$2:$A$500,0)),"") -> Cloud Migration Wave 2 | D19: Cloud Hosting | E19: 80300 | F19: 46029 | G19: Gordon Achebe | I19: =SUMIFS(Actuals!$J$2:$J$6000,Actuals!$C$2:$C$6000,B19,Actuals!$D$2:$D$6000,D19) -> 46125.84 | J19: =E19-I19 -> 34174.16 | K19: =IF(E19=0,0,I19/E19) -> 0.57441893 | L19: =IF(D19="Contingency","Reserve",IF(K19>1,"Overspent",IF(K19>=BudgetNearLimit,"Near limit","Within budget"))) -> Within budget
A20: B-0019 | B20: P-1004 | C20: =IFERROR(INDEX(Projects!$B$2:$B$500,MATCH(B20,Projects!$A$2:$A$500,0)),"") -> Cloud Migration Wave 2 | D20: Hardware | E20: 55800 | F20: 46029 | G20: Gordon Achebe | I20: =SUMIFS(Actuals!$J$2:$J$6000,Actuals!$C$2:$C$6000,B20,Actuals!$D$2:$D$6000,D20) -> 54839.11 | J20: =E20-I20 -> 960.89 | K20: =IF(E20=0,0,I20/E20) -> 0.98277975 | L20: =IF(D20="Contingency","Reserve",IF(K20>1,"Overspent",IF(K20>=BudgetNearLimit,"Near limit","Within budget"))) -> Near limit
A21: B-0020 | B21: P-1004 | C21: =IFERROR(INDEX(Projects!$B$2:$B$500,MATCH(B21,Projects!$A$2:$A$500,0)),"") -> Cloud Migration Wave 2 | D21: Software & Licences | E21: 29500 | F21: 46029 | G21: Gordon Achebe | I21: =SUMIFS(Actuals!$J$2:$J$6000,Actuals!$C$2:$C$6000,B21,Actuals!$D$2:$D$6000,D21) -> 16733.21 | J21: =E21-I21 -> 12766.79 | K21: =IF(E21=0,0,I21/E21) -> 0.56722746 | L21: =IF(D21="Contingency","Reserve",IF(K21>1,"Overspent",IF(K21>=BudgetNearLimit,"Near limit","Within budget"))) -> Within budget
A22: B-0021 | B22: P-1004 | C22: =IFERROR(INDEX(Projects!$B$2:$B$500,MATCH(B22,Projects!$A$2:$A$500,0)),"") -> Cloud Migration Wave 2 | D22: Travel & Expenses | E22: 10800 | F22: 46029 | G22: Gordon Achebe | I22: =SUMIFS(Actuals!$J$2:$J$6000,Actuals!$C$2:$C$6000,B22,Actuals!$D$2:$D$6000,D22) -> 6368.56 | J22: =E22-I22 -> 4431.44 | K22: =IF(E22=0,0,I22/E22) -> 0.58968148 | L22: =IF(D22="Contingency","Reserve",IF(K22>1,"Overspent",IF(K22>=BudgetNearLimit,"Near limit","Within budget"))) -> Within budget
A23: B-0022 | B23: P-1004 | C23: =IFERROR(INDEX(Projects!$B$2:$B$500,MATCH(B23,Projects!$A$2:$A$500,0)),"") -> Cloud Migration Wave 2 | D23: Contingency | E23: 37500 | F23: 46029 | G23: Gordon Achebe | H23: Management reserve; drawn via CR | I23: =SUMIFS(Actuals!$J$2:$J$6000,Actuals!$C$2:$C$6000,B23,Actuals!$D$2:$D$6000,D23) -> 0 | J23: =E23-I23 -> 37500 | K23: =IF(E23=0,0,I23/E23) -> 0 | L23: =IF(D23="Contingency","Reserve",IF(K23>1,"Overspent",IF(K23>=BudgetNearLimit,"Near limit","Within budget"))) -> Reserve
A24: B-0023 | B24: P-1005 | C24: =IFERROR(INDEX(Projects!$B$2:$B$500,MATCH(B24,Projects!$A$2:$A$500,0)),"") -> Fraud Detection ML Platform | D24: Labour | E24: 363500 | F24: 46073 | G24: Helena Marsh | H24: From v1 baseline estimate | I24: =SUMIFS(Actuals!$J$2:$J$6000,Actuals!$C$2:$C$6000,B24,Actuals!$D$2:$D$6000,D24) -> 255129.66 | J24: =E24-I24 -> 108370.34 | K24: =IF(E24=0,0,I24/E24) -> 0.70186977 | L24: =IF(D24="Contingency","Reserve",IF(K24>1,"Overspent",IF(K24>=BudgetNearLimit,"Near limit","Within budget"))) -> Within budget
A25: B-0024 | B25: P-1005 | C25: =IFERROR(INDEX(Projects!$B$2:$B$500,MATCH(B25,Projects!$A$2:$A$500,0)),"") -> Fraud Detection ML Platform | D25: Cloud Hosting | E25: 32500 | F25: 46073 | G25: Helena Marsh | I25: =SUMIFS(Actuals!$J$2:$J$6000,Actuals!$C$2:$C$6000,B25,Actuals!$D$2:$D$6000,D25) -> 18578.25 | J25: =E25-I25 -> 13921.75 | K25: =IF(E25=0,0,I25/E25) -> 0.57163846 | L25: =IF(D25="Contingency","Reserve",IF(K25>1,"Overspent",IF(K25>=BudgetNearLimit,"Near limit","Within budget"))) -> Within budget
A26: B-0025 | B26: P-1005 | C26: =IFERROR(INDEX(Projects!$B$2:$B$500,MATCH(B26,Projects!$A$2:$A$500,0)),"") -> Fraud Detection ML Platform | D26: Software & Licences | E26: 21800 | F26: 46073 | G26: Helena Marsh | I26: =SUMIFS(Actuals!$J$2:$J$6000,Actuals!$C$2:$C$6000,B26,Actuals!$D$2:$D$6000,D26) -> 12550.75 | J26: =E26-I26 -> 9249.25 | K26: =IF(E26=0,0,I26/E26) -> 0.57572248 | L26: =IF(D26="Contingency","Reserve",IF(K26>1,"Overspent",IF(K26>=BudgetNearLimit,"Near limit","Within budget"))) -> Within budget
A27: B-0026 | B27: P-1005 | C27: =IFERROR(INDEX(Projects!$B$2:$B$500,MATCH(B27,Projects!$A$2:$A$500,0)),"") -> Fraud Detection ML Platform | D27: Travel & Expenses | E27: 5000 | F27: 46073 | G27: Helena Marsh | I27: =SUMIFS(Actuals!$J$2:$J$6000,Actuals!$C$2:$C$6000,B27,Actuals!$D$2:$D$6000,D27) -> 3045.04 | J27: =E27-I27 -> 1954.96 | K27: =IF(E27=0,0,I27/E27) -> 0.609008 | L27: =IF(D27="Contingency","Reserve",IF(K27>1,"Overspent",IF(K27>=BudgetNearLimit,"Near limit","Within budget"))) -> Within budget
A28: B-0027 | B28: P-1005 | C28: =IFERROR(INDEX(Projects!$B$2:$B$500,MATCH(B28,Projects!$A$2:$A$500,0)),"") -> Fraud Detection ML Platform | D28: Contingency | E28: 36400 | F28: 46073 | G28: Helena Marsh | H28: Management reserve; drawn via CR | I28: =SUMIFS(Actuals!$J$2:$J$6000,Actuals!$C$2:$C$6000,B28,Actuals!$D$2:$D$6000,D28) -> 0 | J28: =E28-I28 -> 36400 | K28: =IF(E28=0,0,I28/E28) -> 0 | L28: =IF(D28="Contingency","Reserve",IF(K28>1,"Overspent",IF(K28>=BudgetNearLimit,"Near limit","Within budget"))) -> Reserve
A29: B-0028 | B29: P-1006 | C29: =IFERROR(INDEX(Projects!$B$2:$B$500,MATCH(B29,Projects!$A$2:$A$500,0)),"") -> Omnichannel Commerce Replatform | D29: Labour | E29: 456100 | F29: 45917 | G29: Gordon Achebe | H29: From v1 baseline estimate | I29: =SUMIFS(Actuals!$J$2:$J$6000,Actuals!$C$2:$C$6000,B29,Actuals!$D$2:$D$6000,D29) -> 541027.58 | J29: =E29-I29 -> -84927.58 | K29: =IF(E29=0,0,I29/E29) -> 1.1862039 | L29: =IF(D29="Contingency","Reserve",IF(K29>1,"Overspent",IF(K29>=BudgetNearLimit,"Near limit","Within budget"))) -> Overspent
A30: B-0029 | B30: P-1006 | C30: =IFERROR(INDEX(Projects!$B$2:$B$500,MATCH(B30,Projects!$A$2:$A$500,0)),"") -> Omnichannel Commerce Replatform | D30: Software & Licences | E30: 27700 | F30: 45917 | G30: Gordon Achebe | I30: =SUMIFS(Actuals!$J$2:$J$6000,Actuals!$C$2:$C$6000,B30,Actuals!$D$2:$D$6000,D30) -> 27669.73 | J30: =E30-I30 -> 30.27 | K30: =IF(E30=0,0,I30/E30) -> 0.99890722 | L30: =IF(D30="Contingency","Reserve",IF(K30>1,"Overspent",IF(K30>=BudgetNearLimit,"Near limit","Within budget"))) -> Near limit
A31: B-0030 | B31: P-1006 | C31: =IFERROR(INDEX(Projects!$B$2:$B$500,MATCH(B31,Projects!$A$2:$A$500,0)),"") -> Omnichannel Commerce Replatform | D31: Subcontractors | E31: 44700 | F31: 45917 | G31: Gordon Achebe | I31: =SUMIFS(Actuals!$J$2:$J$6000,Actuals!$C$2:$C$6000,B31,Actuals!$D$2:$D$6000,D31) -> 45403.06 | J31: =E31-I31 -> -703.06 | K31: =IF(E31=0,0,I31/E31) -> 1.0157284 | L31: =IF(D31="Contingency","Reserve",IF(K31>1,"Overspent",IF(K31>=BudgetNearLimit,"Near limit","Within budget"))) -> Overspent
A32: B-0031 | B32: P-1006 | C32: =IFERROR(INDEX(Projects!$B$2:$B$500,MATCH(B32,Projects!$A$2:$A$500,0)),"") -> Omnichannel Commerce Replatform | D32: Travel & Expenses | E32: 8200 | F32: 45917 | G32: Gordon Achebe | I32: =SUMIFS(Actuals!$J$2:$J$6000,Actuals!$C$2:$C$6000,B32,Actuals!$D$2:$D$6000,D32) -> 8297.12 | J32: =E32-I32 -> -97.12 | K32: =IF(E32=0,0,I32/E32) -> 1.0118439 | L32: =IF(D32="Contingency","Reserve",IF(K32>1,"Overspent",IF(K32>=BudgetNearLimit,"Near limit","Within budget"))) -> Overspent
A33: B-0032 | B33: P-1006 | C33: =IFERROR(INDEX(Projects!$B$2:$B$500,MATCH(B33,Projects!$A$2:$A$500,0)),"") -> Omnichannel Commerce Replatform | D33: Contingency | E33: 45600 | F33: 45917 | G33: Gordon Achebe | H33: Management reserve; drawn via CR | I33: =SUMIFS(Actuals!$J$2:$J$6000,Actuals!$C$2:$C$6000,B33,Actuals!$D$2:$D$6000,D33) -> 0 | J33: =E33-I33 -> 45600 | K33: =IF(E33=0,0,I33/E33) -> 0 | L33: =IF(D33="Contingency","Reserve",IF(K33>1,"Overspent",IF(K33>=BudgetNearLimit,"Near limit","Within budget"))) -> Reserve
A34: B-0033 | B34: P-1007 | C34: =IFERROR(INDEX(Projects!$B$2:$B$500,MATCH(B34,Projects!$A$2:$A$500,0)),"") -> Student Information System Upgrade | D34: Labour | E34: 479100 | F34: 46083 | G34: Gordon Achebe | H34: From v1 baseline estimate | I34: =SUMIFS(Actuals!$J$2:$J$6000,Actuals!$C$2:$C$6000,B34,Actuals!$D$2:$D$6000,D34) -> 197864.45 | J34: =E34-I34 -> 281235.55 | K34: =IF(E34=0,0,I34/E34) -> 0.41299196 | L34: =IF(D34="Contingency","Reserve",IF(K34>1,"Overspent",IF(K34>=BudgetNearLimit,"Near limit","Within budget"))) -> Within budget
A35: B-0034 | B35: P-1007 | C35: =IFERROR(INDEX(Projects!$B$2:$B$500,MATCH(B35,Projects!$A$2:$A$500,0)),"") -> Student Information System Upgrade | D35: Software & Licences | E35: 42800 | F35: 46083 | G35: Gordon Achebe | I35: =SUMIFS(Actuals!$J$2:$J$6000,Actuals!$C$2:$C$6000,B35,Actuals!$D$2:$D$6000,D35) -> 18377.24 | J35: =E35-I35 -> 24422.76 | K35: =IF(E35=0,0,I35/E35) -> 0.42937477 | L35: =IF(D35="Contingency","Reserve",IF(K35>1,"Overspent",IF(K35>=BudgetNearLimit,"Near limit","Within budget"))) -> Within budget
A36: B-0035 | B36: P-1007 | C36: =IFERROR(INDEX(Projects!$B$2:$B$500,MATCH(B36,Projects!$A$2:$A$500,0)),"") -> Student Information System Upgrade | D36: Subcontractors | E36: 57600 | F36: 46083 | G36: Gordon Achebe | I36: =SUMIFS(Actuals!$J$2:$J$6000,Actuals!$C$2:$C$6000,B36,Actuals!$D$2:$D$6000,D36) -> 23055.89 | J36: =E36-I36 -> 34544.11 | K36: =IF(E36=0,0,I36/E36) -> 0.40027587 | L36: =IF(D36="Contingency","Reserve",IF(K36>1,"Overspent",IF(K36>=BudgetNearLimit,"Near limit","Within budget"))) -> Within budget
A37: B-0036 | B37: P-1007 | C37: =IFERROR(INDEX(Projects!$B$2:$B$500,MATCH(B37,Projects!$A$2:$A$500,0)),"") -> Student Information System Upgrade | D37: Training | E37: 15400 | F37: 46083 | G37: Gordon Achebe | I37: =SUMIFS(Actuals!$J$2:$J$6000,Actuals!$C$2:$C$6000,B37,Actuals!$D$2:$D$6000,D37) -> 6712.26 | J37: =E37-I37 -> 8687.74 | K37: =IF(E37=0,0,I37/E37) -> 0.43586104 | L37: =IF(D37="Contingency","Reserve",IF(K37>1,"Overspent",IF(K37>=BudgetNearLimit,"Near limit","Within budget"))) -> Within budget
A38: B-0037 | B38: P-1007 | C38: =IFERROR(INDEX(Projects!$B$2:$B$500,MATCH(B38,Projects!$A$2:$A$500,0)),"") -> Student Information System Upgrade | D38: Travel & Expenses | E38: 9700 | F38: 46083 | G38: Gordon Achebe | I38: =SUMIFS(Actuals!$J$2:$J$6000,Actuals!$C$2:$C$6000,B38,Actuals!$D$2:$D$6000,D38) -> 3944.09 | J38: =E38-I38 -> 5755.91 | K38: =IF(E38=0,0,I38/E38) -> 0.40660722 | L38: =IF(D38="Contingency","Reserve",IF(K38>1,"Overspent",IF(K38>=BudgetNearLimit,"Near limit","Within budget"))) -> Within budget
A39: B-0038 | B39: P-1007 | C39: =IFERROR(INDEX(Projects!$B$2:$B$500,MATCH(B39,Projects!$A$2:$A$500,0)),"") -> Student Information System Upgrade | D39: Contingency | E39: 34800 | F39: 46083 | G39: Gordon Achebe | H39: Management reserve; drawn via CR | I39: =SUMIFS(Actuals!$J$2:$J$6000,Actuals!$C$2:$C$6000,B39,Actuals!$D$2:$D$6000,D39) -> 0 | J39: =E39-I39 -> 34800 | K39: =IF(E39=0,0,I39/E39) -> 0 | L39: =IF(D39="Contingency","Reserve",IF(K39>1,"Overspent",IF(K39>=BudgetNearLimit,"Near limit","Within budget"))) -> Reserve
A40: B-0039 | B40: P-1008 | C40: =IFERROR(INDEX(Projects!$B$2:$B$500,MATCH(B40,Projects!$A$2:$A$500,0)),"") -> Network Operations Centre Refresh | D40: Labour | E40: 357000 | F40: 46019 | G40: Gordon Achebe | H40: From v1 baseline estimate | I40: =SUMIFS(Actuals!$J$2:$J$6000,Actuals!$C$2:$C$6000,B40,Actuals!$D$2:$D$6000,D40) -> 365748.08 | J40: =E40-I40 -> -8748.08 | K40: =IF(E40=0,0,I40/E40) -> 1.0245044 | L40: =IF(D40="Contingency","Reserve",IF(K40>1,"Overspent",IF(K40>=BudgetNearLimit,"Near limit","Within budget"))) -> Overspent
A41: B-0040 | B41: P-1008 | C41: =IFERROR(INDEX(Projects!$B$2:$B$500,MATCH(B41,Projects!$A$2:$A$500,0)),"") -> Network Operations Centre Refresh | D41: Cloud Hosting | E41: 47200 | F41: 46019 | G41: Gordon Achebe | I41: =SUMIFS(Actuals!$J$2:$J$6000,Actuals!$C$2:$C$6000,B41,Actuals!$D$2:$D$6000,D41) -> 39491.94 | J41: =E41-I41 -> 7708.06 | K41: =IF(E41=0,0,I41/E41) -> 0.83669364 | L41: =IF(D41="Contingency","Reserve",IF(K41>1,"Overspent",IF(K41>=BudgetNearLimit,"Near limit","Within budget"))) -> Within budget
A42: B-0041 | B42: P-1008 | C42: =IFERROR(INDEX(Projects!$B$2:$B$500,MATCH(B42,Projects!$A$2:$A$500,0)),"") -> Network Operations Centre Refresh | D42: Hardware | E42: 30700 | F42: 46019 | G42: Gordon Achebe | I42: =SUMIFS(Actuals!$J$2:$J$6000,Actuals!$C$2:$C$6000,B42,Actuals!$D$2:$D$6000,D42) -> 34396.08 | J42: =E42-I42 -> -3696.08 | K42: =IF(E42=0,0,I42/E42) -> 1.1203935 | L42: =IF(D42="Contingency","Reserve",IF(K42>1,"Overspent",IF(K42>=BudgetNearLimit,"Near limit","Within budget"))) -> Overspent
A43: B-0042 | B43: P-1008 | C43: =IFERROR(INDEX(Projects!$B$2:$B$500,MATCH(B43,Projects!$A$2:$A$500,0)),"") -> Network Operations Centre Refresh | D43: Software & Licences | E43: 20000 | F43: 46019 | G43: Gordon Achebe | I43: =SUMIFS(Actuals!$J$2:$J$6000,Actuals!$C$2:$C$6000,B43,Actuals!$D$2:$D$6000,D43) -> 17751.31 | J43: =E43-I43 -> 2248.69 | K43: =IF(E43=0,0,I43/E43) -> 0.8875655 | L43: =IF(D43="Contingency","Reserve",IF(K43>1,"Overspent",IF(K43>=BudgetNearLimit,"Near limit","Within budget"))) -> Within budget
A44: B-0043 | B44: P-1008 | C44: =IFERROR(INDEX(Projects!$B$2:$B$500,MATCH(B44,Projects!$A$2:$A$500,0)),"") -> Network Operations Centre Refresh | D44: Travel & Expenses | E44: 7900 | F44: 46019 | G44: Gordon Achebe | I44: =SUMIFS(Actuals!$J$2:$J$6000,Actuals!$C$2:$C$6000,B44,Actuals!$D$2:$D$6000,D44) -> 7062.45 | J44: =E44-I44 -> 837.55 | K44: =IF(E44=0,0,I44/E44) -> 0.89398101 | L44: =IF(D44="Contingency","Reserve",IF(K44>1,"Overspent",IF(K44>=BudgetNearLimit,"Near limit","Within budget"))) -> Within budget
A45: B-0044 | B45: P-1008 | C45: =IFERROR(INDEX(Projects!$B$2:$B$500,MATCH(B45,Projects!$A$2:$A$500,0)),"") -> Network Operations Centre Refresh | D45: Contingency | E45: 35700 | F45: 46019 | G45: Gordon Achebe | H45: Management reserve; drawn via CR | I45: =SUMIFS(Actuals!$J$2:$J$6000,Actuals!$C$2:$C$6000,B45,Actuals!$D$2:$D$6000,D45) -> 0 | J45: =E45-I45 -> 35700 | K45: =IF(E45=0,0,I45/E45) -> 0 | L45: =IF(D45="Contingency","Reserve",IF(K45>1,"Overspent",IF(K45>=BudgetNearLimit,"Near limit","Within budget"))) -> Reserve
A46: B-0045 | B46: P-1009 | C46: =IFERROR(INDEX(Projects!$B$2:$B$500,MATCH(B46,Projects!$A$2:$A$500,0)),"") -> Smart Factory IoT Pilot | D46: Labour | E46: 276500 | F46: 46133 | G46: Helena Marsh | H46: From v1 baseline estimate | I46: =SUMIFS(Actuals!$J$2:$J$6000,Actuals!$C$2:$C$6000,B46,Actuals!$D$2:$D$6000,D46) -> 135647.6 | J46: =E46-I46 -> 140852.4 | K46: =IF(E46=0,0,I46/E46) -> 0.49058807 | L46: =IF(D46="Contingency","Reserve",IF(K46>1,"Overspent",IF(K46>=BudgetNearLimit,"Near limit","Within budget"))) -> Within budget
A47: B-0046 | B47: P-1009 | C47: =IFERROR(INDEX(Projects!$B$2:$B$500,MATCH(B47,Projects!$A$2:$A$500,0)),"") -> Smart Factory IoT Pilot | D47: Hardware | E47: 22100 | F47: 46133 | G47: Helena Marsh | I47: =SUMIFS(Actuals!$J$2:$J$6000,Actuals!$C$2:$C$6000,B47,Actuals!$D$2:$D$6000,D47) -> 13460.95 | J47: =E47-I47 -> 8639.05 | K47: =IF(E47=0,0,I47/E47) -> 0.60909276 | L47: =IF(D47="Contingency","Reserve",IF(K47>1,"Overspent",IF(K47>=BudgetNearLimit,"Near limit","Within budget"))) -> Within budget
A48: B-0047 | B48: P-1009 | C48: =IFERROR(INDEX(Projects!$B$2:$B$500,MATCH(B48,Projects!$A$2:$A$500,0)),"") -> Smart Factory IoT Pilot | D48: Software & Licences | E48: 11800 | F48: 46133 | G48: Helena Marsh | I48: =SUMIFS(Actuals!$J$2:$J$6000,Actuals!$C$2:$C$6000,B48,Actuals!$D$2:$D$6000,D48) -> 5465.55 | J48: =E48-I48 -> 6334.45 | K48: =IF(E48=0,0,I48/E48) -> 0.4631822 | L48: =IF(D48="Contingency","Reserve",IF(K48>1,"Overspent",IF(K48>=BudgetNearLimit,"Near limit","Within budget"))) -> Within budget
A49: B-0048 | B49: P-1009 | C49: =IFERROR(INDEX(Projects!$B$2:$B$500,MATCH(B49,Projects!$A$2:$A$500,0)),"") -> Smart Factory IoT Pilot | D49: Training | E49: 7100 | F49: 46133 | G49: Helena Marsh | I49: =SUMIFS(Actuals!$J$2:$J$6000,Actuals!$C$2:$C$6000,B49,Actuals!$D$2:$D$6000,D49) -> 3505.57 | J49: =E49-I49 -> 3594.43 | K49: =IF(E49=0,0,I49/E49) -> 0.49374225 | L49: =IF(D49="Contingency","Reserve",IF(K49>1,"Overspent",IF(K49>=BudgetNearLimit,"Near limit","Within budget"))) -> Within budget
A50: B-0049 | B50: P-1009 | C50: =IFERROR(INDEX(Projects!$B$2:$B$500,MATCH(B50,Projects!$A$2:$A$500,0)),"") -> Smart Factory IoT Pilot | D50: Travel & Expenses | E50: 5600 | F50: 46133 | G50: Helena Marsh | I50: =SUMIFS(Actuals!$J$2:$J$6000,Actuals!$C$2:$C$6000,B50,Actuals!$D$2:$D$6000,D50) -> 2675.86 | J50: =E50-I50 -> 2924.14 | K50: =IF(E50=0,0,I50/E50) -> 0.47783214 | L50: =IF(D50="Contingency","Reserve",IF(K50>1,"Overspent",IF(K50>=BudgetNearLimit,"Near limit","Within budget"))) -> Within budget
A51: B-0050 | B51: P-1009 | C51: =IFERROR(INDEX(Projects!$B$2:$B$500,MATCH(B51,Projects!$A$2:$A$500,0)),"") -> Smart Factory IoT Pilot | D51: Contingency | E51: 19600 | F51: 46133 | G51: Helena Marsh | H51: Management reserve; drawn via CR | I51: =SUMIFS(Actuals!$J$2:$J$6000,Actuals!$C$2:$C$6000,B51,Actuals!$D$2:$D$6000,D51) -> 0 | J51: =E51-I51 -> 19600 | K51: =IF(E51=0,0,I51/E51) -> 0 | L51: =IF(D51="Contingency","Reserve",IF(K51>1,"Overspent",IF(K51>=BudgetNearLimit,"Near limit","Within budget"))) -> Reserve
A52: B-0051 | B52: P-1010 | C52: =IFERROR(INDEX(Projects!$B$2:$B$500,MATCH(B52,Projects!$A$2:$A$500,0)),"") -> 311 Citizen Services App | D52: Labour | E52: 353500 | F52: 45981 | G52: Helena Marsh | H52: From v1 baseline estimate | I52: =SUMIFS(Actuals!$J$2:$J$6000,Actuals!$C$2:$C$6000,B52,Actuals!$D$2:$D$6000,D52) -> 442230.06 | J52: =E52-I52 -> -88730.06 | K52: =IF(E52=0,0,I52/E52) -> 1.2510044 | L52: =IF(D52="Contingency","Reserve",IF(K52>1,"Overspent",IF(K52>=BudgetNearLimit,"Near limit","Within budget"))) -> Overspent
A53: B-0052 | B53: P-1010 | C53: =IFERROR(INDEX(Projects!$B$2:$B$500,MATCH(B53,Projects!$A$2:$A$500,0)),"") -> 311 Citizen Services App | D53: Software & Licences | E53: 27700 | F53: 45981 | G53: Helena Marsh | I53: =SUMIFS(Actuals!$J$2:$J$6000,Actuals!$C$2:$C$6000,B53,Actuals!$D$2:$D$6000,D53) -> 29598.47 | J53: =E53-I53 -> -1898.47 | K53: =IF(E53=0,0,I53/E53) -> 1.0685368 | L53: =IF(D53="Contingency","Reserve",IF(K53>1,"Overspent",IF(K53>=BudgetNearLimit,"Near limit","Within budget"))) -> Overspent
A54: B-0053 | B54: P-1010 | C54: =IFERROR(INDEX(Projects!$B$2:$B$500,MATCH(B54,Projects!$A$2:$A$500,0)),"") -> 311 Citizen Services App | D54: Subcontractors | E54: 31700 | F54: 45981 | G54: Helena Marsh | I54: =SUMIFS(Actuals!$J$2:$J$6000,Actuals!$C$2:$C$6000,B54,Actuals!$D$2:$D$6000,D54) -> 34686.34 | J54: =E54-I54 -> -2986.34 | K54: =IF(E54=0,0,I54/E54) -> 1.0942063 | L54: =IF(D54="Contingency","Reserve",IF(K54>1,"Overspent",IF(K54>=BudgetNearLimit,"Near limit","Within budget"))) -> Overspent
A55: B-0054 | B55: P-1010 | C55: =IFERROR(INDEX(Projects!$B$2:$B$500,MATCH(B55,Projects!$A$2:$A$500,0)),"") -> 311 Citizen Services App | D55: Travel & Expenses | E55: 6800 | F55: 45981 | G55: Helena Marsh | I55: =SUMIFS(Actuals!$J$2:$J$6000,Actuals!$C$2:$C$6000,B55,Actuals!$D$2:$D$6000,D55) -> 7327.43 | J55: =E55-I55 -> -527.43 | K55: =IF(E55=0,0,I55/E55) -> 1.0775632 | L55: =IF(D55="Contingency","Reserve",IF(K55>1,"Overspent",IF(K55>=BudgetNearLimit,"Near limit","Within budget"))) -> Overspent
A56: B-0055 | B56: P-1010 | C56: =IFERROR(INDEX(Projects!$B$2:$B$500,MATCH(B56,Projects!$A$2:$A$500,0)),"") -> 311 Citizen Services App | D56: Contingency | E56: 35300 | F56: 45981 | G56: Helena Marsh | H56: Management reserve; drawn via CR | I56: =SUMIFS(Actuals!$J$2:$J$6000,Actuals!$C$2:$C$6000,B56,Actuals!$D$2:$D$6000,D56) -> 0 | J56: =E56-I56 -> 35300 | K56: =IF(E56=0,0,I56/E56) -> 0 | L56: =IF(D56="Contingency","Reserve",IF(K56>1,"Overspent",IF(K56>=BudgetNearLimit,"Near limit","Within budget"))) -> Reserve
A57: B-0056 | B57: P-1011 | C57: =IFERROR(INDEX(Projects!$B$2:$B$500,MATCH(B57,Projects!$A$2:$A$500,0)),"") -> Clinical Trials Data Hub | D57: Labour | E57: 500100 | F57: 46039 | G57: Gordon Achebe | H57: From v1 baseline estimate | I57: =SUMIFS(Actuals!$J$2:$J$6000,Actuals!$C$2:$C$6000,B57,Actuals!$D$2:$D$6000,D57) -> 209301.16 | J57: =E57-I57 -> 290798.84 | K57: =IF(E57=0,0,I57/E57) -> 0.41851862 | L57: =IF(D57="Contingency","Reserve",IF(K57>1,"Overspent",IF(K57>=BudgetNearLimit,"Near limit","Within budget"))) -> Within budget
A58: B-0057 | B58: P-1011 | C58: =IFERROR(INDEX(Projects!$B$2:$B$500,MATCH(B58,Projects!$A$2:$A$500,0)),"") -> Clinical Trials Data Hub | D58: Cloud Hosting | E58: 43900 | F58: 46039 | G58: Gordon Achebe | I58: =SUMIFS(Actuals!$J$2:$J$6000,Actuals!$C$2:$C$6000,B58,Actuals!$D$2:$D$6000,D58) -> 20246.91 | J58: =E58-I58 -> 23653.09 | K58: =IF(E58=0,0,I58/E58) -> 0.46120524 | L58: =IF(D58="Contingency","Reserve",IF(K58>1,"Overspent",IF(K58>=BudgetNearLimit,"Near limit","Within budget"))) -> Within budget
A59: B-0058 | B59: P-1011 | C59: =IFERROR(INDEX(Projects!$B$2:$B$500,MATCH(B59,Projects!$A$2:$A$500,0)),"") -> Clinical Trials Data Hub | D59: Software & Licences | E59: 34200 | F59: 46039 | G59: Gordon Achebe | I59: =SUMIFS(Actuals!$J$2:$J$6000,Actuals!$C$2:$C$6000,B59,Actuals!$D$2:$D$6000,D59) -> 15413.36 | J59: =E59-I59 -> 18786.64 | K59: =IF(E59=0,0,I59/E59) -> 0.45068304 | L59: =IF(D59="Contingency","Reserve",IF(K59>1,"Overspent",IF(K59>=BudgetNearLimit,"Near limit","Within budget"))) -> Within budget
A60: B-0059 | B60: P-1011 | C60: =IFERROR(INDEX(Projects!$B$2:$B$500,MATCH(B60,Projects!$A$2:$A$500,0)),"") -> Clinical Trials Data Hub | D60: Travel & Expenses | E60: 7200 | F60: 46039 | G60: Gordon Achebe | I60: =SUMIFS(Actuals!$J$2:$J$6000,Actuals!$C$2:$C$6000,B60,Actuals!$D$2:$D$6000,D60) -> 3335.98 | J60: =E60-I60 -> 3864.02 | K60: =IF(E60=0,0,I60/E60) -> 0.46333056 | L60: =IF(D60="Contingency","Reserve",IF(K60>1,"Overspent",IF(K60>=BudgetNearLimit,"Near limit","Within budget"))) -> Within budget
A61: B-0060 | B61: P-1011 | C61: =IFERROR(INDEX(Projects!$B$2:$B$500,MATCH(B61,Projects!$A$2:$A$500,0)),"") -> Clinical Trials Data Hub | D61: Contingency | E61: 35300 | F61: 46039 | G61: Gordon Achebe | H61: Management reserve; drawn via CR | I61: =SUMIFS(Actuals!$J$2:$J$6000,Actuals!$C$2:$C$6000,B61,Actuals!$D$2:$D$6000,D61) -> 0 | J61: =E61-I61 -> 35300 | K61: =IF(E61=0,0,I61/E61) -> 0 | L61: =IF(D61="Contingency","Reserve",IF(K61>1,"Overspent",IF(K61>=BudgetNearLimit,"Near limit","Within budget"))) -> Reserve
A62: B-0061 | B62: P-1012 | C62: =IFERROR(INDEX(Projects!$B$2:$B$500,MATCH(B62,Projects!$A$2:$A$500,0)),"") -> Grid Analytics Dashboard | D62: Labour | E62: 277700 | F62: 46148 | G62: Gordon Achebe | H62: From v1 baseline estimate | I62: =SUMIFS(Actuals!$J$2:$J$6000,Actuals!$C$2:$C$6000,B62,Actuals!$D$2:$D$6000,D62) -> 121112.82 | J62: =E62-I62 -> 156587.18 | K62: =IF(E62=0,0,I62/E62) -> 0.43612827 | L62: =IF(D62="Contingency","Reserve",IF(K62>1,"Overspent",IF(K62>=BudgetNearLimit,"Near limit","Within budget"))) -> Within budget
A63: B-0062 | B63: P-1012 | C63: =IFERROR(INDEX(Projects!$B$2:$B$500,MATCH(B63,Projects!$A$2:$A$500,0)),"") -> Grid Analytics Dashboard | D63: Cloud Hosting | E63: 28600 | F63: 46148 | G63: Gordon Achebe | I63: =SUMIFS(Actuals!$J$2:$J$6000,Actuals!$C$2:$C$6000,B63,Actuals!$D$2:$D$6000,D63) -> 12344.9 | J63: =E63-I63 -> 16255.1 | K63: =IF(E63=0,0,I63/E63) -> 0.43163986 | L63: =IF(D63="Contingency","Reserve",IF(K63>1,"Overspent",IF(K63>=BudgetNearLimit,"Near limit","Within budget"))) -> Within budget
A64: B-0063 | B64: P-1012 | C64: =IFERROR(INDEX(Projects!$B$2:$B$500,MATCH(B64,Projects!$A$2:$A$500,0)),"") -> Grid Analytics Dashboard | D64: Software & Licences | E64: 16100 | F64: 46148 | G64: Gordon Achebe | I64: =SUMIFS(Actuals!$J$2:$J$6000,Actuals!$C$2:$C$6000,B64,Actuals!$D$2:$D$6000,D64) -> 7072.57 | J64: =E64-I64 -> 9027.43 | K64: =IF(E64=0,0,I64/E64) -> 0.43929006 | L64: =IF(D64="Contingency","Reserve",IF(K64>1,"Overspent",IF(K64>=BudgetNearLimit,"Near limit","Within budget"))) -> Within budget
A65: B-0064 | B65: P-1012 | C65: =IFERROR(INDEX(Projects!$B$2:$B$500,MATCH(B65,Projects!$A$2:$A$500,0)),"") -> Grid Analytics Dashboard | D65: Travel & Expenses | E65: 4300 | F65: 46148 | G65: Gordon Achebe | I65: =SUMIFS(Actuals!$J$2:$J$6000,Actuals!$C$2:$C$6000,B65,Actuals!$D$2:$D$6000,D65) -> 1730.53 | J65: =E65-I65 -> 2569.47 | K65: =IF(E65=0,0,I65/E65) -> 0.40244884 | L65: =IF(D65="Contingency","Reserve",IF(K65>1,"Overspent",IF(K65>=BudgetNearLimit,"Near limit","Within budget"))) -> Within budget
A66: B-0065 | B66: P-1012 | C66: =IFERROR(INDEX(Projects!$B$2:$B$500,MATCH(B66,Projects!$A$2:$A$500,0)),"") -> Grid Analytics Dashboard | D66: Contingency | E66: 19800 | F66: 46148 | G66: Gordon Achebe | H66: Management reserve; drawn via CR | I66: =SUMIFS(Actuals!$J$2:$J$6000,Actuals!$C$2:$C$6000,B66,Actuals!$D$2:$D$6000,D66) -> 0 | J66: =E66-I66 -> 19800 | K66: =IF(E66=0,0,I66/E66) -> 0 | L66: =IF(D66="Contingency","Reserve",IF(K66>1,"Overspent",IF(K66>=BudgetNearLimit,"Near limit","Within budget"))) -> Reserve
A67: B-0066 | B67: P-1013 | C67: =IFERROR(INDEX(Projects!$B$2:$B$500,MATCH(B67,Projects!$A$2:$A$500,0)),"") -> Core Banking API Layer | D67: Labour | E67: 667400 | F67: 45866 | G67: Gordon Achebe | H67: From v1 baseline estimate | I67: =SUMIFS(Actuals!$J$2:$J$6000,Actuals!$C$2:$C$6000,B67,Actuals!$D$2:$D$6000,D67) -> 742205.97 | J67: =E67-I67 -> -74805.97 | K67: =IF(E67=0,0,I67/E67) -> 1.1120857 | L67: =IF(D67="Contingency","Reserve",IF(K67>1,"Overspent",IF(K67>=BudgetNearLimit,"Near limit","Within budget"))) -> Overspent
A68: B-0067 | B68: P-1013 | C68: =IFERROR(INDEX(Projects!$B$2:$B$500,MATCH(B68,Projects!$A$2:$A$500,0)),"") -> Core Banking API Layer | D68: Software & Licences | E68: 56000 | F68: 45866 | G68: Gordon Achebe | I68: =SUMIFS(Actuals!$J$2:$J$6000,Actuals!$C$2:$C$6000,B68,Actuals!$D$2:$D$6000,D68) -> 52279.5 | J68: =E68-I68 -> 3720.5 | K68: =IF(E68=0,0,I68/E68) -> 0.9335625 | L68: =IF(D68="Contingency","Reserve",IF(K68>1,"Overspent",IF(K68>=BudgetNearLimit,"Near limit","Within budget"))) -> Near limit
A69: B-0068 | B69: P-1013 | C69: =IFERROR(INDEX(Projects!$B$2:$B$500,MATCH(B69,Projects!$A$2:$A$500,0)),"") -> Core Banking API Layer | D69: Subcontractors | E69: 77000 | F69: 45866 | G69: Gordon Achebe | I69: =SUMIFS(Actuals!$J$2:$J$6000,Actuals!$C$2:$C$6000,B69,Actuals!$D$2:$D$6000,D69) -> 72540.8 | J69: =E69-I69 -> 4459.2 | K69: =IF(E69=0,0,I69/E69) -> 0.94208831 | L69: =IF(D69="Contingency","Reserve",IF(K69>1,"Overspent",IF(K69>=BudgetNearLimit,"Near limit","Within budget"))) -> Near limit
A70: B-0069 | B70: P-1013 | C70: =IFERROR(INDEX(Projects!$B$2:$B$500,MATCH(B70,Projects!$A$2:$A$500,0)),"") -> Core Banking API Layer | D70: Training | E70: 19500 | F70: 45866 | G70: Gordon Achebe | I70: =SUMIFS(Actuals!$J$2:$J$6000,Actuals!$C$2:$C$6000,B70,Actuals!$D$2:$D$6000,D70) -> 18815.52 | J70: =E70-I70 -> 684.48 | K70: =IF(E70=0,0,I70/E70) -> 0.96489846 | L70: =IF(D70="Contingency","Reserve",IF(K70>1,"Overspent",IF(K70>=BudgetNearLimit,"Near limit","Within budget"))) -> Near limit
A71: B-0070 | B71: P-1013 | C71: =IFERROR(INDEX(Projects!$B$2:$B$500,MATCH(B71,Projects!$A$2:$A$500,0)),"") -> Core Banking API Layer | D71: Travel & Expenses | E71: 14500 | F71: 45866 | G71: Gordon Achebe | I71: =SUMIFS(Actuals!$J$2:$J$6000,Actuals!$C$2:$C$6000,B71,Actuals!$D$2:$D$6000,D71) -> 13958.69 | J71: =E71-I71 -> 541.31 | K71: =IF(E71=0,0,I71/E71) -> 0.96266828 | L71: =IF(D71="Contingency","Reserve",IF(K71>1,"Overspent",IF(K71>=BudgetNearLimit,"Near limit","Within budget"))) -> Near limit
A72: B-0071 | B72: P-1013 | C72: =IFERROR(INDEX(Projects!$B$2:$B$500,MATCH(B72,Projects!$A$2:$A$500,0)),"") -> Core Banking API Layer | D72: Contingency | E72: 100100 | F72: 45866 | G72: Gordon Achebe | H72: Management reserve; drawn via CR | I72: =SUMIFS(Actuals!$J$2:$J$6000,Actuals!$C$2:$C$6000,B72,Actuals!$D$2:$D$6000,D72) -> 0 | J72: =E72-I72 -> 100100 | K72: =IF(E72=0,0,I72/E72) -> 0 | L72: =IF(D72="Contingency","Reserve",IF(K72>1,"Overspent",IF(K72>=BudgetNearLimit,"Near limit","Within budget"))) -> Reserve
A73: B-0072 | B73: P-1014 | C73: =IFERROR(INDEX(Projects!$B$2:$B$500,MATCH(B73,Projects!$A$2:$A$500,0)),"") -> Managed Cloud Operations | D73: Labour | E73: 679300 | F73: 45820 | G73: Helena Marsh | H73: From v1 baseline estimate | I73: =SUMIFS(Actuals!$J$2:$J$6000,Actuals!$C$2:$C$6000,B73,Actuals!$D$2:$D$6000,D73) -> 543368.13 | J73: =E73-I73 -> 135931.87 | K73: =IF(E73=0,0,I73/E73) -> 0.7998942 | L73: =IF(D73="Contingency","Reserve",IF(K73>1,"Overspent",IF(K73>=BudgetNearLimit,"Near limit","Within budget"))) -> Within budget
A74: B-0073 | B74: P-1014 | C74: =IFERROR(INDEX(Projects!$B$2:$B$500,MATCH(B74,Projects!$A$2:$A$500,0)),"") -> Managed Cloud Operations | D74: Cloud Hosting | E74: 93200 | F74: 45820 | G74: Helena Marsh | I74: =SUMIFS(Actuals!$J$2:$J$6000,Actuals!$C$2:$C$6000,B74,Actuals!$D$2:$D$6000,D74) -> 72602.16 | J74: =E74-I74 -> 20597.84 | K74: =IF(E74=0,0,I74/E74) -> 0.77899313 | L74: =IF(D74="Contingency","Reserve",IF(K74>1,"Overspent",IF(K74>=BudgetNearLimit,"Near limit","Within budget"))) -> Within budget
A75: B-0074 | B75: P-1014 | C75: =IFERROR(INDEX(Projects!$B$2:$B$500,MATCH(B75,Projects!$A$2:$A$500,0)),"") -> Managed Cloud Operations | D75: Hardware | E75: 75600 | F75: 45820 | G75: Helena Marsh | I75: =SUMIFS(Actuals!$J$2:$J$6000,Actuals!$C$2:$C$6000,B75,Actuals!$D$2:$D$6000,D75) -> 75398.73 | J75: =E75-I75 -> 201.27 | K75: =IF(E75=0,0,I75/E75) -> 0.9973377 | L75: =IF(D75="Contingency","Reserve",IF(K75>1,"Overspent",IF(K75>=BudgetNearLimit,"Near limit","Within budget"))) -> Near limit
A76: B-0075 | B76: P-1014 | C76: =IFERROR(INDEX(Projects!$B$2:$B$500,MATCH(B76,Projects!$A$2:$A$500,0)),"") -> Managed Cloud Operations | D76: Software & Licences | E76: 33100 | F76: 45820 | G76: Helena Marsh | I76: =SUMIFS(Actuals!$J$2:$J$6000,Actuals!$C$2:$C$6000,B76,Actuals!$D$2:$D$6000,D76) -> 24630.91 | J76: =E76-I76 -> 8469.09 | K76: =IF(E76=0,0,I76/E76) -> 0.74413625 | L76: =IF(D76="Contingency","Reserve",IF(K76>1,"Overspent",IF(K76>=BudgetNearLimit,"Near limit","Within budget"))) -> Within budget
A77: B-0076 | B77: P-1014 | C77: =IFERROR(INDEX(Projects!$B$2:$B$500,MATCH(B77,Projects!$A$2:$A$500,0)),"") -> Managed Cloud Operations | D77: Travel & Expenses | E77: 13400 | F77: 45820 | G77: Helena Marsh | I77: =SUMIFS(Actuals!$J$2:$J$6000,Actuals!$C$2:$C$6000,B77,Actuals!$D$2:$D$6000,D77) -> 10209.65 | J77: =E77-I77 -> 3190.35 | K77: =IF(E77=0,0,I77/E77) -> 0.76191418 | L77: =IF(D77="Contingency","Reserve",IF(K77>1,"Overspent",IF(K77>=BudgetNearLimit,"Near limit","Within budget"))) -> Within budget
A78: B-0077 | B78: P-1014 | C78: =IFERROR(INDEX(Projects!$B$2:$B$500,MATCH(B78,Projects!$A$2:$A$500,0)),"") -> Managed Cloud Operations | D78: Contingency | E78: 49300 | F78: 45820 | G78: Helena Marsh | H78: Management reserve; drawn via CR | I78: =SUMIFS(Actuals!$J$2:$J$6000,Actuals!$C$2:$C$6000,B78,Actuals!$D$2:$D$6000,D78) -> 0 | J78: =E78-I78 -> 49300 | K78: =IF(E78=0,0,I78/E78) -> 0 | L78: =IF(D78="Contingency","Reserve",IF(K78>1,"Overspent",IF(K78>=BudgetNearLimit,"Near limit","Within budget"))) -> Reserve
A79: B-0078 | B79: P-1015 | C79: =IFERROR(INDEX(Projects!$B$2:$B$500,MATCH(B79,Projects!$A$2:$A$500,0)),"") -> Policy Admin Consolidation | D79: Labour | E79: 661800 | F79: 46084 | G79: Gordon Achebe | H79: From v1 baseline estimate | I79: =SUMIFS(Actuals!$J$2:$J$6000,Actuals!$C$2:$C$6000,B79,Actuals!$D$2:$D$6000,D79) -> 272909.89 | J79: =E79-I79 -> 388890.11 | K79: =IF(E79=0,0,I79/E79) -> 0.41237517 | L79: =IF(D79="Contingency","Reserve",IF(K79>1,"Overspent",IF(K79>=BudgetNearLimit,"Near limit","Within budget"))) -> Within budget
A80: B-0079 | B80: P-1015 | C80: =IFERROR(INDEX(Projects!$B$2:$B$500,MATCH(B80,Projects!$A$2:$A$500,0)),"") -> Policy Admin Consolidation | D80: Software & Licences | E80: 60200 | F80: 46084 | G80: Gordon Achebe | I80: =SUMIFS(Actuals!$J$2:$J$6000,Actuals!$C$2:$C$6000,B80,Actuals!$D$2:$D$6000,D80) -> 24291.8 | J80: =E80-I80 -> 35908.2 | K80: =IF(E80=0,0,I80/E80) -> 0.40351827 | L80: =IF(D80="Contingency","Reserve",IF(K80>1,"Overspent",IF(K80>=BudgetNearLimit,"Near limit","Within budget"))) -> Within budget
A81: B-0080 | B81: P-1015 | C81: =IFERROR(INDEX(Projects!$B$2:$B$500,MATCH(B81,Projects!$A$2:$A$500,0)),"") -> Policy Admin Consolidation | D81: Subcontractors | E81: 71100 | F81: 46084 | G81: Gordon Achebe | I81: =SUMIFS(Actuals!$J$2:$J$6000,Actuals!$C$2:$C$6000,B81,Actuals!$D$2:$D$6000,D81) -> 28461.26 | J81: =E81-I81 -> 42638.74 | K81: =IF(E81=0,0,I81/E81) -> 0.40029902 | L81: =IF(D81="Contingency","Reserve",IF(K81>1,"Overspent",IF(K81>=BudgetNearLimit,"Near limit","Within budget"))) -> Within budget
A82: B-0081 | B82: P-1015 | C82: =IFERROR(INDEX(Projects!$B$2:$B$500,MATCH(B82,Projects!$A$2:$A$500,0)),"") -> Policy Admin Consolidation | D82: Training | E82: 19100 | F82: 46084 | G82: Gordon Achebe | I82: =SUMIFS(Actuals!$J$2:$J$6000,Actuals!$C$2:$C$6000,B82,Actuals!$D$2:$D$6000,D82) -> 8001.7 | J82: =E82-I82 -> 11098.3 | K82: =IF(E82=0,0,I82/E82) -> 0.41893717 | L82: =IF(D82="Contingency","Reserve",IF(K82>1,"Overspent",IF(K82>=BudgetNearLimit,"Near limit","Within budget"))) -> Within budget
A83: B-0082 | B83: P-1015 | C83: =IFERROR(INDEX(Projects!$B$2:$B$500,MATCH(B83,Projects!$A$2:$A$500,0)),"") -> Policy Admin Consolidation | D83: Travel & Expenses | E83: 14400 | F83: 46084 | G83: Gordon Achebe | I83: =SUMIFS(Actuals!$J$2:$J$6000,Actuals!$C$2:$C$6000,B83,Actuals!$D$2:$D$6000,D83) -> 6086.18 | J83: =E83-I83 -> 8313.82 | K83: =IF(E83=0,0,I83/E83) -> 0.42265139 | L83: =IF(D83="Contingency","Reserve",IF(K83>1,"Overspent",IF(K83>=BudgetNearLimit,"Near limit","Within budget"))) -> Within budget
A84: B-0083 | B84: P-1015 | C84: =IFERROR(INDEX(Projects!$B$2:$B$500,MATCH(B84,Projects!$A$2:$A$500,0)),"") -> Policy Admin Consolidation | D84: Contingency | E84: 66200 | F84: 46084 | G84: Gordon Achebe | H84: Management reserve; drawn via CR | I84: =SUMIFS(Actuals!$J$2:$J$6000,Actuals!$C$2:$C$6000,B84,Actuals!$D$2:$D$6000,D84) -> 0 | J84: =E84-I84 -> 66200 | K84: =IF(E84=0,0,I84/E84) -> 0 | L84: =IF(D84="Contingency","Reserve",IF(K84>1,"Overspent",IF(K84>=BudgetNearLimit,"Near limit","Within budget"))) -> Reserve
A85: B-0084 | B85: P-1016 | C85: =IFERROR(INDEX(Projects!$B$2:$B$500,MATCH(B85,Projects!$A$2:$A$500,0)),"") -> Warehouse Robotics Integration | D85: Labour | E85: 224900 | F85: 46106 | G85: Helena Marsh | H85: From v1 baseline estimate | I85: =SUMIFS(Actuals!$J$2:$J$6000,Actuals!$C$2:$C$6000,B85,Actuals!$D$2:$D$6000,D85) -> 134731.62 | J85: =E85-I85 -> 90168.38 | K85: =IF(E85=0,0,I85/E85) -> 0.59907345 | L85: =IF(D85="Contingency","Reserve",IF(K85>1,"Overspent",IF(K85>=BudgetNearLimit,"Near limit","Within budget"))) -> Within budget
A86: B-0085 | B86: P-1016 | C86: =IFERROR(INDEX(Projects!$B$2:$B$500,MATCH(B86,Projects!$A$2:$A$500,0)),"") -> Warehouse Robotics Integration | D86: Hardware | E86: 20600 | F86: 46106 | G86: Helena Marsh | I86: =SUMIFS(Actuals!$J$2:$J$6000,Actuals!$C$2:$C$6000,B86,Actuals!$D$2:$D$6000,D86) -> 20222.4 | J86: =E86-I86 -> 377.6 | K86: =IF(E86=0,0,I86/E86) -> 0.9816699 | L86: =IF(D86="Contingency","Reserve",IF(K86>1,"Overspent",IF(K86>=BudgetNearLimit,"Near limit","Within budget"))) -> Near limit
A87: B-0086 | B87: P-1016 | C87: =IFERROR(INDEX(Projects!$B$2:$B$500,MATCH(B87,Projects!$A$2:$A$500,0)),"") -> Warehouse Robotics Integration | D87: Software & Licences | E87: 11100 | F87: 46106 | G87: Helena Marsh | I87: =SUMIFS(Actuals!$J$2:$J$6000,Actuals!$C$2:$C$6000,B87,Actuals!$D$2:$D$6000,D87) -> 7017.05 | J87: =E87-I87 -> 4082.95 | K87: =IF(E87=0,0,I87/E87) -> 0.63216667 | L87: =IF(D87="Contingency","Reserve",IF(K87>1,"Overspent",IF(K87>=BudgetNearLimit,"Near limit","Within budget"))) -> Within budget
A88: B-0087 | B88: P-1016 | C88: =IFERROR(INDEX(Projects!$B$2:$B$500,MATCH(B88,Projects!$A$2:$A$500,0)),"") -> Warehouse Robotics Integration | D88: Training | E88: 6100 | F88: 46106 | G88: Helena Marsh | I88: =SUMIFS(Actuals!$J$2:$J$6000,Actuals!$C$2:$C$6000,B88,Actuals!$D$2:$D$6000,D88) -> 3771.52 | J88: =E88-I88 -> 2328.48 | K88: =IF(E88=0,0,I88/E88) -> 0.61828197 | L88: =IF(D88="Contingency","Reserve",IF(K88>1,"Overspent",IF(K88>=BudgetNearLimit,"Near limit","Within budget"))) -> Within budget
A89: B-0088 | B89: P-1016 | C89: =IFERROR(INDEX(Projects!$B$2:$B$500,MATCH(B89,Projects!$A$2:$A$500,0)),"") -> Warehouse Robotics Integration | D89: Travel & Expenses | E89: 4600 | F89: 46106 | G89: Helena Marsh | I89: =SUMIFS(Actuals!$J$2:$J$6000,Actuals!$C$2:$C$6000,B89,Actuals!$D$2:$D$6000,D89) -> 2869.44 | J89: =E89-I89 -> 1730.56 | K89: =IF(E89=0,0,I89/E89) -> 0.6237913 | L89: =IF(D89="Contingency","Reserve",IF(K89>1,"Overspent",IF(K89>=BudgetNearLimit,"Near limit","Within budget"))) -> Within budget
A90: B-0089 | B90: P-1016 | C90: =IFERROR(INDEX(Projects!$B$2:$B$500,MATCH(B90,Projects!$A$2:$A$500,0)),"") -> Warehouse Robotics Integration | D90: Contingency | E90: 16400 | F90: 46106 | G90: Helena Marsh | H90: Management reserve; drawn via CR | I90: =SUMIFS(Actuals!$J$2:$J$6000,Actuals!$C$2:$C$6000,B90,Actuals!$D$2:$D$6000,D90) -> 0 | J90: =E90-I90 -> 16400 | K90: =IF(E90=0,0,I90/E90) -> 0 | L90: =IF(D90="Contingency","Reserve",IF(K90>1,"Overspent",IF(K90>=BudgetNearLimit,"Near limit","Within budget"))) -> Reserve
A91: B-0090 | B91: P-1017 | C91: =IFERROR(INDEX(Projects!$B$2:$B$500,MATCH(B91,Projects!$A$2:$A$500,0)),"") -> Loyalty Program Relaunch | D91: Labour | E91: 254300 | F91: 46024 | G91: Helena Marsh | H91: From v1 baseline estimate | I91: =SUMIFS(Actuals!$J$2:$J$6000,Actuals!$C$2:$C$6000,B91,Actuals!$D$2:$D$6000,D91) -> 323638.17 | J91: =E91-I91 -> -69338.17 | K91: =IF(E91=0,0,I91/E91) -> 1.2726629 | L91: =IF(D91="Contingency","Reserve",IF(K91>1,"Overspent",IF(K91>=BudgetNearLimit,"Near limit","Within budget"))) -> Overspent
A92: B-0091 | B92: P-1017 | C92: =IFERROR(INDEX(Projects!$B$2:$B$500,MATCH(B92,Projects!$A$2:$A$500,0)),"") -> Loyalty Program Relaunch | D92: Software & Licences | E92: 17200 | F92: 46024 | G92: Helena Marsh | I92: =SUMIFS(Actuals!$J$2:$J$6000,Actuals!$C$2:$C$6000,B92,Actuals!$D$2:$D$6000,D92) -> 17904.88 | J92: =E92-I92 -> -704.88 | K92: =IF(E92=0,0,I92/E92) -> 1.0409814 | L92: =IF(D92="Contingency","Reserve",IF(K92>1,"Overspent",IF(K92>=BudgetNearLimit,"Near limit","Within budget"))) -> Overspent
A93: B-0092 | B93: P-1017 | C93: =IFERROR(INDEX(Projects!$B$2:$B$500,MATCH(B93,Projects!$A$2:$A$500,0)),"") -> Loyalty Program Relaunch | D93: Subcontractors | E93: 22400 | F93: 46024 | G93: Helena Marsh | I93: =SUMIFS(Actuals!$J$2:$J$6000,Actuals!$C$2:$C$6000,B93,Actuals!$D$2:$D$6000,D93) -> 24550.03 | J93: =E93-I93 -> -2150.03 | K93: =IF(E93=0,0,I93/E93) -> 1.0959835 | L93: =IF(D93="Contingency","Reserve",IF(K93>1,"Overspent",IF(K93>=BudgetNearLimit,"Near limit","Within budget"))) -> Overspent
A94: B-0093 | B94: P-1017 | C94: =IFERROR(INDEX(Projects!$B$2:$B$500,MATCH(B94,Projects!$A$2:$A$500,0)),"") -> Loyalty Program Relaunch | D94: Travel & Expenses | E94: 4700 | F94: 46024 | G94: Helena Marsh | I94: =SUMIFS(Actuals!$J$2:$J$6000,Actuals!$C$2:$C$6000,B94,Actuals!$D$2:$D$6000,D94) -> 5102.35 | J94: =E94-I94 -> -402.35 | K94: =IF(E94=0,0,I94/E94) -> 1.0856064 | L94: =IF(D94="Contingency","Reserve",IF(K94>1,"Overspent",IF(K94>=BudgetNearLimit,"Near limit","Within budget"))) -> Overspent
A95: B-0094 | B95: P-1017 | C95: =IFERROR(INDEX(Projects!$B$2:$B$500,MATCH(B95,Projects!$A$2:$A$500,0)),"") -> Loyalty Program Relaunch | D95: Contingency | E95: 25400 | F95: 46024 | G95: Helena Marsh | H95: Management reserve; drawn via CR | I95: =SUMIFS(Actuals!$J$2:$J$6000,Actuals!$C$2:$C$6000,B95,Actuals!$D$2:$D$6000,D95) -> 0 | J95: =E95-I95 -> 25400 | K95: =IF(E95=0,0,I95/E95) -> 0 | L95: =IF(D95="Contingency","Reserve",IF(K95>1,"Overspent",IF(K95>=BudgetNearLimit,"Near limit","Within budget"))) -> Reserve
A96: B-0095 | B96: P-1018 | C96: =IFERROR(INDEX(Projects!$B$2:$B$500,MATCH(B96,Projects!$A$2:$A$500,0)),"") -> Cybersecurity Posture Assessment | D96: Labour | E96: 305700 | F96: 45803 | G96: Helena Marsh | H96: From v1 baseline estimate | I96: =SUMIFS(Actuals!$J$2:$J$6000,Actuals!$C$2:$C$6000,B96,Actuals!$D$2:$D$6000,D96) -> 297113.52 | J96: =E96-I96 -> 8586.48 | K96: =IF(E96=0,0,I96/E96) -> 0.97191207 | L96: =IF(D96="Contingency","Reserve",IF(K96>1,"Overspent",IF(K96>=BudgetNearLimit,"Near limit","Within budget"))) -> Near limit
A97: B-0096 | B97: P-1018 | C97: =IFERROR(INDEX(Projects!$B$2:$B$500,MATCH(B97,Projects!$A$2:$A$500,0)),"") -> Cybersecurity Posture Assessment | D97: Cloud Hosting | E97: 42200 | F97: 45803 | G97: Helena Marsh | I97: =SUMIFS(Actuals!$J$2:$J$6000,Actuals!$C$2:$C$6000,B97,Actuals!$D$2:$D$6000,D97) -> 39781.05 | J97: =E97-I97 -> 2418.95 | K97: =IF(E97=0,0,I97/E97) -> 0.94267891 | L97: =IF(D97="Contingency","Reserve",IF(K97>1,"Overspent",IF(K97>=BudgetNearLimit,"Near limit","Within budget"))) -> Near limit
A98: B-0097 | B98: P-1018 | C98: =IFERROR(INDEX(Projects!$B$2:$B$500,MATCH(B98,Projects!$A$2:$A$500,0)),"") -> Cybersecurity Posture Assessment | D98: Hardware | E98: 32700 | F98: 45803 | G98: Helena Marsh | I98: =SUMIFS(Actuals!$J$2:$J$6000,Actuals!$C$2:$C$6000,B98,Actuals!$D$2:$D$6000,D98) -> 31326.96 | J98: =E98-I98 -> 1373.04 | K98: =IF(E98=0,0,I98/E98) -> 0.95801101 | L98: =IF(D98="Contingency","Reserve",IF(K98>1,"Overspent",IF(K98>=BudgetNearLimit,"Near limit","Within budget"))) -> Near limit
A99: B-0098 | B99: P-1018 | C99: =IFERROR(INDEX(Projects!$B$2:$B$500,MATCH(B99,Projects!$A$2:$A$500,0)),"") -> Cybersecurity Posture Assessment | D99: Software & Licences | E99: 13800 | F99: 45803 | G99: Helena Marsh | I99: =SUMIFS(Actuals!$J$2:$J$6000,Actuals!$C$2:$C$6000,B99,Actuals!$D$2:$D$6000,D99) -> 12874.54 | J99: =E99-I99 -> 925.46 | K99: =IF(E99=0,0,I99/E99) -> 0.93293768 | L99: =IF(D99="Contingency","Reserve",IF(K99>1,"Overspent",IF(K99>=BudgetNearLimit,"Near limit","Within budget"))) -> Near limit
A100: B-0099 | B100: P-1018 | C100: =IFERROR(INDEX(Projects!$B$2:$B$500,MATCH(B100,Projects!$A$2:$A$500,0)),"") -> Cybersecurity Posture Assessment | D100: Travel & Expenses | E100: 5700 | F100: 45803 | G100: Helena Marsh | I100: =SUMIFS(Actuals!$J$2:$J$6000,Actuals!$C$2:$C$6000,B100,Actuals!$D$2:$D$6000,D100) -> 5454.26 | J100: =E100-I100 -> 245.74 | K100: =IF(E100=0,0,I100/E100) -> 0.95688772 | L100: =IF(D100="Contingency","Reserve",IF(K100>1,"Overspent",IF(K100>=BudgetNearLimit,"Near limit","Within budget"))) -> Near limit
...

Sheet Actuals
A1: ActualID | B1: Period | C1: ProjectID | D1: CostCategory | E1: EmployeeID | F1: Vendor | G1: Source | H1: Hours | I1: Billable | J1: Amount | K1: PeriodLabel | L1: Portfolio | M1: BillableValue
A2: ACT-00001 | B2: 45808 | C2: P-1019 | D2: Labour | E2: E-0010 | G2: Timesheet | H2: 86.5 | I2: Yes | J2: 7612 | K2: =TEXT(B2,"yyyy-mm") -> 2025-05 | L2: =IFERROR(INDEX(Projects!$E$2:$E$500,MATCH(C2,Projects!$A$2:$A$500,0)),"") -> Digital Transformation | M2: =IF(I2="Yes",H2*INDEX(Resources!$I$2:$I$500,MATCH(E2,Resources!$A$2:$A$500,0)),0) -> 15137.5
A3: ACT-00002 | B3: 45808 | C3: P-1019 | D3: Labour | E3: E-0013 | G3: Timesheet | H3: 41.9 | I3: Yes | J3: 5068.22 | K3: =TEXT(B3,"yyyy-mm") -> 2025-05 | L3: =IFERROR(INDEX(Projects!$E$2:$E$500,MATCH(C3,Projects!$A$2:$A$500,0)),"") -> Digital Transformation | M3: =IF(I3="Yes",H3*INDEX(Resources!$I$2:$I$500,MATCH(E3,Resources!$A$2:$A$500,0)),0) -> 10265.5
A4: ACT-00003 | B4: 45808 | C4: P-1019 | D4: Labour | E4: E-0017 | G4: Timesheet | H4: 131.6 | I4: Yes | J4: 8322.38 | K4: =TEXT(B4,"yyyy-mm") -> 2025-05 | L4: =IFERROR(INDEX(Projects!$E$2:$E$500,MATCH(C4,Projects!$A$2:$A$500,0)),"") -> Digital Transformation | M4: =IF(I4="Yes",H4*INDEX(Resources!$I$2:$I$500,MATCH(E4,Resources!$A$2:$A$500,0)),0) -> 17108
A5: ACT-00004 | B5: 45808 | C5: P-1019 | D5: Labour | E5: E-0025 | G5: Timesheet | H5: 133.3 | I5: Yes | J5: 14256.44 | K5: =TEXT(B5,"yyyy-mm") -> 2025-05 | L5: =IFERROR(INDEX(Projects!$E$2:$E$500,MATCH(C5,Projects!$A$2:$A$500,0)),"") -> Digital Transformation | M5: =IF(I5="Yes",H5*INDEX(Resources!$I$2:$I$500,MATCH(E5,Resources!$A$2:$A$500,0)),0) -> 22661
A6: ACT-00005 | B6: 45808 | C6: P-1019 | D6: Labour | E6: E-0034 | G6: Timesheet | H6: 133.7 | I6: Yes | J6: 7273.28 | K6: =TEXT(B6,"yyyy-mm") -> 2025-05 | L6: =IFERROR(INDEX(Projects!$E$2:$E$500,MATCH(C6,Projects!$A$2:$A$500,0)),"") -> Digital Transformation | M6: =IF(I6="Yes",H6*INDEX(Resources!$I$2:$I$500,MATCH(E6,Resources!$A$2:$A$500,0)),0) -> 14707
A7: ACT-00006 | B7: 45808 | C7: P-1019 | D7: Software & Licences | F7: Figma Inc. | G7: AP Invoice | H7: 0 | I7: No | J7: 3056.49 | K7: =TEXT(B7,"yyyy-mm") -> 2025-05 | L7: =IFERROR(INDEX(Projects!$E$2:$E$500,MATCH(C7,Projects!$A$2:$A$500,0)),"") -> Digital Transformation | M7: =IF(I7="Yes",H7*INDEX(Resources!$I$2:$I$500,MATCH(E7,Resources!$A$2:$A$500,0)),0) -> 0
A8: ACT-00007 | B8: 45808 | C8: P-1019 | D8: Subcontractors | F8: NorthByte Testing | G8: AP Invoice | H8: 0 | I8: No | J8: 5410.8 | K8: =TEXT(B8,"yyyy-mm") -> 2025-05 | L8: =IFERROR(INDEX(Projects!$E$2:$E$500,MATCH(C8,Projects!$A$2:$A$500,0)),"") -> Digital Transformation | M8: =IF(I8="Yes",H8*INDEX(Resources!$I$2:$I$500,MATCH(E8,Resources!$A$2:$A$500,0)),0) -> 0
A9: ACT-00008 | B9: 45808 | C9: P-1019 | D9: Training | F9: Learning Tree | G9: AP Invoice | H9: 0 | I9: No | J9: 1502.46 | K9: =TEXT(B9,"yyyy-mm") -> 2025-05 | L9: =IFERROR(INDEX(Projects!$E$2:$E$500,MATCH(C9,Projects!$A$2:$A$500,0)),"") -> Digital Transformation | M9: =IF(I9="Yes",H9*INDEX(Resources!$I$2:$I$500,MATCH(E9,Resources!$A$2:$A$500,0)),0) -> 0
A10: ACT-00009 | B10: 45808 | C10: P-1019 | D10: Travel & Expenses | F10: Corporate Travel (Navan) | G10: Expense Claim | H10: 0 | I10: No | J10: 1069.75 | K10: =TEXT(B10,"yyyy-mm") -> 2025-05 | L10: =IFERROR(INDEX(Projects!$E$2:$E$500,MATCH(C10,Projects!$A$2:$A$500,0)),"") -> Digital Transformation | M10: =IF(I10="Yes",H10*INDEX(Resources!$I$2:$I$500,MATCH(E10,Resources!$A$2:$A$500,0)),0) -> 0
A11: ACT-00010 | B11: 45838 | C11: P-1018 | D11: Cloud Hosting | F11: Microsoft Azure | G11: AP Invoice | H11: 0 | I11: No | J11: 5405.35 | K11: =TEXT(B11,"yyyy-mm") -> 2025-06 | L11: =IFERROR(INDEX(Projects!$E$2:$E$500,MATCH(C11,Projects!$A$2:$A$500,0)),"") -> Cloud & Infrastructure | M11: =IF(I11="Yes",H11*INDEX(Resources!$I$2:$I$500,MATCH(E11,Resources!$A$2:$A$500,0)),0) -> 0
A12: ACT-00011 | B12: 45838 | C12: P-1018 | D12: Labour | E12: E-0006 | G12: Timesheet | H12: 75.7 | I12: Yes | J12: 6661.6 | K12: =TEXT(B12,"yyyy-mm") -> 2025-06 | L12: =IFERROR(INDEX(Projects!$E$2:$E$500,MATCH(C12,Projects!$A$2:$A$500,0)),"") -> Cloud & Infrastructure | M12: =IF(I12="Yes",H12*INDEX(Resources!$I$2:$I$500,MATCH(E12,Resources!$A$2:$A$500,0)),0) -> 13247.5
A13: ACT-00012 | B13: 45838 | C13: P-1018 | D13: Labour | E13: E-0012 | G13: Timesheet | H13: 37.9 | I13: Yes | J13: 4923.97 | K13: =TEXT(B13,"yyyy-mm") -> 2025-06 | L13: =IFERROR(INDEX(Projects!$E$2:$E$500,MATCH(C13,Projects!$A$2:$A$500,0)),"") -> Cloud & Infrastructure | M13: =IF(I13="Yes",H13*INDEX(Resources!$I$2:$I$500,MATCH(E13,Resources!$A$2:$A$500,0)),0) -> 9854
A14: ACT-00013 | B14: 45838 | C14: P-1018 | D14: Labour | E14: E-0027 | G14: Timesheet | H14: 83.2 | I14: Yes | J14: 8266.75 | K14: =TEXT(B14,"yyyy-mm") -> 2025-06 | L14: =IFERROR(INDEX(Projects!$E$2:$E$500,MATCH(C14,Projects!$A$2:$A$500,0)),"") -> Cloud & Infrastructure | M14: =IF(I14="Yes",H14*INDEX(Resources!$I$2:$I$500,MATCH(E14,Resources!$A$2:$A$500,0)),0) -> 16640
A15: ACT-00014 | B15: 45838 | C15: P-1018 | D15: Labour | E15: E-0055 | G15: Timesheet | H15: 157.3 | I15: Yes | J15: 17151.99 | K15: =TEXT(B15,"yyyy-mm") -> 2025-06 | L15: =IFERROR(INDEX(Projects!$E$2:$E$500,MATCH(C15,Projects!$A$2:$A$500,0)),"") -> Cloud & Infrastructure | M15: =IF(I15="Yes",H15*INDEX(Resources!$I$2:$I$500,MATCH(E15,Resources!$A$2:$A$500,0)),0) -> 34606
A16: ACT-00015 | B16: 45838 | C16: P-1018 | D16: Labour | E16: E-0061 | G16: Timesheet | H16: 80.7 | I16: Yes | J16: 6940.2 | K16: =TEXT(B16,"yyyy-mm") -> 2025-06 | L16: =IFERROR(INDEX(Projects!$E$2:$E$500,MATCH(C16,Projects!$A$2:$A$500,0)),"") -> Cloud & Infrastructure | M16: =IF(I16="Yes",H16*INDEX(Resources!$I$2:$I$500,MATCH(E16,Resources!$A$2:$A$500,0)),0) -> 14122.5
A17: ACT-00016 | B17: 45838 | C17: P-1018 | D17: Software & Licences | F17: Figma Inc. | G17: AP Invoice | H17: 0 | I17: No | J17: 1862.73 | K17: =TEXT(B17,"yyyy-mm") -> 2025-06 | L17: =IFERROR(INDEX(Projects!$E$2:$E$500,MATCH(C17,Projects!$A$2:$A$500,0)),"") -> Cloud & Infrastructure | M17: =IF(I17="Yes",H17*INDEX(Resources!$I$2:$I$500,MATCH(E17,Resources!$A$2:$A$500,0)),0) -> 0
A18: ACT-00017 | B18: 45838 | C18: P-1018 | D18: Travel & Expenses | F18: Corporate Travel (Navan) | G18: Expense Claim | H18: 0 | I18: No | J18: 903.53 | K18: =TEXT(B18,"yyyy-mm") -> 2025-06 | L18: =IFERROR(INDEX(Projects!$E$2:$E$500,MATCH(C18,Projects!$A$2:$A$500,0)),"") -> Cloud & Infrastructure | M18: =IF(I18="Yes",H18*INDEX(Resources!$I$2:$I$500,MATCH(E18,Resources!$A$2:$A$500,0)),0) -> 0
A19: ACT-00018 | B19: 45838 | C19: P-1019 | D19: Labour | E19: E-0010 | G19: Timesheet | H19: 88.4 | I19: Yes | J19: 7779.2 | K19: =TEXT(B19,"yyyy-mm") -> 2025-06 | L19: =IFERROR(INDEX(Projects!$E$2:$E$500,MATCH(C19,Projects!$A$2:$A$500,0)),"") -> Digital Transformation | M19: =IF(I19="Yes",H19*INDEX(Resources!$I$2:$I$500,MATCH(E19,Resources!$A$2:$A$500,0)),0) -> 15470
A20: ACT-00019 | B20: 45838 | C20: P-1019 | D20: Labour | E20: E-0013 | G20: Timesheet | H20: 45.1 | I20: Yes | J20: 5455.3 | K20: =TEXT(B20,"yyyy-mm") -> 2025-06 | L20: =IFERROR(INDEX(Projects!$E$2:$E$500,MATCH(C20,Projects!$A$2:$A$500,0)),"") -> Digital Transformation | M20: =IF(I20="Yes",H20*INDEX(Resources!$I$2:$I$500,MATCH(E20,Resources!$A$2:$A$500,0)),0) -> 11049.5
A21: ACT-00020 | B21: 45838 | C21: P-1019 | D21: Labour | E21: E-0017 | G21: Timesheet | H21: 145.4 | I21: Yes | J21: 9195.1 | K21: =TEXT(B21,"yyyy-mm") -> 2025-06 | L21: =IFERROR(INDEX(Projects!$E$2:$E$500,MATCH(C21,Projects!$A$2:$A$500,0)),"") -> Digital Transformation | M21: =IF(I21="Yes",H21*INDEX(Resources!$I$2:$I$500,MATCH(E21,Resources!$A$2:$A$500,0)),0) -> 18902
A22: ACT-00021 | B22: 45838 | C22: P-1019 | D22: Labour | E22: E-0025 | G22: Timesheet | H22: 147.8 | I22: Yes | J22: 15807.21 | K22: =TEXT(B22,"yyyy-mm") -> 2025-06 | L22: =IFERROR(INDEX(Projects!$E$2:$E$500,MATCH(C22,Projects!$A$2:$A$500,0)),"") -> Digital Transformation | M22: =IF(I22="Yes",H22*INDEX(Resources!$I$2:$I$500,MATCH(E22,Resources!$A$2:$A$500,0)),0) -> 25126
A23: ACT-00022 | B23: 45838 | C23: P-1019 | D23: Labour | E23: E-0034 | G23: Timesheet | H23: 148.7 | I23: Yes | J23: 8089.28 | K23: =TEXT(B23,"yyyy-mm") -> 2025-06 | L23: =IFERROR(INDEX(Projects!$E$2:$E$500,MATCH(C23,Projects!$A$2:$A$500,0)),"") -> Digital Transformation | M23: =IF(I23="Yes",H23*INDEX(Resources!$I$2:$I$500,MATCH(E23,Resources!$A$2:$A$500,0)),0) -> 16357
A24: ACT-00023 | B24: 45838 | C24: P-1019 | D24: Software & Licences | F24: Figma Inc. | G24: AP Invoice | H24: 0 | I24: No | J24: 3700.14 | K24: =TEXT(B24,"yyyy-mm") -> 2025-06 | L24: =IFERROR(INDEX(Projects!$E$2:$E$500,MATCH(C24,Projects!$A$2:$A$500,0)),"") -> Digital Transformation | M24: =IF(I24="Yes",H24*INDEX(Resources!$I$2:$I$500,MATCH(E24,Resources!$A$2:$A$500,0)),0) -> 0
A25: ACT-00024 | B25: 45838 | C25: P-1019 | D25: Subcontractors | F25: NorthByte Testing | G25: AP Invoice | H25: 0 | I25: No | J25: 6708.67 | K25: =TEXT(B25,"yyyy-mm") -> 2025-06 | L25: =IFERROR(INDEX(Projects!$E$2:$E$500,MATCH(C25,Projects!$A$2:$A$500,0)),"") -> Digital Transformation | M25: =IF(I25="Yes",H25*INDEX(Resources!$I$2:$I$500,MATCH(E25,Resources!$A$2:$A$500,0)),0) -> 0
A26: ACT-00025 | B26: 45838 | C26: P-1019 | D26: Training | F26: Learning Tree | G26: AP Invoice | H26: 0 | I26: No | J26: 1339.38 | K26: =TEXT(B26,"yyyy-mm") -> 2025-06 | L26: =IFERROR(INDEX(Projects!$E$2:$E$500,MATCH(C26,Projects!$A$2:$A$500,0)),"") -> Digital Transformation | M26: =IF(I26="Yes",H26*INDEX(Resources!$I$2:$I$500,MATCH(E26,Resources!$A$2:$A$500,0)),0) -> 0
A27: ACT-00026 | B27: 45838 | C27: P-1019 | D27: Travel & Expenses | F27: Corporate Travel (Navan) | G27: Expense Claim | H27: 0 | I27: No | J27: 864.28 | K27: =TEXT(B27,"yyyy-mm") -> 2025-06 | L27: =IFERROR(INDEX(Projects!$E$2:$E$500,MATCH(C27,Projects!$A$2:$A$500,0)),"") -> Digital Transformation | M27: =IF(I27="Yes",H27*INDEX(Resources!$I$2:$I$500,MATCH(E27,Resources!$A$2:$A$500,0)),0) -> 0
A28: ACT-00027 | B28: 45869 | C28: P-1014 | D28: Cloud Hosting | F28: Microsoft Azure | G28: AP Invoice | H28: 0 | I28: No | J28: 4907.02 | K28: =TEXT(B28,"yyyy-mm") -> 2025-07 | L28: =IFERROR(INDEX(Projects!$E$2:$E$500,MATCH(C28,Projects!$A$2:$A$500,0)),"") -> Cloud & Infrastructure | M28: =IF(I28="Yes",H28*INDEX(Resources!$I$2:$I$500,MATCH(E28,Resources!$A$2:$A$500,0)),0) -> 0
A29: ACT-00028 | B29: 45869 | C29: P-1014 | D29: Labour | E29: E-0008 | G29: Timesheet | H29: 48.3 | I29: Yes | J29: 4590.43 | K29: =TEXT(B29,"yyyy-mm") -> 2025-07 | L29: =IFERROR(INDEX(Projects!$E$2:$E$500,MATCH(C29,Projects!$A$2:$A$500,0)),"") -> Cloud & Infrastructure | M29: =IF(I29="Yes",H29*INDEX(Resources!$I$2:$I$500,MATCH(E29,Resources!$A$2:$A$500,0)),0) -> 9177
A30: ACT-00029 | B30: 45869 | C30: P-1014 | D30: Labour | E30: E-0011 | G30: Timesheet | H30: 49.9 | I30: Yes | J30: 6483.01 | K30: =TEXT(B30,"yyyy-mm") -> 2025-07 | L30: =IFERROR(INDEX(Projects!$E$2:$E$500,MATCH(C30,Projects!$A$2:$A$500,0)),"") -> Cloud & Infrastructure | M30: =IF(I30="Yes",H30*INDEX(Resources!$I$2:$I$500,MATCH(E30,Resources!$A$2:$A$500,0)),0) -> 12974
A31: ACT-00030 | B31: 45869 | C31: P-1014 | D31: Labour | E31: E-0029 | G31: Timesheet | H31: 93.3 | I31: Yes | J31: 9270.29 | K31: =TEXT(B31,"yyyy-mm") -> 2025-07 | L31: =IFERROR(INDEX(Projects!$E$2:$E$500,MATCH(C31,Projects!$A$2:$A$500,0)),"") -> Cloud & Infrastructure | M31: =IF(I31="Yes",H31*INDEX(Resources!$I$2:$I$500,MATCH(E31,Resources!$A$2:$A$500,0)),0) -> 18660
A32: ACT-00031 | B32: 45869 | C32: P-1014 | D32: Labour | E32: E-0057 | G32: Timesheet | H32: 143 | I32: Yes | J32: 15592.72 | K32: =TEXT(B32,"yyyy-mm") -> 2025-07 | L32: =IFERROR(INDEX(Projects!$E$2:$E$500,MATCH(C32,Projects!$A$2:$A$500,0)),"") -> Cloud & Infrastructure | M32: =IF(I32="Yes",H32*INDEX(Resources!$I$2:$I$500,MATCH(E32,Resources!$A$2:$A$500,0)),0) -> 31460
A33: ACT-00032 | B33: 45869 | C33: P-1014 | D33: Labour | E33: E-0061 | G33: Timesheet | H33: 97.9 | I33: Yes | J33: 8419.4 | K33: =TEXT(B33,"yyyy-mm") -> 2025-07 | L33: =IFERROR(INDEX(Projects!$E$2:$E$500,MATCH(C33,Projects!$A$2:$A$500,0)),"") -> Cloud & Infrastructure | M33: =IF(I33="Yes",H33*INDEX(Resources!$I$2:$I$500,MATCH(E33,Resources!$A$2:$A$500,0)),0) -> 17132.5
A34: ACT-00033 | B34: 45869 | C34: P-1014 | D34: Software & Licences | F34: Microsoft | G34: AP Invoice | H34: 0 | I34: No | J34: 1861.53 | K34: =TEXT(B34,"yyyy-mm") -> 2025-07 | L34: =IFERROR(INDEX(Projects!$E$2:$E$500,MATCH(C34,Projects!$A$2:$A$500,0)),"") -> Cloud & Infrastructure | M34: =IF(I34="Yes",H34*INDEX(Resources!$I$2:$I$500,MATCH(E34,Resources!$A$2:$A$500,0)),0) -> 0
A35: ACT-00034 | B35: 45869 | C35: P-1014 | D35: Travel & Expenses | F35: Corporate Travel (Navan) | G35: Expense Claim | H35: 0 | I35: No | J35: 631.86 | K35: =TEXT(B35,"yyyy-mm") -> 2025-07 | L35: =IFERROR(INDEX(Projects!$E$2:$E$500,MATCH(C35,Projects!$A$2:$A$500,0)),"") -> Cloud & Infrastructure | M35: =IF(I35="Yes",H35*INDEX(Resources!$I$2:$I$500,MATCH(E35,Resources!$A$2:$A$500,0)),0) -> 0
A36: ACT-00035 | B36: 45869 | C36: P-1018 | D36: Cloud Hosting | F36: Microsoft Azure | G36: AP Invoice | H36: 0 | I36: No | J36: 6094.71 | K36: =TEXT(B36,"yyyy-mm") -> 2025-07 | L36: =IFERROR(INDEX(Projects!$E$2:$E$500,MATCH(C36,Projects!$A$2:$A$500,0)),"") -> Cloud & Infrastructure | M36: =IF(I36="Yes",H36*INDEX(Resources!$I$2:$I$500,MATCH(E36,Resources!$A$2:$A$500,0)),0) -> 0
A37: ACT-00036 | B37: 45869 | C37: P-1018 | D37: Hardware | F37: Cisco Systems | G37: AP Invoice | H37: 0 | I37: No | J37: 18858.49 | K37: =TEXT(B37,"yyyy-mm") -> 2025-07 | L37: =IFERROR(INDEX(Projects!$E$2:$E$500,MATCH(C37,Projects!$A$2:$A$500,0)),"") -> Cloud & Infrastructure | M37: =IF(I37="Yes",H37*INDEX(Resources!$I$2:$I$500,MATCH(E37,Resources!$A$2:$A$500,0)),0) -> 0
A38: ACT-00037 | B38: 45869 | C38: P-1018 | D38: Labour | E38: E-0006 | G38: Timesheet | H38: 86.6 | I38: Yes | J38: 7620.8 | K38: =TEXT(B38,"yyyy-mm") -> 2025-07 | L38: =IFERROR(INDEX(Projects!$E$2:$E$500,MATCH(C38,Projects!$A$2:$A$500,0)),"") -> Cloud & Infrastructure | M38: =IF(I38="Yes",H38*INDEX(Resources!$I$2:$I$500,MATCH(E38,Resources!$A$2:$A$500,0)),0) -> 15155
A39: ACT-00038 | B39: 45869 | C39: P-1018 | D39: Labour | E39: E-0012 | G39: Timesheet | H39: 45.1 | I39: Yes | J39: 5859.39 | K39: =TEXT(B39,"yyyy-mm") -> 2025-07 | L39: =IFERROR(INDEX(Projects!$E$2:$E$500,MATCH(C39,Projects!$A$2:$A$500,0)),"") -> Cloud & Infrastructure | M39: =IF(I39="Yes",H39*INDEX(Resources!$I$2:$I$500,MATCH(E39,Resources!$A$2:$A$500,0)),0) -> 11726
A40: ACT-00039 | B40: 45869 | C40: P-1018 | D40: Labour | E40: E-0027 | G40: Timesheet | H40: 92.2 | I40: Yes | J40: 9160.99 | K40: =TEXT(B40,"yyyy-mm") -> 2025-07 | L40: =IFERROR(INDEX(Projects!$E$2:$E$500,MATCH(C40,Projects!$A$2:$A$500,0)),"") -> Cloud & Infrastructure | M40: =IF(I40="Yes",H40*INDEX(Resources!$I$2:$I$500,MATCH(E40,Resources!$A$2:$A$500,0)),0) -> 18440
A41: ACT-00040 | B41: 45869 | C41: P-1018 | D41: Labour | E41: E-0055 | G41: Timesheet | H41: 175.2 | I41: Yes | J41: 19103.81 | K41: =TEXT(B41,"yyyy-mm") -> 2025-07 | L41: =IFERROR(INDEX(Projects!$E$2:$E$500,MATCH(C41,Projects!$A$2:$A$500,0)),"") -> Cloud & Infrastructure | M41: =IF(I41="Yes",H41*INDEX(Resources!$I$2:$I$500,MATCH(E41,Resources!$A$2:$A$500,0)),0) -> 38544
A42: ACT-00041 | B42: 45869 | C42: P-1018 | D42: Labour | E42: E-0061 | G42: Timesheet | H42: 96.6 | I42: Yes | J42: 8307.6 | K42: =TEXT(B42,"yyyy-mm") -> 2025-07 | L42: =IFERROR(INDEX(Projects!$E$2:$E$500,MATCH(C42,Projects!$A$2:$A$500,0)),"") -> Cloud & Infrastructure | M42: =IF(I42="Yes",H42*INDEX(Resources!$I$2:$I$500,MATCH(E42,Resources!$A$2:$A$500,0)),0) -> 16905
A43: ACT-00042 | B43: 45869 | C43: P-1018 | D43: Software & Licences | F43: Figma Inc. | G43: AP Invoice | H43: 0 | I43: No | J43: 1829.07 | K43: =TEXT(B43,"yyyy-mm") -> 2025-07 | L43: =IFERROR(INDEX(Projects!$E$2:$E$500,MATCH(C43,Projects!$A$2:$A$500,0)),"") -> Cloud & Infrastructure | M43: =IF(I43="Yes",H43*INDEX(Resources!$I$2:$I$500,MATCH(E43,Resources!$A$2:$A$500,0)),0) -> 0
A44: ACT-00043 | B44: 45869 | C44: P-1018 | D44: Travel & Expenses | F44: Expense claims | G44: Expense Claim | H44: 0 | I44: No | J44: 706.69 | K44: =TEXT(B44,"yyyy-mm") -> 2025-07 | L44: =IFERROR(INDEX(Projects!$E$2:$E$500,MATCH(C44,Projects!$A$2:$A$500,0)),"") -> Cloud & Infrastructure | M44: =IF(I44="Yes",H44*INDEX(Resources!$I$2:$I$500,MATCH(E44,Resources!$A$2:$A$500,0)),0) -> 0
A45: ACT-00044 | B45: 45869 | C45: P-1019 | D45: Labour | E45: E-0010 | G45: Timesheet | H45: 95.9 | I45: Yes | J45: 8439.2 | K45: =TEXT(B45,"yyyy-mm") -> 2025-07 | L45: =IFERROR(INDEX(Projects!$E$2:$E$500,MATCH(C45,Projects!$A$2:$A$500,0)),"") -> Digital Transformation | M45: =IF(I45="Yes",H45*INDEX(Resources!$I$2:$I$500,MATCH(E45,Resources!$A$2:$A$500,0)),0) -> 16782.5
A46: ACT-00045 | B46: 45869 | C46: P-1019 | D46: Labour | E46: E-0013 | G46: Timesheet | H46: 44.9 | I46: Yes | J46: 5431.1 | K46: =TEXT(B46,"yyyy-mm") -> 2025-07 | L46: =IFERROR(INDEX(Projects!$E$2:$E$500,MATCH(C46,Projects!$A$2:$A$500,0)),"") -> Digital Transformation | M46: =IF(I46="Yes",H46*INDEX(Resources!$I$2:$I$500,MATCH(E46,Resources!$A$2:$A$500,0)),0) -> 11000.5
A47: ACT-00046 | B47: 45869 | C47: P-1019 | D47: Labour | E47: E-0017 | G47: Timesheet | H47: 164.1 | I47: Yes | J47: 10377.68 | K47: =TEXT(B47,"yyyy-mm") -> 2025-07 | L47: =IFERROR(INDEX(Projects!$E$2:$E$500,MATCH(C47,Projects!$A$2:$A$500,0)),"") -> Digital Transformation | M47: =IF(I47="Yes",H47*INDEX(Resources!$I$2:$I$500,MATCH(E47,Resources!$A$2:$A$500,0)),0) -> 21333
A48: ACT-00047 | B48: 45869 | C48: P-1019 | D48: Labour | E48: E-0025 | G48: Timesheet | H48: 156.6 | I48: Yes | J48: 16748.37 | K48: =TEXT(B48,"yyyy-mm") -> 2025-07 | L48: =IFERROR(INDEX(Projects!$E$2:$E$500,MATCH(C48,Projects!$A$2:$A$500,0)),"") -> Digital Transformation | M48: =IF(I48="Yes",H48*INDEX(Resources!$I$2:$I$500,MATCH(E48,Resources!$A$2:$A$500,0)),0) -> 26622
A49: ACT-00048 | B49: 45869 | C49: P-1019 | D49: Labour | E49: E-0034 | G49: Timesheet | H49: 174.6 | I49: Yes | J49: 9498.24 | K49: =TEXT(B49,"yyyy-mm") -> 2025-07 | L49: =IFERROR(INDEX(Projects!$E$2:$E$500,MATCH(C49,Projects!$A$2:$A$500,0)),"") -> Digital Transformation | M49: =IF(I49="Yes",H49*INDEX(Resources!$I$2:$I$500,MATCH(E49,Resources!$A$2:$A$500,0)),0) -> 19206
A50: ACT-00049 | B50: 45869 | C50: P-1019 | D50: Software & Licences | F50: Figma Inc. | G50: AP Invoice | H50: 0 | I50: No | J50: 3818.71 | K50: =TEXT(B50,"yyyy-mm") -> 2025-07 | L50: =IFERROR(INDEX(Projects!$E$2:$E$500,MATCH(C50,Projects!$A$2:$A$500,0)),"") -> Digital Transformation | M50: =IF(I50="Yes",H50*INDEX(Resources!$I$2:$I$500,MATCH(E50,Resources!$A$2:$A$500,0)),0) -> 0
A51: ACT-00050 | B51: 45869 | C51: P-1019 | D51: Subcontractors | F51: NorthByte Testing | G51: AP Invoice | H51: 0 | I51: No | J51: 5951.93 | K51: =TEXT(B51,"yyyy-mm") -> 2025-07 | L51: =IFERROR(INDEX(Projects!$E$2:$E$500,MATCH(C51,Projects!$A$2:$A$500,0)),"") -> Digital Transformation | M51: =IF(I51="Yes",H51*INDEX(Resources!$I$2:$I$500,MATCH(E51,Resources!$A$2:$A$500,0)),0) -> 0
A52: ACT-00051 | B52: 45869 | C52: P-1019 | D52: Training | F52: Learning Tree | G52: AP Invoice | H52: 0 | I52: No | J52: 1438.15 | K52: =TEXT(B52,"yyyy-mm") -> 2025-07 | L52: =IFERROR(INDEX(Projects!$E$2:$E$500,MATCH(C52,Projects!$A$2:$A$500,0)),"") -> Digital Transformation | M52: =IF(I52="Yes",H52*INDEX(Resources!$I$2:$I$500,MATCH(E52,Resources!$A$2:$A$500,0)),0) -> 0
A53: ACT-00052 | B53: 45869 | C53: P-1019 | D53: Travel & Expenses | F53: Expense claims | G53: Expense Claim | H53: 0 | I53: No | J53: 939.92 | K53: =TEXT(B53,"yyyy-mm") -> 2025-07 | L53: =IFERROR(INDEX(Projects!$E$2:$E$500,MATCH(C53,Projects!$A$2:$A$500,0)),"") -> Digital Transformation | M53: =IF(I53="Yes",H53*INDEX(Resources!$I$2:$I$500,MATCH(E53,Resources!$A$2:$A$500,0)),0) -> 0
A54: ACT-00053 | B54: 45900 | C54: P-1013 | D54: Labour | E54: E-0004 | G54: Timesheet | H54: 94 | I54: Yes | J54: 9595.52 | K54: =TEXT(B54,"yyyy-mm") -> 2025-08 | L54: =IFERROR(INDEX(Projects!$E$2:$E$500,MATCH(C54,Projects!$A$2:$A$500,0)),"") -> Digital Transformation | M54: =IF(I54="Yes",H54*INDEX(Resources!$I$2:$I$500,MATCH(E54,Resources!$A$2:$A$500,0)),0) -> 19270
A55: ACT-00054 | B55: 45900 | C55: P-1013 | D55: Labour | E55: E-0014 | G55: Timesheet | H55: 98.8 | I55: Yes | J55: 10291.01 | K55: =TEXT(B55,"yyyy-mm") -> 2025-08 | L55: =IFERROR(INDEX(Projects!$E$2:$E$500,MATCH(C55,Projects!$A$2:$A$500,0)),"") -> Digital Transformation | M55: =IF(I55="Yes",H55*INDEX(Resources!$I$2:$I$500,MATCH(E55,Resources!$A$2:$A$500,0)),0) -> 20748
A56: ACT-00055 | B56: 45900 | C56: P-1013 | D56: Labour | E56: E-0019 | G56: Timesheet | H56: 155.9 | I56: Yes | J56: 11263.77 | K56: =TEXT(B56,"yyyy-mm") -> 2025-08 | L56: =IFERROR(INDEX(Projects!$E$2:$E$500,MATCH(C56,Projects!$A$2:$A$500,0)),"") -> Digital Transformation | M56: =IF(I56="Yes",H56*INDEX(Resources!$I$2:$I$500,MATCH(E56,Resources!$A$2:$A$500,0)),0) -> 18708
A57: ACT-00056 | B57: 45900 | C57: P-1013 | D57: Labour | E57: E-0028 | G57: Timesheet | H57: 139.7 | I57: Yes | J57: 11952.73 | K57: =TEXT(B57,"yyyy-mm") -> 2025-08 | L57: =IFERROR(INDEX(Projects!$E$2:$E$500,MATCH(C57,Projects!$A$2:$A$500,0)),"") -> Digital Transformation | M57: =IF(I57="Yes",H57*INDEX(Resources!$I$2:$I$500,MATCH(E57,Resources!$A$2:$A$500,0)),0) -> 23749
A58: ACT-00057 | B58: 45900 | C58: P-1013 | D58: Labour | E58: E-0041 | G58: Timesheet | H58: 106.7 | I58: Yes | J58: 6828.8 | K58: =TEXT(B58,"yyyy-mm") -> 2025-08 | L58: =IFERROR(INDEX(Projects!$E$2:$E$500,MATCH(C58,Projects!$A$2:$A$500,0)),"") -> Digital Transformation | M58: =IF(I58="Yes",H58*INDEX(Resources!$I$2:$I$500,MATCH(E58,Resources!$A$2:$A$500,0)),0) -> 13871
A59: ACT-00058 | B59: 45900 | C59: P-1013 | D59: Software & Licences | F59: Salesforce | G59: AP Invoice | H59: 0 | I59: No | J59: 3984.55 | K59: =TEXT(B59,"yyyy-mm") -> 2025-08 | L59: =IFERROR(INDEX(Projects!$E$2:$E$500,MATCH(C59,Projects!$A$2:$A$500,0)),"") -> Digital Transformation | M59: =IF(I59="Yes",H59*INDEX(Resources!$I$2:$I$500,MATCH(E59,Resources!$A$2:$A$500,0)),0) -> 0
A60: ACT-00059 | B60: 45900 | C60: P-1013 | D60: Subcontractors | F60: NorthByte Testing | G60: AP Invoice | H60: 0 | I60: No | J60: 5706.99 | K60: =TEXT(B60,"yyyy-mm") -> 2025-08 | L60: =IFERROR(INDEX(Projects!$E$2:$E$500,MATCH(C60,Projects!$A$2:$A$500,0)),"") -> Digital Transformation | M60: =IF(I60="Yes",H60*INDEX(Resources!$I$2:$I$500,MATCH(E60,Resources!$A$2:$A$500,0)),0) -> 0
A61: ACT-00060 | B61: 45900 | C61: P-1013 | D61: Training | F61: Learning Tree | G61: AP Invoice | H61: 0 | I61: No | J61: 1509.96 | K61: =TEXT(B61,"yyyy-mm") -> 2025-08 | L61: =IFERROR(INDEX(Projects!$E$2:$E$500,MATCH(C61,Projects!$A$2:$A$500,0)),"") -> Digital Transformation | M61: =IF(I61="Yes",H61*INDEX(Resources!$I$2:$I$500,MATCH(E61,Resources!$A$2:$A$500,0)),0) -> 0
A62: ACT-00061 | B62: 45900 | C62: P-1013 | D62: Travel & Expenses | F62: Expense claims | G62: Expense Claim | H62: 0 | I62: No | J62: 993.27 | K62: =TEXT(B62,"yyyy-mm") -> 2025-08 | L62: =IFERROR(INDEX(Projects!$E$2:$E$500,MATCH(C62,Projects!$A$2:$A$500,0)),"") -> Digital Transformation | M62: =IF(I62="Yes",H62*INDEX(Resources!$I$2:$I$500,MATCH(E62,Resources!$A$2:$A$500,0)),0) -> 0
A63: ACT-00062 | B63: 45900 | C63: P-1014 | D63: Cloud Hosting | F63: Microsoft Azure | G63: AP Invoice | H63: 0 | I63: No | J63: 5249.87 | K63: =TEXT(B63,"yyyy-mm") -> 2025-08 | L63: =IFERROR(INDEX(Projects!$E$2:$E$500,MATCH(C63,Projects!$A$2:$A$500,0)),"") -> Cloud & Infrastructure | M63: =IF(I63="Yes",H63*INDEX(Resources!$I$2:$I$500,MATCH(E63,Resources!$A$2:$A$500,0)),0) -> 0
A64: ACT-00063 | B64: 45900 | C64: P-1014 | D64: Labour | E64: E-0008 | G64: Timesheet | H64: 42.1 | I64: Yes | J64: 4001.18 | K64: =TEXT(B64,"yyyy-mm") -> 2025-08 | L64: =IFERROR(INDEX(Projects!$E$2:$E$500,MATCH(C64,Projects!$A$2:$A$500,0)),"") -> Cloud & Infrastructure | M64: =IF(I64="Yes",H64*INDEX(Resources!$I$2:$I$500,MATCH(E64,Resources!$A$2:$A$500,0)),0) -> 7999
A65: ACT-00064 | B65: 45900 | C65: P-1014 | D65: Labour | E65: E-0011 | G65: Timesheet | H65: 44.5 | I65: Yes | J65: 5781.44 | K65: =TEXT(B65,"yyyy-mm") -> 2025-08 | L65: =IFERROR(INDEX(Projects!$E$2:$E$500,MATCH(C65,Projects!$A$2:$A$500,0)),"") -> Cloud & Infrastructure | M65: =IF(I65="Yes",H65*INDEX(Resources!$I$2:$I$500,MATCH(E65,Resources!$A$2:$A$500,0)),0) -> 11570
A66: ACT-00065 | B66: 45900 | C66: P-1014 | D66: Labour | E66: E-0029 | G66: Timesheet | H66: 88.9 | I66: Yes | J66: 8833.1 | K66: =TEXT(B66,"yyyy-mm") -> 2025-08 | L66: =IFERROR(INDEX(Projects!$E$2:$E$500,MATCH(C66,Projects!$A$2:$A$500,0)),"") -> Cloud & Infrastructure | M66: =IF(I66="Yes",H66*INDEX(Resources!$I$2:$I$500,MATCH(E66,Resources!$A$2:$A$500,0)),0) -> 17780
A67: ACT-00066 | B67: 45900 | C67: P-1014 | D67: Labour | E67: E-0057 | G67: Timesheet | H67: 119.3 | I67: Yes | J67: 13008.47 | K67: =TEXT(B67,"yyyy-mm") -> 2025-08 | L67: =IFERROR(INDEX(Projects!$E$2:$E$500,MATCH(C67,Projects!$A$2:$A$500,0)),"") -> Cloud & Infrastructure | M67: =IF(I67="Yes",H67*INDEX(Resources!$I$2:$I$500,MATCH(E67,Resources!$A$2:$A$500,0)),0) -> 26246
A68: ACT-00067 | B68: 45900 | C68: P-1014 | D68: Labour | E68: E-0061 | G68: Timesheet | H68: 88.8 | I68: Yes | J68: 7636.8 | K68: =TEXT(B68,"yyyy-mm") -> 2025-08 | L68: =IFERROR(INDEX(Projects!$E$2:$E$500,MATCH(C68,Projects!$A$2:$A$500,0)),"") -> Cloud & Infrastructure | M68: =IF(I68="Yes",H68*INDEX(Resources!$I$2:$I$500,MATCH(E68,Resources!$A$2:$A$500,0)),0) -> 15540
A69: ACT-00068 | B69: 45900 | C69: P-1014 | D69: Software & Licences | F69: Microsoft | G69: AP Invoice | H69: 0 | I69: No | J69: 1866.04 | K69: =TEXT(B69,"yyyy-mm") -> 2025-08 | L69: =IFERROR(INDEX(Projects!$E$2:$E$500,MATCH(C69,Projects!$A$2:$A$500,0)),"") -> Cloud & Infrastructure | M69: =IF(I69="Yes",H69*INDEX(Resources!$I$2:$I$500,MATCH(E69,Resources!$A$2:$A$500,0)),0) -> 0
A70: ACT-00069 | B70: 45900 | C70: P-1014 | D70: Travel & Expenses | F70: Corporate Travel (Navan) | G70: Expense Claim | H70: 0 | I70: No | J70: 793.61 | K70: =TEXT(B70,"yyyy-mm") -> 2025-08 | L70: =IFERROR(INDEX(Projects!$E$2:$E$500,MATCH(C70,Projects!$A$2:$A$500,0)),"") -> Cloud & Infrastructure | M70: =IF(I70="Yes",H70*INDEX(Resources!$I$2:$I$500,MATCH(E70,Resources!$A$2:$A$500,0)),0) -> 0
A71: ACT-00070 | B71: 45900 | C71: P-1018 | D71: Cloud Hosting | F71: Microsoft Azure | G71: AP Invoice | H71: 0 | I71: No | J71: 5215.63 | K71: =TEXT(B71,"yyyy-mm") -> 2025-08 | L71: =IFERROR(INDEX(Projects!$E$2:$E$500,MATCH(C71,Projects!$A$2:$A$500,0)),"") -> Cloud & Infrastructure | M71: =IF(I71="Yes",H71*INDEX(Resources!$I$2:$I$500,MATCH(E71,Resources!$A$2:$A$500,0)),0) -> 0
A72: ACT-00071 | B72: 45900 | C72: P-1018 | D72: Labour | E72: E-0006 | G72: Timesheet | H72: 79.5 | I72: Yes | J72: 6996 | K72: =TEXT(B72,"yyyy-mm") -> 2025-08 | L72: =IFERROR(INDEX(Projects!$E$2:$E$500,MATCH(C72,Projects!$A$2:$A$500,0)),"") -> Cloud & Infrastructure | M72: =IF(I72="Yes",H72*INDEX(Resources!$I$2:$I$500,MATCH(E72,Resources!$A$2:$A$500,0)),0) -> 13912.5
A73: ACT-00072 | B73: 45900 | C73: P-1018 | D73: Labour | E73: E-0012 | G73: Timesheet | H73: 43.9 | I73: Yes | J73: 5703.49 | K73: =TEXT(B73,"yyyy-mm") -> 2025-08 | L73: =IFERROR(INDEX(Projects!$E$2:$E$500,MATCH(C73,Projects!$A$2:$A$500,0)),"") -> Cloud & Infrastructure | M73: =IF(I73="Yes",H73*INDEX(Resources!$I$2:$I$500,MATCH(E73,Resources!$A$2:$A$500,0)),0) -> 11414
A74: ACT-00073 | B74: 45900 | C74: P-1018 | D74: Labour | E74: E-0027 | G74: Timesheet | H74: 76 | I74: Yes | J74: 7551.36 | K74: =TEXT(B74,"yyyy-mm") -> 2025-08 | L74: =IFERROR(INDEX(Projects!$E$2:$E$500,MATCH(C74,Projects!$A$2:$A$500,0)),"") -> Cloud & Infrastructure | M74: =IF(I74="Yes",H74*INDEX(Resources!$I$2:$I$500,MATCH(E74,Resources!$A$2:$A$500,0)),0) -> 15200
A75: ACT-00074 | B75: 45900 | C75: P-1018 | D75: Labour | E75: E-0055 | G75: Timesheet | H75: 157.5 | I75: Yes | J75: 17173.8 | K75: =TEXT(B75,"yyyy-mm") -> 2025-08 | L75: =IFERROR(INDEX(Projects!$E$2:$E$500,MATCH(C75,Projects!$A$2:$A$500,0)),"") -> Cloud & Infrastructure | M75: =IF(I75="Yes",H75*INDEX(Resources!$I$2:$I$500,MATCH(E75,Resources!$A$2:$A$500,0)),0) -> 34650
A76: ACT-00075 | B76: 45900 | C76: P-1018 | D76: Labour | E76: E-0061 | G76: Timesheet | H76: 74.7 | I76: Yes | J76: 6424.2 | K76: =TEXT(B76,"yyyy-mm") -> 2025-08 | L76: =IFERROR(INDEX(Projects!$E$2:$E$500,MATCH(C76,Projects!$A$2:$A$500,0)),"") -> Cloud & Infrastructure | M76: =IF(I76="Yes",H76*INDEX(Resources!$I$2:$I$500,MATCH(E76,Resources!$A$2:$A$500,0)),0) -> 13072.5
A77: ACT-00076 | B77: 45900 | C77: P-1018 | D77: Software & Licences | F77: Figma Inc. | G77: AP Invoice | H77: 0 | I77: No | J77: 1906.29 | K77: =TEXT(B77,"yyyy-mm") -> 2025-08 | L77: =IFERROR(INDEX(Projects!$E$2:$E$500,MATCH(C77,Projects!$A$2:$A$500,0)),"") -> Cloud & Infrastructure | M77: =IF(I77="Yes",H77*INDEX(Resources!$I$2:$I$500,MATCH(E77,Resources!$A$2:$A$500,0)),0) -> 0
A78: ACT-00077 | B78: 45900 | C78: P-1018 | D78: Travel & Expenses | F78: Corporate Travel (Navan) | G78: Expense Claim | H78: 0 | I78: No | J78: 879.18 | K78: =TEXT(B78,"yyyy-mm") -> 2025-08 | L78: =IFERROR(INDEX(Projects!$E$2:$E$500,MATCH(C78,Projects!$A$2:$A$500,0)),"") -> Cloud & Infrastructure | M78: =IF(I78="Yes",H78*INDEX(Resources!$I$2:$I$500,MATCH(E78,Resources!$A$2:$A$500,0)),0) -> 0
A79: ACT-00078 | B79: 45900 | C79: P-1019 | D79: Labour | E79: E-0010 | G79: Timesheet | H79: 91.7 | I79: Yes | J79: 8069.6 | K79: =TEXT(B79,"yyyy-mm") -> 2025-08 | L79: =IFERROR(INDEX(Projects!$E$2:$E$500,MATCH(C79,Projects!$A$2:$A$500,0)),"") -> Digital Transformation | M79: =IF(I79="Yes",H79*INDEX(Resources!$I$2:$I$500,MATCH(E79,Resources!$A$2:$A$500,0)),0) -> 16047.5
A80: ACT-00079 | B80: 45900 | C80: P-1019 | D80: Labour | E80: E-0013 | G80: Timesheet | H80: 49.7 | I80: Yes | J80: 6011.71 | K80: =TEXT(B80,"yyyy-mm") -> 2025-08 | L80: =IFERROR(INDEX(Projects!$E$2:$E$500,MATCH(C80,Projects!$A$2:$A$500,0)),"") -> Digital Transformation | M80: =IF(I80="Yes",H80*INDEX(Resources!$I$2:$I$500,MATCH(E80,Resources!$A$2:$A$500,0)),0) -> 12176.5
A81: ACT-00080 | B81: 45900 | C81: P-1019 | D81: Labour | E81: E-0017 | G81: Timesheet | H81: 132.4 | I81: Yes | J81: 8372.98 | K81: =TEXT(B81,"yyyy-mm") -> 2025-08 | L81: =IFERROR(INDEX(Projects!$E$2:$E$500,MATCH(C81,Projects!$A$2:$A$500,0)),"") -> Digital Transformation | M81: =IF(I81="Yes",H81*INDEX(Resources!$I$2:$I$500,MATCH(E81,Resources!$A$2:$A$500,0)),0) -> 17212
A82: ACT-00081 | B82: 45900 | C82: P-1019 | D82: Labour | E82: E-0025 | G82: Timesheet | H82: 132.8 | I82: Yes | J82: 14202.96 | K82: =TEXT(B82,"yyyy-mm") -> 2025-08 | L82: =IFERROR(INDEX(Projects!$E$2:$E$500,MATCH(C82,Projects!$A$2:$A$500,0)),"") -> Digital Transformation | M82: =IF(I82="Yes",H82*INDEX(Resources!$I$2:$I$500,MATCH(E82,Resources!$A$2:$A$500,0)),0) -> 22576
A83: ACT-00082 | B83: 45900 | C83: P-1019 | D83: Labour | E83: E-0034 | G83: Timesheet | H83: 140.1 | I83: Yes | J83: 7621.44 | K83: =TEXT(B83,"yyyy-mm") -> 2025-08 | L83: =IFERROR(INDEX(Projects!$E$2:$E$500,MATCH(C83,Projects!$A$2:$A$500,0)),"") -> Digital Transformation | M83: =IF(I83="Yes",H83*INDEX(Resources!$I$2:$I$500,MATCH(E83,Resources!$A$2:$A$500,0)),0) -> 15411
A84: ACT-00083 | B84: 45900 | C84: P-1019 | D84: Software & Licences | F84: Figma Inc. | G84: AP Invoice | H84: 0 | I84: No | J84: 3006.99 | K84: =TEXT(B84,"yyyy-mm") -> 2025-08 | L84: =IFERROR(INDEX(Projects!$E$2:$E$500,MATCH(C84,Projects!$A$2:$A$500,0)),"") -> Digital Transformation | M84: =IF(I84="Yes",H84*INDEX(Resources!$I$2:$I$500,MATCH(E84,Resources!$A$2:$A$500,0)),0) -> 0
A85: ACT-00084 | B85: 45900 | C85: P-1019 | D85: Subcontractors | F85: NorthByte Testing | G85: AP Invoice | H85: 0 | I85: No | J85: 6514.26 | K85: =TEXT(B85,"yyyy-mm") -> 2025-08 | L85: =IFERROR(INDEX(Projects!$E$2:$E$500,MATCH(C85,Projects!$A$2:$A$500,0)),"") -> Digital Transformation | M85: =IF(I85="Yes",H85*INDEX(Resources!$I$2:$I$500,MATCH(E85,Resources!$A$2:$A$500,0)),0) -> 0
A86: ACT-00085 | B86: 45900 | C86: P-1019 | D86: Training | F86: Learning Tree | G86: AP Invoice | H86: 0 | I86: No | J86: 1330.84 | K86: =TEXT(B86,"yyyy-mm") -> 2025-08 | L86: =IFERROR(INDEX(Projects!$E$2:$E$500,MATCH(C86,Projects!$A$2:$A$500,0)),"") -> Digital Transformation | M86: =IF(I86="Yes",H86*INDEX(Resources!$I$2:$I$500,MATCH(E86,Resources!$A$2:$A$500,0)),0) -> 0
A87: ACT-00086 | B87: 45900 | C87: P-1019 | D87: Travel & Expenses | F87: Expense claims | G87: Expense Claim | H87: 0 | I87: No | J87: 845.42 | K87: =TEXT(B87,"yyyy-mm") -> 2025-08 | L87: =IFERROR(INDEX(Projects!$E$2:$E$500,MATCH(C87,Projects!$A$2:$A$500,0)),"") -> Digital Transformation | M87: =IF(I87="Yes",H87*INDEX(Resources!$I$2:$I$500,MATCH(E87,Resources!$A$2:$A$500,0)),0) -> 0
A88: ACT-00087 | B88: 45930 | C88: P-1003 | D88: Cloud Hosting | F88: Microsoft Azure | G88: AP Invoice | H88: 0 | I88: No | J88: 4487.92 | K88: =TEXT(B88,"yyyy-mm") -> 2025-09 | L88: =IFERROR(INDEX(Projects!$E$2:$E$500,MATCH(C88,Projects!$A$2:$A$500,0)),"") -> Data & AI | M88: =IF(I88="Yes",H88*INDEX(Resources!$I$2:$I$500,MATCH(E88,Resources!$A$2:$A$500,0)),0) -> 0
A89: ACT-00088 | B89: 45930 | C89: P-1003 | D89: Labour | E89: E-0005 | G89: Timesheet | H89: 38.8 | I89: No | J89: 2902.24 | K89: =TEXT(B89,"yyyy-mm") -> 2025-09 | L89: =IFERROR(INDEX(Projects!$E$2:$E$500,MATCH(C89,Projects!$A$2:$A$500,0)),"") -> Data & AI | M89: =IF(I89="Yes",H89*INDEX(Resources!$I$2:$I$500,MATCH(E89,Resources!$A$2:$A$500,0)),0) -> 0
A90: ACT-00089 | B90: 45930 | C90: P-1003 | D90: Labour | E90: E-0013 | G90: Timesheet | H90: 38.8 | I90: Yes | J90: 4693.25 | K90: =TEXT(B90,"yyyy-mm") -> 2025-09 | L90: =IFERROR(INDEX(Projects!$E$2:$E$500,MATCH(C90,Projects!$A$2:$A$500,0)),"") -> Data & AI | M90: =IF(I90="Yes",H90*INDEX(Resources!$I$2:$I$500,MATCH(E90,Resources!$A$2:$A$500,0)),0) -> 9506
A91: ACT-00090 | B91: 45930 | C91: P-1003 | D91: Labour | E91: E-0033 | G91: Timesheet | H91: 72 | I91: Yes | J91: 4285.44 | K91: =TEXT(B91,"yyyy-mm") -> 2025-09 | L91: =IFERROR(INDEX(Projects!$E$2:$E$500,MATCH(C91,Projects!$A$2:$A$500,0)),"") -> Data & AI | M91: =IF(I91="Yes",H91*INDEX(Resources!$I$2:$I$500,MATCH(E91,Resources!$A$2:$A$500,0)),0) -> 8640
A92: ACT-00091 | B92: 45930 | C92: P-1003 | D92: Labour | E92: E-0048 | G92: Timesheet | H92: 164 | I92: Yes | J92: 17121.6 | K92: =TEXT(B92,"yyyy-mm") -> 2025-09 | L92: =IFERROR(INDEX(Projects!$E$2:$E$500,MATCH(C92,Projects!$A$2:$A$500,0)),"") -> Data & AI | M92: =IF(I92="Yes",H92*INDEX(Resources!$I$2:$I$500,MATCH(E92,Resources!$A$2:$A$500,0)),0) -> 34440
A93: ACT-00092 | B93: 45930 | C93: P-1003 | D93: Software & Licences | F93: Microsoft | G93: AP Invoice | H93: 0 | I93: No | J93: 2781.28 | K93: =TEXT(B93,"yyyy-mm") -> 2025-09 | L93: =IFERROR(INDEX(Projects!$E$2:$E$500,MATCH(C93,Projects!$A$2:$A$500,0)),"") -> Data & AI | M93: =IF(I93="Yes",H93*INDEX(Resources!$I$2:$I$500,MATCH(E93,Resources!$A$2:$A$500,0)),0) -> 0
A94: ACT-00093 | B94: 45930 | C94: P-1003 | D94: Travel & Expenses | F94: Corporate Travel (Navan) | G94: Expense Claim | H94: 0 | I94: No | J94: 503.25 | K94: =TEXT(B94,"yyyy-mm") -> 2025-09 | L94: =IFERROR(INDEX(Projects!$E$2:$E$500,MATCH(C94,Projects!$A$2:$A$500,0)),"") -> Data & AI | M94: =IF(I94="Yes",H94*INDEX(Resources!$I$2:$I$500,MATCH(E94,Resources!$A$2:$A$500,0)),0) -> 0
A95: ACT-00094 | B95: 45930 | C95: P-1013 | D95: Labour | E95: E-0004 | G95: Timesheet | H95: 108.5 | I95: Yes | J95: 11075.68 | K95: =TEXT(B95,"yyyy-mm") -> 2025-09 | L95: =IFERROR(INDEX(Projects!$E$2:$E$500,MATCH(C95,Projects!$A$2:$A$500,0)),"") -> Digital Transformation | M95: =IF(I95="Yes",H95*INDEX(Resources!$I$2:$I$500,MATCH(E95,Resources!$A$2:$A$500,0)),0) -> 22242.5
A96: ACT-00095 | B96: 45930 | C96: P-1013 | D96: Labour | E96: E-0014 | G96: Timesheet | H96: 106.4 | I96: Yes | J96: 11082.62 | K96: =TEXT(B96,"yyyy-mm") -> 2025-09 | L96: =IFERROR(INDEX(Projects!$E$2:$E$500,MATCH(C96,Projects!$A$2:$A$500,0)),"") -> Digital Transformation | M96: =IF(I96="Yes",H96*INDEX(Resources!$I$2:$I$500,MATCH(E96,Resources!$A$2:$A$500,0)),0) -> 22344
A97: ACT-00096 | B97: 45930 | C97: P-1013 | D97: Labour | E97: E-0019 | G97: Timesheet | H97: 170.4 | I97: Yes | J97: 12311.4 | K97: =TEXT(B97,"yyyy-mm") -> 2025-09 | L97: =IFERROR(INDEX(Projects!$E$2:$E$500,MATCH(C97,Projects!$A$2:$A$500,0)),"") -> Digital Transformation | M97: =IF(I97="Yes",H97*INDEX(Resources!$I$2:$I$500,MATCH(E97,Resources!$A$2:$A$500,0)),0) -> 20448
A98: ACT-00097 | B98: 45930 | C98: P-1013 | D98: Labour | E98: E-0028 | G98: Timesheet | H98: 179.7 | I98: Yes | J98: 15375.13 | K98: =TEXT(B98,"yyyy-mm") -> 2025-09 | L98: =IFERROR(INDEX(Projects!$E$2:$E$500,MATCH(C98,Projects!$A$2:$A$500,0)),"") -> Digital Transformation | M98: =IF(I98="Yes",H98*INDEX(Resources!$I$2:$I$500,MATCH(E98,Resources!$A$2:$A$500,0)),0) -> 30549
A99: ACT-00098 | B99: 45930 | C99: P-1013 | D99: Labour | E99: E-0041 | G99: Timesheet | H99: 117.6 | I99: Yes | J99: 7526.4 | K99: =TEXT(B99,"yyyy-mm") -> 2025-09 | L99: =IFERROR(INDEX(Projects!$E$2:$E$500,MATCH(C99,Projects!$A$2:$A$500,0)),"") -> Digital Transformation | M99: =IF(I99="Yes",H99*INDEX(Resources!$I$2:$I$500,MATCH(E99,Resources!$A$2:$A$500,0)),0) -> 15288
A100: ACT-00099 | B100: 45930 | C100: P-1013 | D100: Software & Licences | F100: Salesforce | G100: AP Invoice | H100: 0 | I100: No | J100: 3850.29 | K100: =TEXT(B100,"yyyy-mm") -> 2025-09 | L100: =IFERROR(INDEX(Projects!$E$2:$E$500,MATCH(C100,Projects!$A$2:$A$500,0)),"") -> Digital Transformation | M100: =IF(I100="Yes",H100*INDEX(Resources!$I$2:$I$500,MATCH(E100,Resources!$A$2:$A$500,0)),0) -> 0
...

Sheet Milestones
A1: MilestoneID | B1: ProjectID | C1: MilestoneName | D1: Phase | E1: BaselineDate | F1: ForecastDate | G1: ActualDate | H1: IsBillingMilestone | I1: BillingPct | J1: BillingAmount | K1: VarianceDays | L1: Status | M1: Invoiced
A2: M-0001 | B2: P-1001 | C2: Discovery sign-off | D2: Discovery | E2: 46000 | F2: 46000 | G2: 46000 | H2: Yes | I2: 0.1 | J2: =IF(H2="Yes",I2*INDEX(Projects!$R$2:$R$500,MATCH(B2,Projects!$A$2:$A$500,0)),0) -> 110000 | K2: =IF(ISNUMBER(G2),G2-E2,F2-E2) -> 0 | L2: =IF(ISNUMBER(G2),"Completed",IF(F2<AsOfDate,"Overdue",IF(F2-E2>MilestoneAtRiskDays,"At Risk","On Track"))) -> Completed | M2: =IF(COUNTIF(Invoices!$C$2:$C$2000,A2)>0,"Yes","No") -> Yes
A3: M-0002 | B3: P-1001 | C3: Design approval | D3: Design | E3: 46057 | F3: 46057 | G3: 46057 | H3: Yes | I3: 0.2 | J3: =IF(H3="Yes",I3*INDEX(Projects!$R$2:$R$500,MATCH(B3,Projects!$A$2:$A$500,0)),0) -> 220000 | K3: =IF(ISNUMBER(G3),G3-E3,F3-E3) -> 0 | L3: =IF(ISNUMBER(G3),"Completed",IF(F3<AsOfDate,"Overdue",IF(F3-E3>MilestoneAtRiskDays,"At Risk","On Track"))) -> Completed | M3: =IF(COUNTIF(Invoices!$C$2:$C$2000,A3)>0,"Yes","No") -> Yes
A4: M-0003 | B4: P-1001 | C4: Build complete | D4: Build | E4: 46216 | F4: 46218 | G4: 46218 | H4: Yes | I4: 0.3 | J4: =IF(H4="Yes",I4*INDEX(Projects!$R$2:$R$500,MATCH(B4,Projects!$A$2:$A$500,0)),0) -> 330000 | K4: =IF(ISNUMBER(G4),G4-E4,F4-E4) -> 2 | L4: =IF(ISNUMBER(G4),"Completed",IF(F4<AsOfDate,"Overdue",IF(F4-E4>MilestoneAtRiskDays,"At Risk","On Track"))) -> Completed | M4: =IF(COUNTIF(Invoices!$C$2:$C$2000,A4)>0,"Yes","No") -> Yes
A5: M-0004 | B5: P-1001 | C5: UAT sign-off | D5: Test | E5: 46288 | F5: 46293 | H5: Yes | I5: 0.2 | J5: =IF(H5="Yes",I5*INDEX(Projects!$R$2:$R$500,MATCH(B5,Projects!$A$2:$A$500,0)),0) -> 220000 | K5: =IF(ISNUMBER(G5),G5-E5,F5-E5) -> 5 | L5: =IF(ISNUMBER(G5),"Completed",IF(F5<AsOfDate,"Overdue",IF(F5-E5>MilestoneAtRiskDays,"At Risk","On Track"))) -> On Track | M5: =IF(COUNTIF(Invoices!$C$2:$C$2000,A5)>0,"Yes","No") -> No
A6: M-0005 | B6: P-1001 | C6: Go-live | D6: Deploy | E6: 46325 | F6: 46329 | H6: Yes | I6: 0.2 | J6: =IF(H6="Yes",I6*INDEX(Projects!$R$2:$R$500,MATCH(B6,Projects!$A$2:$A$500,0)),0) -> 220000 | K6: =IF(ISNUMBER(G6),G6-E6,F6-E6) -> 4 | L6: =IF(ISNUMBER(G6),"Completed",IF(F6<AsOfDate,"Overdue",IF(F6-E6>MilestoneAtRiskDays,"At Risk","On Track"))) -> On Track | M6: =IF(COUNTIF(Invoices!$C$2:$C$2000,A6)>0,"Yes","No") -> No
A7: M-0006 | B7: P-1002 | C7: Discovery sign-off | D7: Discovery | E7: 46066 | F7: 46066 | G7: 46066 | H7: Yes | I7: 0.1 | J7: =IF(H7="Yes",I7*INDEX(Projects!$R$2:$R$500,MATCH(B7,Projects!$A$2:$A$500,0)),0) -> 68500 | K7: =IF(ISNUMBER(G7),G7-E7,F7-E7) -> 0 | L7: =IF(ISNUMBER(G7),"Completed",IF(F7<AsOfDate,"Overdue",IF(F7-E7>MilestoneAtRiskDays,"At Risk","On Track"))) -> Completed | M7: =IF(COUNTIF(Invoices!$C$2:$C$2000,A7)>0,"Yes","No") -> Yes
A8: M-0007 | B8: P-1002 | C8: Design approval | D8: Design | E8: 46122 | F8: 46125 | G8: 46125 | H8: Yes | I8: 0.2 | J8: =IF(H8="Yes",I8*INDEX(Projects!$R$2:$R$500,MATCH(B8,Projects!$A$2:$A$500,0)),0) -> 137000 | K8: =IF(ISNUMBER(G8),G8-E8,F8-E8) -> 3 | L8: =IF(ISNUMBER(G8),"Completed",IF(F8<AsOfDate,"Overdue",IF(F8-E8>MilestoneAtRiskDays,"At Risk","On Track"))) -> Completed | M8: =IF(COUNTIF(Invoices!$C$2:$C$2000,A8)>0,"Yes","No") -> Yes
A9: M-0008 | B9: P-1002 | C9: Build complete | D9: Build | E9: 46269 | F9: 46269 | H9: Yes | I9: 0.3 | J9: =IF(H9="Yes",I9*INDEX(Projects!$R$2:$R$500,MATCH(B9,Projects!$A$2:$A$500,0)),0) -> 205500 | K9: =IF(ISNUMBER(G9),G9-E9,F9-E9) -> 0 | L9: =IF(ISNUMBER(G9),"Completed",IF(F9<AsOfDate,"Overdue",IF(F9-E9>MilestoneAtRiskDays,"At Risk","On Track"))) -> Overdue | M9: =IF(COUNTIF(Invoices!$C$2:$C$2000,A9)>0,"Yes","No") -> No
A10: M-0009 | B10: P-1002 | C10: UAT sign-off | D10: Test | E10: 46339 | F10: 46353 | H10: Yes | I10: 0.2 | J10: =IF(H10="Yes",I10*INDEX(Projects!$R$2:$R$500,MATCH(B10,Projects!$A$2:$A$500,0)),0) -> 137000 | K10: =IF(ISNUMBER(G10),G10-E10,F10-E10) -> 14 | L10: =IF(ISNUMBER(G10),"Completed",IF(F10<AsOfDate,"Overdue",IF(F10-E10>MilestoneAtRiskDays,"At Risk","On Track"))) -> On Track | M10: =IF(COUNTIF(Invoices!$C$2:$C$2000,A10)>0,"Yes","No") -> No
A11: M-0010 | B11: P-1002 | C11: Go-live | D11: Deploy | E11: 46374 | F11: 46391 | H11: Yes | I11: 0.2 | J11: =IF(H11="Yes",I11*INDEX(Projects!$R$2:$R$500,MATCH(B11,Projects!$A$2:$A$500,0)),0) -> 137000 | K11: =IF(ISNUMBER(G11),G11-E11,F11-E11) -> 17 | L11: =IF(ISNUMBER(G11),"Completed",IF(F11<AsOfDate,"Overdue",IF(F11-E11>MilestoneAtRiskDays,"At Risk","On Track"))) -> At Risk | M11: =IF(COUNTIF(Invoices!$C$2:$C$2000,A11)>0,"Yes","No") -> No
A12: M-0011 | B12: P-1003 | C12: Discovery sign-off | D12: Discovery | E12: 45952 | F12: 45954 | G12: 45954 | H12: No | I12: 0 | J12: =IF(H12="Yes",I12*INDEX(Projects!$R$2:$R$500,MATCH(B12,Projects!$A$2:$A$500,0)),0) -> 0 | K12: =IF(ISNUMBER(G12),G12-E12,F12-E12) -> 2 | L12: =IF(ISNUMBER(G12),"Completed",IF(F12<AsOfDate,"Overdue",IF(F12-E12>MilestoneAtRiskDays,"At Risk","On Track"))) -> Completed | M12: =IF(COUNTIF(Invoices!$C$2:$C$2000,A12)>0,"Yes","No") -> No
A13: M-0012 | B13: P-1003 | C13: Design approval | D13: Design | E13: 46023 | F13: 46030 | G13: 46030 | H13: No | I13: 0 | J13: =IF(H13="Yes",I13*INDEX(Projects!$R$2:$R$500,MATCH(B13,Projects!$A$2:$A$500,0)),0) -> 0 | K13: =IF(ISNUMBER(G13),G13-E13,F13-E13) -> 7 | L13: =IF(ISNUMBER(G13),"Completed",IF(F13<AsOfDate,"Overdue",IF(F13-E13>MilestoneAtRiskDays,"At Risk","On Track"))) -> Completed | M13: =IF(COUNTIF(Invoices!$C$2:$C$2000,A13)>0,"Yes","No") -> No
A14: M-0013 | B14: P-1003 | C14: Build complete | D14: Build | E14: 46219 | F14: 46263 | H14: No | I14: 0 | J14: =IF(H14="Yes",I14*INDEX(Projects!$R$2:$R$500,MATCH(B14,Projects!$A$2:$A$500,0)),0) -> 0 | K14: =IF(ISNUMBER(G14),G14-E14,F14-E14) -> 44 | L14: =IF(ISNUMBER(G14),"Completed",IF(F14<AsOfDate,"Overdue",IF(F14-E14>MilestoneAtRiskDays,"At Risk","On Track"))) -> Overdue | M14: =IF(COUNTIF(Invoices!$C$2:$C$2000,A14)>0,"Yes","No") -> No
A15: M-0014 | B15: P-1003 | C15: UAT sign-off | D15: Test | E15: 46308 | F15: 46343 | H15: No | I15: 0 | J15: =IF(H15="Yes",I15*INDEX(Projects!$R$2:$R$500,MATCH(B15,Projects!$A$2:$A$500,0)),0) -> 0 | K15: =IF(ISNUMBER(G15),G15-E15,F15-E15) -> 35 | L15: =IF(ISNUMBER(G15),"Completed",IF(F15<AsOfDate,"Overdue",IF(F15-E15>MilestoneAtRiskDays,"At Risk","On Track"))) -> At Risk | M15: =IF(COUNTIF(Invoices!$C$2:$C$2000,A15)>0,"Yes","No") -> No
A16: M-0015 | B16: P-1003 | C16: Go-live | D16: Deploy | E16: 46353 | F16: 46394 | H16: No | I16: 0 | J16: =IF(H16="Yes",I16*INDEX(Projects!$R$2:$R$500,MATCH(B16,Projects!$A$2:$A$500,0)),0) -> 0 | K16: =IF(ISNUMBER(G16),G16-E16,F16-E16) -> 41 | L16: =IF(ISNUMBER(G16),"Completed",IF(F16<AsOfDate,"Overdue",IF(F16-E16>MilestoneAtRiskDays,"At Risk","On Track"))) -> At Risk | M16: =IF(COUNTIF(Invoices!$C$2:$C$2000,A16)>0,"Yes","No") -> No
A17: M-0016 | B17: P-1004 | C17: Discovery sign-off | D17: Discovery | E17: 46091 | F17: 46091 | G17: 46091 | H17: Yes | I17: 0.1 | J17: =IF(H17="Yes",I17*INDEX(Projects!$R$2:$R$500,MATCH(B17,Projects!$A$2:$A$500,0)),0) -> 115500 | K17: =IF(ISNUMBER(G17),G17-E17,F17-E17) -> 0 | L17: =IF(ISNUMBER(G17),"Completed",IF(F17<AsOfDate,"Overdue",IF(F17-E17>MilestoneAtRiskDays,"At Risk","On Track"))) -> Completed | M17: =IF(COUNTIF(Invoices!$C$2:$C$2000,A17)>0,"Yes","No") -> Yes
A18: M-0017 | B18: P-1004 | C18: Design approval | D18: Design | E18: 46148 | F18: 46149 | G18: 46149 | H18: Yes | I18: 0.2 | J18: =IF(H18="Yes",I18*INDEX(Projects!$R$2:$R$500,MATCH(B18,Projects!$A$2:$A$500,0)),0) -> 231000 | K18: =IF(ISNUMBER(G18),G18-E18,F18-E18) -> 1 | L18: =IF(ISNUMBER(G18),"Completed",IF(F18<AsOfDate,"Overdue",IF(F18-E18>MilestoneAtRiskDays,"At Risk","On Track"))) -> Completed | M18: =IF(COUNTIF(Invoices!$C$2:$C$2000,A18)>0,"Yes","No") -> Yes
A19: M-0018 | B19: P-1004 | C19: Build complete | D19: Build | E19: 46307 | F19: 46310 | H19: Yes | I19: 0.3 | J19: =IF(H19="Yes",I19*INDEX(Projects!$R$2:$R$500,MATCH(B19,Projects!$A$2:$A$500,0)),0) -> 346500 | K19: =IF(ISNUMBER(G19),G19-E19,F19-E19) -> 3 | L19: =IF(ISNUMBER(G19),"Completed",IF(F19<AsOfDate,"Overdue",IF(F19-E19>MilestoneAtRiskDays,"At Risk","On Track"))) -> On Track | M19: =IF(COUNTIF(Invoices!$C$2:$C$2000,A19)>0,"Yes","No") -> No
A20: M-0019 | B20: P-1004 | C20: UAT sign-off | D20: Test | E20: 46379 | F20: 46384 | H20: Yes | I20: 0.2 | J20: =IF(H20="Yes",I20*INDEX(Projects!$R$2:$R$500,MATCH(B20,Projects!$A$2:$A$500,0)),0) -> 231000 | K20: =IF(ISNUMBER(G20),G20-E20,F20-E20) -> 5 | L20: =IF(ISNUMBER(G20),"Completed",IF(F20<AsOfDate,"Overdue",IF(F20-E20>MilestoneAtRiskDays,"At Risk","On Track"))) -> On Track | M20: =IF(COUNTIF(Invoices!$C$2:$C$2000,A20)>0,"Yes","No") -> No
A21: M-0020 | B21: P-1004 | C21: Go-live | D21: Deploy | E21: 46416 | F21: 46422 | H21: Yes | I21: 0.2 | J21: =IF(H21="Yes",I21*INDEX(Projects!$R$2:$R$500,MATCH(B21,Projects!$A$2:$A$500,0)),0) -> 231000 | K21: =IF(ISNUMBER(G21),G21-E21,F21-E21) -> 6 | L21: =IF(ISNUMBER(G21),"Completed",IF(F21<AsOfDate,"Overdue",IF(F21-E21>MilestoneAtRiskDays,"At Risk","On Track"))) -> On Track | M21: =IF(COUNTIF(Invoices!$C$2:$C$2000,A21)>0,"Yes","No") -> No
A22: M-0021 | B22: P-1005 | C22: Discovery sign-off | D22: Discovery | E22: 46119 | F22: 46122 | G22: 46122 | H22: Yes | I22: 0.1 | J22: =IF(H22="Yes",I22*INDEX(Projects!$R$2:$R$500,MATCH(B22,Projects!$A$2:$A$500,0)),0) -> 74000 | K22: =IF(ISNUMBER(G22),G22-E22,F22-E22) -> 3 | L22: =IF(ISNUMBER(G22),"Completed",IF(F22<AsOfDate,"Overdue",IF(F22-E22>MilestoneAtRiskDays,"At Risk","On Track"))) -> Completed | M22: =IF(COUNTIF(Invoices!$C$2:$C$2000,A22)>0,"Yes","No") -> Yes
A23: M-0022 | B23: P-1005 | C23: Design approval | D23: Design | E23: 46176 | F23: 46188 | G23: 46188 | H23: Yes | I23: 0.2 | J23: =IF(H23="Yes",I23*INDEX(Projects!$R$2:$R$500,MATCH(B23,Projects!$A$2:$A$500,0)),0) -> 148000 | K23: =IF(ISNUMBER(G23),G23-E23,F23-E23) -> 12 | L23: =IF(ISNUMBER(G23),"Completed",IF(F23<AsOfDate,"Overdue",IF(F23-E23>MilestoneAtRiskDays,"At Risk","On Track"))) -> Completed | M23: =IF(COUNTIF(Invoices!$C$2:$C$2000,A23)>0,"Yes","No") -> Yes
A24: M-0023 | B24: P-1005 | C24: Build complete | D24: Build | E24: 46335 | F24: 46377 | H24: Yes | I24: 0.3 | J24: =IF(H24="Yes",I24*INDEX(Projects!$R$2:$R$500,MATCH(B24,Projects!$A$2:$A$500,0)),0) -> 222000 | K24: =IF(ISNUMBER(G24),G24-E24,F24-E24) -> 42 | L24: =IF(ISNUMBER(G24),"Completed",IF(F24<AsOfDate,"Overdue",IF(F24-E24>MilestoneAtRiskDays,"At Risk","On Track"))) -> At Risk | M24: =IF(COUNTIF(Invoices!$C$2:$C$2000,A24)>0,"Yes","No") -> No
A25: M-0024 | B25: P-1005 | C25: UAT sign-off | D25: Test | E25: 46407 | F25: 46464 | H25: Yes | I25: 0.2 | J25: =IF(H25="Yes",I25*INDEX(Projects!$R$2:$R$500,MATCH(B25,Projects!$A$2:$A$500,0)),0) -> 148000 | K25: =IF(ISNUMBER(G25),G25-E25,F25-E25) -> 57 | L25: =IF(ISNUMBER(G25),"Completed",IF(F25<AsOfDate,"Overdue",IF(F25-E25>MilestoneAtRiskDays,"At Risk","On Track"))) -> At Risk | M25: =IF(COUNTIF(Invoices!$C$2:$C$2000,A25)>0,"Yes","No") -> No
A26: M-0025 | B26: P-1005 | C26: Go-live | D26: Deploy | E26: 46444 | F26: 46510 | H26: Yes | I26: 0.2 | J26: =IF(H26="Yes",I26*INDEX(Projects!$R$2:$R$500,MATCH(B26,Projects!$A$2:$A$500,0)),0) -> 148000 | K26: =IF(ISNUMBER(G26),G26-E26,F26-E26) -> 66 | L26: =IF(ISNUMBER(G26),"Completed",IF(F26<AsOfDate,"Overdue",IF(F26-E26>MilestoneAtRiskDays,"At Risk","On Track"))) -> At Risk | M26: =IF(COUNTIF(Invoices!$C$2:$C$2000,A26)>0,"Yes","No") -> No
A27: M-0026 | B27: P-1006 | C27: Discovery sign-off | D27: Discovery | E27: 45971 | F27: 45971 | G27: 45971 | H27: Yes | I27: 0.1 | J27: =IF(H27="Yes",I27*INDEX(Projects!$R$2:$R$500,MATCH(B27,Projects!$A$2:$A$500,0)),0) -> 94000 | K27: =IF(ISNUMBER(G27),G27-E27,F27-E27) -> 0 | L27: =IF(ISNUMBER(G27),"Completed",IF(F27<AsOfDate,"Overdue",IF(F27-E27>MilestoneAtRiskDays,"At Risk","On Track"))) -> Completed | M27: =IF(COUNTIF(Invoices!$C$2:$C$2000,A27)>0,"Yes","No") -> Yes
A28: M-0027 | B28: P-1006 | C28: Design approval | D28: Design | E28: 46028 | F28: 46029 | G28: 46029 | H28: Yes | I28: 0.2 | J28: =IF(H28="Yes",I28*INDEX(Projects!$R$2:$R$500,MATCH(B28,Projects!$A$2:$A$500,0)),0) -> 188000 | K28: =IF(ISNUMBER(G28),G28-E28,F28-E28) -> 1 | L28: =IF(ISNUMBER(G28),"Completed",IF(F28<AsOfDate,"Overdue",IF(F28-E28>MilestoneAtRiskDays,"At Risk","On Track"))) -> Completed | M28: =IF(COUNTIF(Invoices!$C$2:$C$2000,A28)>0,"Yes","No") -> Yes
A29: M-0028 | B29: P-1006 | C29: Build complete | D29: Build | E29: 46183 | F29: 46189 | G29: 46189 | H29: Yes | I29: 0.3 | J29: =IF(H29="Yes",I29*INDEX(Projects!$R$2:$R$500,MATCH(B29,Projects!$A$2:$A$500,0)),0) -> 282000 | K29: =IF(ISNUMBER(G29),G29-E29,F29-E29) -> 6 | L29: =IF(ISNUMBER(G29),"Completed",IF(F29<AsOfDate,"Overdue",IF(F29-E29>MilestoneAtRiskDays,"At Risk","On Track"))) -> Completed | M29: =IF(COUNTIF(Invoices!$C$2:$C$2000,A29)>0,"Yes","No") -> Yes
A30: M-0029 | B30: P-1006 | C30: UAT sign-off | D30: Test | E30: 46254 | F30: 46262 | G30: 46262 | H30: Yes | I30: 0.2 | J30: =IF(H30="Yes",I30*INDEX(Projects!$R$2:$R$500,MATCH(B30,Projects!$A$2:$A$500,0)),0) -> 188000 | K30: =IF(ISNUMBER(G30),G30-E30,F30-E30) -> 8 | L30: =IF(ISNUMBER(G30),"Completed",IF(F30<AsOfDate,"Overdue",IF(F30-E30>MilestoneAtRiskDays,"At Risk","On Track"))) -> Completed | M30: =IF(COUNTIF(Invoices!$C$2:$C$2000,A30)>0,"Yes","No") -> Yes
A31: M-0030 | B31: P-1006 | C31: Go-live | D31: Deploy | E31: 46290 | F31: 46300 | H31: Yes | I31: 0.2 | J31: =IF(H31="Yes",I31*INDEX(Projects!$R$2:$R$500,MATCH(B31,Projects!$A$2:$A$500,0)),0) -> 188000 | K31: =IF(ISNUMBER(G31),G31-E31,F31-E31) -> 10 | L31: =IF(ISNUMBER(G31),"Completed",IF(F31<AsOfDate,"Overdue",IF(F31-E31>MilestoneAtRiskDays,"At Risk","On Track"))) -> On Track | M31: =IF(COUNTIF(Invoices!$C$2:$C$2000,A31)>0,"Yes","No") -> No
A32: M-0031 | B32: P-1007 | C32: Discovery sign-off | D32: Discovery | E32: 46153 | F32: 46153 | G32: 46153 | H32: Yes | I32: 0.1 | J32: =IF(H32="Yes",I32*INDEX(Projects!$R$2:$R$500,MATCH(B32,Projects!$A$2:$A$500,0)),0) -> 97000 | K32: =IF(ISNUMBER(G32),G32-E32,F32-E32) -> 0 | L32: =IF(ISNUMBER(G32),"Completed",IF(F32<AsOfDate,"Overdue",IF(F32-E32>MilestoneAtRiskDays,"At Risk","On Track"))) -> Completed | M32: =IF(COUNTIF(Invoices!$C$2:$C$2000,A32)>0,"Yes","No") -> Yes
A33: M-0032 | B33: P-1007 | C33: Design approval | D33: Design | E33: 46210 | F33: 46210 | G33: 46210 | H33: Yes | I33: 0.2 | J33: =IF(H33="Yes",I33*INDEX(Projects!$R$2:$R$500,MATCH(B33,Projects!$A$2:$A$500,0)),0) -> 194000 | K33: =IF(ISNUMBER(G33),G33-E33,F33-E33) -> 0 | L33: =IF(ISNUMBER(G33),"Completed",IF(F33<AsOfDate,"Overdue",IF(F33-E33>MilestoneAtRiskDays,"At Risk","On Track"))) -> Completed | M33: =IF(COUNTIF(Invoices!$C$2:$C$2000,A33)>0,"Yes","No") -> Yes
A34: M-0033 | B34: P-1007 | C34: Build complete | D34: Build | E34: 46365 | F34: 46366 | H34: Yes | I34: 0.3 | J34: =IF(H34="Yes",I34*INDEX(Projects!$R$2:$R$500,MATCH(B34,Projects!$A$2:$A$500,0)),0) -> 291000 | K34: =IF(ISNUMBER(G34),G34-E34,F34-E34) -> 1 | L34: =IF(ISNUMBER(G34),"Completed",IF(F34<AsOfDate,"Overdue",IF(F34-E34>MilestoneAtRiskDays,"At Risk","On Track"))) -> On Track | M34: =IF(COUNTIF(Invoices!$C$2:$C$2000,A34)>0,"Yes","No") -> No
A35: M-0034 | B35: P-1007 | C35: UAT sign-off | D35: Test | E35: 46436 | F35: 46440 | H35: Yes | I35: 0.2 | J35: =IF(H35="Yes",I35*INDEX(Projects!$R$2:$R$500,MATCH(B35,Projects!$A$2:$A$500,0)),0) -> 194000 | K35: =IF(ISNUMBER(G35),G35-E35,F35-E35) -> 4 | L35: =IF(ISNUMBER(G35),"Completed",IF(F35<AsOfDate,"Overdue",IF(F35-E35>MilestoneAtRiskDays,"At Risk","On Track"))) -> On Track | M35: =IF(COUNTIF(Invoices!$C$2:$C$2000,A35)>0,"Yes","No") -> No
A36: M-0035 | B36: P-1007 | C36: Go-live | D36: Deploy | E36: 46472 | F36: 46475 | H36: Yes | I36: 0.2 | J36: =IF(H36="Yes",I36*INDEX(Projects!$R$2:$R$500,MATCH(B36,Projects!$A$2:$A$500,0)),0) -> 194000 | K36: =IF(ISNUMBER(G36),G36-E36,F36-E36) -> 3 | L36: =IF(ISNUMBER(G36),"Completed",IF(F36<AsOfDate,"Overdue",IF(F36-E36>MilestoneAtRiskDays,"At Risk","On Track"))) -> On Track | M36: =IF(COUNTIF(Invoices!$C$2:$C$2000,A36)>0,"Yes","No") -> No
A37: M-0036 | B37: P-1008 | C37: Discovery sign-off | D37: Discovery | E37: 46055 | F37: 46055 | G37: 46055 | H37: No | I37: 0 | J37: =IF(H37="Yes",I37*INDEX(Projects!$R$2:$R$500,MATCH(B37,Projects!$A$2:$A$500,0)),0) -> 0 | K37: =IF(ISNUMBER(G37),G37-E37,F37-E37) -> 0 | L37: =IF(ISNUMBER(G37),"Completed",IF(F37<AsOfDate,"Overdue",IF(F37-E37>MilestoneAtRiskDays,"At Risk","On Track"))) -> Completed | M37: =IF(COUNTIF(Invoices!$C$2:$C$2000,A37)>0,"Yes","No") -> No
A38: M-0037 | B38: P-1008 | C38: Design approval | D38: Design | E38: 46100 | F38: 46104 | G38: 46104 | H38: No | I38: 0 | J38: =IF(H38="Yes",I38*INDEX(Projects!$R$2:$R$500,MATCH(B38,Projects!$A$2:$A$500,0)),0) -> 0 | K38: =IF(ISNUMBER(G38),G38-E38,F38-E38) -> 4 | L38: =IF(ISNUMBER(G38),"Completed",IF(F38<AsOfDate,"Overdue",IF(F38-E38>MilestoneAtRiskDays,"At Risk","On Track"))) -> Completed | M38: =IF(COUNTIF(Invoices!$C$2:$C$2000,A38)>0,"Yes","No") -> No
